Workbook

Sheet Read me
A1: SiteGuard — neatHack 2026 financial model
A2: Hypothetical planning simulation; not company performance. USD. October 2026–September 2027.
A3: Proposed prices are user hypotheses. All demand, churn, site use, non-token costs, staffing and cash are author estimates.
A4: Blue cells are editable inputs. Black cells are formulas. All forecasts open with zero customers and no financing.
A5: Revenue uses average active customers and prorated monthly charges. Exit MRR uses ending paid customers.
A6: Model references: OpenAI GPT-5 mini $0.25 input/$2 output per million; GPT-5 $1.25/$10. Standard uncached reference rates, reviewed 12 Oct 2026.
A7: Stripe US domestic-card reference 2.9% + $0.30; geographic applicability is unconfirmed. Billing software 0.7% is unverified allowance.
A8: See SiteGuard_Financial_Report.pdf for supplier URLs, detailed assumptions, risks, scope and recommendations.
A9: MVP features are intended, not independently verified shipped. Production connectors, rollback, multi-region, teams and advanced analytics are future.
A10: Scenarios: Base, Conservative, Optimistic, Guardrailed and six independent stresses. Scenario sheets inherit visible Inputs/Pricing except stated blue overrides.
A11: Acquisition spend = new paid customers x CAC. Lower conversion lowers spending as well as revenue; fixed traffic-budget losses may be worse.
A12: Negative cash is a financing gap, not an ability to operate unfunded. Founder cash pay = zero is a subsidy, not market compensation.
... A15: This portable workbook reproduces the checked native model with standard Excel formulas; it is not a live connection to the app.

Sheet Scenario summary
A1: Hypothetical case | B1: Exit paid | C1: Exit MRR | D1: Year revenue | E1: Service cost | F1: Operating expenses | G1: Operating profit/(loss) | H1: Year GM | I1: Max cash need | J1: Exit cash from $15k
A2: Base | B2: =Base!M73 -> 216.49017 | C2: =Base!M76 -> 5195.764 | D2: =SUM(Base!B77:M77) -> 26670.625 | E2: =SUM(Base!B83:M83) -> 23889.684 | F2: =SUM(Base!B91:M91) -> 37564.456 | G2: =SUM(Base!B92:M92) -> -34783.516 | H2: =IFERROR((D2-E2)/D2,0) -> 0.10426979 | I2: =MAX(0,-MIN(Base!B93:M93)) -> 34783.516 | J2: =Base!M96 -> -19783.516
A3: Conservative | B3: =Conservative!M73 -> 36.726934 | C3: =Conservative!M76 -> 591.30364 | D3: =SUM(Conservative!B77:M77) -> 3563.4621 | E3: =SUM(Conservative!B83:M83) -> 5641.8527 | F3: =SUM(Conservative!B91:M91) -> 30356.088 | G3: =SUM(Conservative!B92:M92) -> -32434.479 | H3: =IFERROR((D3-E3)/D3,0) -> -0.58325038 | I3: =MAX(0,-MIN(Conservative!B93:M93)) -> 32434.479 | J3: =Conservative!M96 -> -17434.479
A4: Optimistic | B4: =Optimistic!M73 -> 948.80608 | C4: =Optimistic!M76 -> 28938.585 | D4: =SUM(Optimistic!B77:M77) -> 130679.11 | E4: =SUM(Optimistic!B83:M83) -> 98525.66 | F4: =SUM(Optimistic!B91:M91) -> 58621.801 | G4: =SUM(Optimistic!B92:M92) -> -26468.351 | H4: =IFERROR((D4-E4)/D4,0) -> 0.24604889 | I4: =MAX(0,-MIN(Optimistic!B93:M93)) -> 26468.351 | J4: =Optimistic!M96 -> -11468.351
A5: Guardrailed | B5: =Guardrailed!M73 -> 216.49017 | C5: =Guardrailed!M76 -> 5195.764 | D5: =SUM(Guardrailed!B77:M77) -> 26670.625 | E5: =SUM(Guardrailed!B83:M83) -> 9681.2589 | F5: =SUM(Guardrailed!B91:M91) -> 25564.456 | G5: =SUM(Guardrailed!B92:M92) -> -8575.0904 | H5: =IFERROR((D5-E5)/D5,0) -> 0.63700667 | I5: =MAX(0,-MIN(Guardrailed!B93:M93)) -> 8762.9553 | J5: =Guardrailed!M96 -> 6424.9096
A6: AI 2x | B6: ='AI 2x'!M73 -> 216.49017 | C6: ='AI 2x'!M76 -> 5195.764 | D6: =SUM('AI 2x'!B77:M77) -> 26670.625 | E6: =SUM('AI 2x'!B83:M83) -> 23901.916 | F6: =SUM('AI 2x'!B91:M91) -> 37564.456 | G6: =SUM('AI 2x'!B92:M92) -> -34795.748 | H6: =IFERROR((D6-E6)/D6,0) -> 0.10381115 | I6: =MAX(0,-MIN('AI 2x'!B93:M93)) -> 34795.748 | J6: ='AI 2x'!M96 -> -19795.748
A7: CAC +50pct | B7: ='CAC +50pct'!M73 -> 216.49017 | C7: ='CAC +50pct'!M76 -> 5195.764 | D7: =SUM('CAC +50pct'!B77:M77) -> 26670.625 | E7: =SUM('CAC +50pct'!B83:M83) -> 23889.684 | F7: =SUM('CAC +50pct'!B91:M91) -> 42696.684 | G7: =SUM('CAC +50pct'!B92:M92) -> -39915.744 | H7: =IFERROR((D7-E7)/D7,0) -> 0.10426979 | I7: =MAX(0,-MIN('CAC +50pct'!B93:M93)) -> 39915.744 | J7: ='CAC +50pct'!M96 -> -24915.744
A8: Conversion -25pct | B8: ='Conversion -25pct'!M73 -> 162.36763 | C8: ='Conversion -25pct'!M76 -> 3896.823 | D8: =SUM('Conversion -25pct'!B77:M77) -> 20002.969 | E8: =SUM('Conversion -25pct'!B83:M83) -> 19777.819 | F8: =SUM('Conversion -25pct'!B91:M91) -> 34998.342 | G8: =SUM('Conversion -25pct'!B92:M92) -> -34773.193 | H8: =IFERROR((D8-E8)/D8,0) -> 0.011255804 | I8: =MAX(0,-MIN('Conversion -25pct'!B93:M93)) -> 34773.193 | J8: ='Conversion -25pct'!M96 -> -19773.193
A9: Monitoring 5x | B9: ='Monitoring 5x'!M73 -> 216.49017 | C9: ='Monitoring 5x'!M76 -> 5195.764 | D9: =SUM('Monitoring 5x'!B77:M77) -> 26670.625 | E9: =SUM('Monitoring 5x'!B83:M83) -> 94369.894 | F9: =SUM('Monitoring 5x'!B91:M91) -> 37564.456 | G9: =SUM('Monitoring 5x'!B92:M92) -> -105263.73 | H9: =IFERROR((D9-E9)/D9,0) -> -2.5383458 | I9: =MAX(0,-MIN('Monitoring 5x'!B93:M93)) -> 105263.73 | J9: ='Monitoring 5x'!M96 -> -90263.726
A10: Incidents 3x | B10: ='Incidents 3x'!M73 -> 216.49017 | C10: ='Incidents 3x'!M76 -> 5195.764 | D10: =SUM('Incidents 3x'!B77:M77) -> 26670.625 | E10: =SUM('Incidents 3x'!B83:M83) -> 23993.104 | F10: =SUM('Incidents 3x'!B91:M91) -> 37564.456 | G10: =SUM('Incidents 3x'!B92:M92) -> -34886.935 | H10: =IFERROR((D10-E10)/D10,0) -> 0.10039213 | I10: =MAX(0,-MIN('Incidents 3x'!B93:M93)) -> 34886.935 | J10: ='Incidents 3x'!M96 -> -19886.935
A11: Churn +2pp | B11: ='Churn +2pp'!M73 -> 199.6881 | C11: ='Churn +2pp'!M76 -> 4792.5145 | D11: =SUM('Churn +2pp'!B77:M77) -> 25165.577 | E11: =SUM('Churn +2pp'!B83:M83) -> 23049.72 | F11: =SUM('Churn +2pp'!B91:M91) -> 37564.456 | G11: =SUM('Churn +2pp'!B92:M92) -> -35448.599 | H11: =IFERROR((D11-E11)/D11,0) -> 0.084077428 | I11: =MAX(0,-MIN('Churn +2pp'!B93:M93)) -> 35448.599 | J11: ='Churn +2pp'!M96 -> -20448.599

Sheet Inputs
A1: Editable assumption | B1: Base input | C1: Basis
A2: Initial monthly signups | B2: 150 | C2: Hypothetical planning assumption
A3: Monthly signup growth | B3: 0.1 | C3: Hypothetical planning assumption
A4: Paid conversion rate | B4: 0.08 | C4: Hypothetical planning assumption
A5: Monthly paid churn | B5: 0.04 | C5: Hypothetical planning assumption
A6: Monthly free churn | B6: 0.15 | C6: Hypothetical planning assumption
A7: Blended acquisition CAC | B7: 40 | C7: Hypothetical planning assumption
A8: Incidents per website month | B8: 0.4 | C8: Hypothetical planning assumption
A9: AI analysis share | B9: 0.6 | C9: Hypothetical planning assumption
A10: AI input tokens per attempt | B10: 6000 | C10: Hypothetical planning assumption
A11: AI billed output tokens per attempt | B11: 1000 | C11: Hypothetical planning assumption
A12: AI attempt multiplier | B12: 1.2 | C12: Hypothetical planning assumption
A13: Tool execution cost per attempt | B13: 0.01 | C13: Hypothetical planning assumption
... A52: Incident volume multiplier | B52: 1 | C52: Hypothetical planning assumption
A53: Forecast start date | B53: 2026-10-01 | C53: Hypothetical planning assumption
A54: Starting cash 5k | B54: 5000 | C54: Hypothetical alternative starting cash
A55: Starting cash 15k | B55: 15000 | C55: Hypothetical alternative starting cash
A56: Starting cash 30k | B56: 30000 | C56: Hypothetical alternative starting cash

Sheet Pricing
A1: Plan | B1: Monthly price | C1: Paid acquisition mix | D1: Sites/account | E1: Interval minutes | F1: AI eligibility
A2: Free | B2: 0 | C2: 0 | D2: 1 | E2: 15 | F2: 0
A3: Starter | B3: 9 | C3: 0.6 | D3: 3 | E3: 5 | F3: 1
A4: Pro | B4: 29 | C4: 0.3 | D4: 10 | E4: 5 | F4: 1
A5: Business | B5: 99 | C5: 0.1 | D5: 30 | E5: 5 | F5: 1

Sheet Base
A1: Base — hypothetical 12-month forecast
A4: Initial monthly signups | B4: =Inputs!$B$2 -> 150
A5: Monthly signup growth | B5: =Inputs!$B$3 -> 0.1
A6: Paid conversion rate | B6: =Inputs!$B$4 -> 0.08
A7: Monthly paid churn | B7: =Inputs!$B$5 -> 0.04
A8: Monthly free churn | B8: =Inputs!$B$6 -> 0.15
A9: Blended acquisition CAC | B9: =Inputs!$B$7 -> 40
A10: Staff monthly budget | B10: =Inputs!$B$45 -> 3000
A11: AI cost stress multiplier | B11: =Inputs!$B$50 -> 1
A12: Monitoring frequency multiplier | B12: =Inputs!$B$51 -> 1
A13: Incident volume multiplier | B13: =Inputs!$B$52 -> 1
A17: Free | B17: =Pricing!B2 -> 0 | C17: =Pricing!C2 -> 0 | D17: =Pricing!D2 -> 1 | E17: =Pricing!E2 -> 15 | F17: =Pricing!F2 -> 0
A18: Starter | B18: =Pricing!B3 -> 9 | C18: =Pricing!C3 -> 0.6 | D18: =Pricing!D3 -> 3 | E18: =Pricing!E3 -> 5 | F18: =Pricing!F3 -> 1
A19: Pro | B19: =Pricing!B4 -> 29 | C19: =Pricing!C4 -> 0.3 | D19: =Pricing!D4 -> 10 | E19: =Pricing!E4 -> 5 | F19: =Pricing!F4 -> 1
A20: Business | B20: =Pricing!B5 -> 99 | C20: =Pricing!C5 -> 0.1 | D20: =Pricing!D5 -> 30 | E20: =Pricing!E5 -> 5 | F20: =Pricing!F5 -> 1
B25: 46296 | C25: 46327 | D25: 46357 | E25: 46388 | F25: 46419 | G25: 46447 | H25: 46478 | I25: 46508 | J25: 46539 | K25: 46569 | L25: 46600 | M25: 46631
A26: New signups | B26: =$B$4 -> 150 | C26: =B26*(1+$B$5) -> 165 | D26: =C26*(1+$B$5) -> 181.5 | E26: =D26*(1+$B$5) -> 199.65 | F26: =E26*(1+$B$5) -> 219.615 | G26: =F26*(1+$B$5) -> 241.5765 | H26: =G26*(1+$B$5) -> 265.73415 | I26: =H26*(1+$B$5) -> 292.30757 | J26: =I26*(1+$B$5) -> 321.53832 | ... M26: =L26*(1+$B$5) -> 427.96751
A27: New paid | B27: =B26*$B$6 -> 12 | C27: =C26*$B$6 -> 13.2 | D27: =D26*$B$6 -> 14.52 | E27: =E26*$B$6 -> 15.972 | F27: =F26*$B$6 -> 17.5692 | G27: =G26*$B$6 -> 19.32612 | H27: =H26*$B$6 -> 21.258732 | I27: =I26*$B$6 -> 23.384605 | ... M27: =M26*$B$6 -> 34.2374
A28: New free | B28: =B26-B27 -> 138 | C28: =C26-C27 -> 151.8 | D28: =D26-D27 -> 166.98 | E28: =E26-E27 -> 183.678 | F28: =F26-F27 -> 202.0458 | G28: =G26-G27 -> 222.25038 | H28: =H26-H27 -> 244.47542 | I28: =I26-I27 -> 268.92296 | ... M28: =M26-M27 -> 393.73011
A31: Free | Opening accounts | B31: =0 -> 0 | C31: =B34 -> 138 | D31: =C34 -> 269.1 | E31: =D34 -> 395.715 | F31: =E34 -> 520.03575 | G31: =F34 -> 644.07619 | H31: =G34 -> 769.71514 | I31: =H34 -> 898.73329 | J31: =I34 -> 1032.8463 | ... M31: =L34 -> 1482.547
A32: Free | New accounts | B32: =B28 -> 138 | C32: =C28 -> 151.8 | D32: =D28 -> 166.98 | E32: =E28 -> 183.678 | F32: =F28 -> 202.0458 | G32: =G28 -> 222.25038 | H32: =H28 -> 244.47542 | I32: =I28 -> 268.92296 | ... M32: =M28 -> 393.73011
A33: Free | Churned accounts | B33: =B31*$B$8 -> 0 | C33: =C31*$B$8 -> 20.7 | D33: =D31*$B$8 -> 40.365 | E33: =E31*$B$8 -> 59.35725 | F33: =F31*$B$8 -> 78.005363 | G33: =G31*$B$8 -> 96.611428 | H33: =H31*$B$8 -> 115.45727 | I33: =I31*$B$8 -> 134.80999 | ... M33: =M31*$B$8 -> 222.38204
A34: Free | Ending accounts | B34: =B31+B32-B33 -> 138 | C34: =C31+C32-C33 -> 269.1 | D34: =D31+D32-D33 -> 395.715 | E34: =E31+E32-E33 -> 520.03575 | F34: =F31+F32-F33 -> 644.07619 | G34: =G31+G32-G33 -> 769.71514 | H34: =H31+H32-H33 -> 898.73329 | I34: =I31+I32-I33 -> 1032.8463 | ... M34: =M31+M32-M33 -> 1653.895
A35: Free | Average accounts | B35: =(B31+B34)/2 -> 69 | C35: =(C31+C34)/2 -> 203.55 | D35: =(D31+D34)/2 -> 332.4075 | E35: =(E31+E34)/2 -> 457.87538 | F35: =(F31+F34)/2 -> 582.05597 | G35: =(G31+G34)/2 -> 706.89566 | H35: =(H31+H34)/2 -> 834.22421 | I35: =(I31+I34)/2 -> 965.78977 | ... M35: =(M31+M34)/2 -> 1568.221
A36: Free | Revenue | B36: =B35*$B$17 -> 0 | C36: =C35*$B$17 -> 0 | D36: =D35*$B$17 -> 0 | E36: =E35*$B$17 -> 0 | F36: =F35*$B$17 -> 0 | G36: =G35*$B$17 -> 0 | H36: =H35*$B$17 -> 0 | I36: =I35*$B$17 -> 0 | ... M36: =M35*$B$17 -> 0
A37: Free | Monitoring checks | B37: =(B35*$D$17)*DAY(EOMONTH(B$25,0))*1440/$E$17*$B$12 -> 205344 | C37: =(C35*$D$17)*DAY(EOMONTH(C$25,0))*1440/$E$17*$B$12 -> 586224 | D37: =(D35*$D$17)*DAY(EOMONTH(D$25,0))*1440/$E$17*$B$12 -> 989244.72 | E37: =(E35*$D$17)*DAY(EOMONTH(E$25,0))*1440/$E$17*$B$12 -> 1362637.1 | F37: =(F35*$D$17)*DAY(EOMONTH(F$25,0))*1440/$E$17*$B$12 -> 1564566.4 | G37: =(G35*$D$17)*DAY(EOMONTH(G$25,0))*1440/$E$17*$B$12 -> 2103721.5 | H37: =(H35*$D$17)*DAY(EOMONTH(H$25,0))*1440/$E$17*$B$12 -> 2402565.7 | I37: =(I35*$D$17)*DAY(EOMONTH(I$25,0))*1440/$E$17*$B$12 -> 2874190.4 | ... M37: =(M35*$D$17)*DAY(EOMONTH(M$25,0))*1440/$E$17*$B$12 -> 4516476.4
A38: Free | AI diagnoses | B38: =(B35*$D$17)*Inputs!$B$8*$B$13*Inputs!$B$9*$F$17 -> 0 | C38: =(C35*$D$17)*Inputs!$B$8*$B$13*Inputs!$B$9*$F$17 -> 0 | D38: =(D35*$D$17)*Inputs!$B$8*$B$13*Inputs!$B$9*$F$17 -> 0 | E38: =(E35*$D$17)*Inputs!$B$8*$B$13*Inputs!$B$9*$F$17 -> 0 | F38: =(F35*$D$17)*Inputs!$B$8*$B$13*Inputs!$B$9*$F$17 -> 0 | G38: =(G35*$D$17)*Inputs!$B$8*$B$13*Inputs!$B$9*$F$17 -> 0 | H38: =(H35*$D$17)*Inputs!$B$8*$B$13*Inputs!$B$9*$F$17 -> 0 | I38: =(I35*$D$17)*Inputs!$B$8*$B$13*Inputs!$B$9*$F$17 -> 0 | ... M38: =(M35*$D$17)*Inputs!$B$8*$B$13*Inputs!$B$9*$F$17 -> 0
A39: Free | Variable service expense | B39: =B37/1000*(Inputs!$B$19+Inputs!$B$20+Inputs!$B$21+Inputs!$B$22+Inputs!$B$23+Inputs!$B$24)+B38*((((Inputs!$B$10*Inputs!$B$15+Inputs!$B$11*Inputs!$B$16)*(1-Inputs!$B$14)+(Inputs!$B$10*Inputs!$B$17+Inputs!$B$11*Inputs!$B$18)*Inputs!$B$14)/1000000*Inputs!$B$12)*$B$11+Inputs!$B$12*Inputs!$B$13)+(B35*$D$17)*Inputs!$B$25*Inputs!$B$26+((B35*$D$17)*Inputs!$B$8*$B$13)*Inputs!$B$27*Inputs!$B$28+B36*(Inputs!$B$29+Inputs!$B$31) -> 35.10168 | C39: =C37/1000*(Inputs!$B$19+Inputs!$B$20+Inputs!$B$21+Inputs!$B$22+Inputs!$B$23+Inputs!$B$24)+C38*((((Inputs!$B$10*Inputs!$B$15+Inputs!$B$11*Inputs!$B$16)*(1-Inputs!$B$14)+(Inputs!$B$10*Inputs!$B$17+Inputs!$B$11*Inputs!$B$18)*Inputs!$B$14)/1000000*Inputs!$B$12)*$B$11+Inputs!$B$12*Inputs!$B$13)+(C35*$D$17)*Inputs!$B$25*Inputs!$B$26+((C35*$D$17)*Inputs!$B$8*$B$13)*Inputs!$B$27*Inputs!$B$28+C36*(Inputs!$B$29+Inputs!$B$31) -> 100.22802 | D39: =D37/1000*(Inputs!$B$19+Inputs!$B$20+Inputs!$B$21+Inputs!$B$22+Inputs!$B$23+Inputs!$B$24)+D38*((((Inputs!$B$10*Inputs!$B$15+Inputs!$B$11*Inputs!$B$16)*(1-Inputs!$B$14)+(Inputs!$B$10*Inputs!$B$17+Inputs!$B$11*Inputs!$B$18)*Inputs!$B$14)/1000000*Inputs!$B$12)*$B$11+Inputs!$B$12*Inputs!$B$13)+(D35*$D$17)*Inputs!$B$25*Inputs!$B$26+((D35*$D$17)*Inputs!$B$8*$B$13)*Inputs!$B$27*Inputs!$B$28+D36*(Inputs!$B$29+Inputs!$B$31) -> 169.10234 | E39: =E37/1000*(Inputs!$B$19+Inputs!$B$20+Inputs!$B$21+Inputs!$B$22+Inputs!$B$23+Inputs!$B$24)+E38*((((Inputs!$B$10*Inputs!$B$15+Inputs!$B$11*Inputs!$B$16)*(1-Inputs!$B$14)+(Inputs!$B$10*Inputs!$B$17+Inputs!$B$11*Inputs!$B$18)*Inputs!$B$14)/1000000*Inputs!$B$12)*$B$11+Inputs!$B$12*Inputs!$B$13)+(E35*$D$17)*Inputs!$B$25*Inputs!$B$26+((E35*$D$17)*Inputs!$B$8*$B$13)*Inputs!$B$27*Inputs!$B$28+E36*(Inputs!$B$29+Inputs!$B$31) -> 232.93036 | F39: =F37/1000*(Inputs!$B$19+Inputs!$B$20+Inputs!$B$21+Inputs!$B$22+Inputs!$B$23+Inputs!$B$24)+F38*((((Inputs!$B$10*Inputs!$B$15+Inputs!$B$11*Inputs!$B$16)*(1-Inputs!$B$14)+(Inputs!$B$10*Inputs!$B$17+Inputs!$B$11*Inputs!$B$18)*Inputs!$B$14)/1000000*Inputs!$B$12)*$B$11+Inputs!$B$12*Inputs!$B$13)+(F35*$D$17)*Inputs!$B$25*Inputs!$B$26+((F35*$D$17)*Inputs!$B$8*$B$13)*Inputs!$B$27*Inputs!$B$28+F36*(Inputs!$B$29+Inputs!$B$31) -> 267.60605 | G39: =G37/1000*(Inputs!$B$19+Inputs!$B$20+Inputs!$B$21+Inputs!$B$22+Inputs!$B$23+Inputs!$B$24)+G38*((((Inputs!$B$10*Inputs!$B$15+Inputs!$B$11*Inputs!$B$16)*(1-Inputs!$B$14)+(Inputs!$B$10*Inputs!$B$17+Inputs!$B$11*Inputs!$B$18)*Inputs!$B$14)/1000000*Inputs!$B$12)*$B$11+Inputs!$B$12*Inputs!$B$13)+(G35*$D$17)*Inputs!$B$25*Inputs!$B$26+((G35*$D$17)*Inputs!$B$8*$B$13)*Inputs!$B$27*Inputs!$B$28+G36*(Inputs!$B$29+Inputs!$B$31) -> 359.61196 | H39: =H37/1000*(Inputs!$B$19+Inputs!$B$20+Inputs!$B$21+Inputs!$B$22+Inputs!$B$23+Inputs!$B$24)+H38*((((Inputs!$B$10*Inputs!$B$15+Inputs!$B$11*Inputs!$B$16)*(1-Inputs!$B$14)+(Inputs!$B$10*Inputs!$B$17+Inputs!$B$11*Inputs!$B$18)*Inputs!$B$14)/1000000*Inputs!$B$12)*$B$11+Inputs!$B$12*Inputs!$B$13)+(H35*$D$17)*Inputs!$B$25*Inputs!$B$26+((H35*$D$17)*Inputs!$B$8*$B$13)*Inputs!$B$27*Inputs!$B$28+H36*(Inputs!$B$29+Inputs!$B$31) -> 410.772 | I39: =I37/1000*(Inputs!$B$19+Inputs!$B$20+Inputs!$B$21+Inputs!$B$22+Inputs!$B$23+Inputs!$B$24)+I38*((((Inputs!$B$10*Inputs!$B$15+Inputs!$B$11*Inputs!$B$16)*(1-Inputs!$B$14)+(Inputs!$B$10*Inputs!$B$17+Inputs!$B$11*Inputs!$B$18)*Inputs!$B$14)/1000000*Inputs!$B$12)*$B$11+Inputs!$B$12*Inputs!$B$13)+(I35*$D$17)*Inputs!$B$25*Inputs!$B$26+((I35*$D$17)*Inputs!$B$8*$B$13)*Inputs!$B$27*Inputs!$B$28+I36*(Inputs!$B$29+Inputs!$B$31) -> 491.31657 | ... M39: =M37/1000*(Inputs!$B$19+Inputs!$B$20+Inputs!$B$21+Inputs!$B$22+Inputs!$B$23+Inputs!$B$24)+M38*((((Inputs!$B$10*Inputs!$B$15+Inputs!$B$11*Inputs!$B$16)*(1-Inputs!$B$14)+(Inputs!$B$10*Inputs!$B$17+Inputs!$B$11*Inputs!$B$18)*Inputs!$B$14)/1000000*Inputs!$B$12)*$B$11+Inputs!$B$12*Inputs!$B$13)+(M35*$D$17)*Inputs!$B$25*Inputs!$B$26+((M35*$D$17)*Inputs!$B$8*$B$13)*Inputs!$B$27*Inputs!$B$28+M36*(Inputs!$B$29+Inputs!$B$31) -> 772.19201
A41: Starter | Opening accounts | B41: =0 -> 0 | C41: =B44 -> 7.2 | D41: =C44 -> 14.832 | E41: =D44 -> 22.95072 | F41: =E44 -> 31.615891 | G41: =F44 -> 40.892776 | H41: =G44 -> 50.852737 | I41: =H44 -> 61.573866 | J41: =I44 -> 73.141675 | ... M41: =L44 -> 113.90798
A42: Starter | New accounts | B42: =B27*$C$18 -> 7.2 | C42: =C27*$C$18 -> 7.92 | D42: =D27*$C$18 -> 8.712 | E42: =E27*$C$18 -> 9.5832 | F42: =F27*$C$18 -> 10.54152 | G42: =G27*$C$18 -> 11.595672 | H42: =H27*$C$18 -> 12.755239 | I42: =I27*$C$18 -> 14.030763 | ... M42: =M27*$C$18 -> 20.54244
A43: Starter | Churned accounts | B43: =B41*$B$7 -> 0 | C43: =C41*$B$7 -> 0.288 | D43: =D41*$B$7 -> 0.59328 | E43: =E41*$B$7 -> 0.9180288 | F43: =F41*$B$7 -> 1.2646356 | G43: =G41*$B$7 -> 1.635711 | H43: =H41*$B$7 -> 2.0341095 | I43: =I41*$B$7 -> 2.4629547 | ... M43: =M41*$B$7 -> 4.5563192
A44: Starter | Ending accounts | B44: =B41+B42-B43 -> 7.2 | C44: =C41+C42-C43 -> 14.832 | D44: =D41+D42-D43 -> 22.95072 | E44: =E41+E42-E43 -> 31.615891 | F44: =F41+F42-F43 -> 40.892776 | G44: =G41+G42-G43 -> 50.852737 | H44: =H41+H42-H43 -> 61.573866 | I44: =I41+I42-I43 -> 73.141675 | ... M44: =M41+M42-M43 -> 129.8941
A45: Starter | Average accounts | B45: =(B41+B44)/2 -> 3.6 | C45: =(C41+C44)/2 -> 11.016 | D45: =(D41+D44)/2 -> 18.89136 | E45: =(E41+E44)/2 -> 27.283306 | F45: =(F41+F44)/2 -> 36.254333 | G45: =(G41+G44)/2 -> 45.872756 | H45: =(H41+H44)/2 -> 56.213301 | I45: =(I41+I44)/2 -> 67.357771 | ... M45: =(M41+M44)/2 -> 121.90104
A46: Starter | Revenue | B46: =B45*$B$18 -> 32.4 | C46: =C45*$B$18 -> 99.144 | D46: =D45*$B$18 -> 170.02224 | E46: =E45*$B$18 -> 245.54975 | F46: =F45*$B$18 -> 326.289 | G46: =G45*$B$18 -> 412.8548 | H46: =H45*$B$18 -> 505.91971 | I46: =I45*$B$18 -> 606.21993 | ... M46: =M45*$B$18 -> 1097.1094
A47: Starter | Monitoring checks | B47: =(B45*$D$18)*DAY(EOMONTH(B$25,0))*1440/$E$18*$B$12 -> 96422.4 | C47: =(C45*$D$18)*DAY(EOMONTH(C$25,0))*1440/$E$18*$B$12 -> 285534.72 | D47: =(D45*$D$18)*DAY(EOMONTH(D$25,0))*1440/$E$18*$B$12 -> 505986.19 | E47: =(E45*$D$18)*DAY(EOMONTH(E$25,0))*1440/$E$18*$B$12 -> 730756.06 | F47: =(F45*$D$18)*DAY(EOMONTH(F$25,0))*1440/$E$18*$B$12 -> 877064.83 | G47: =(G45*$D$18)*DAY(EOMONTH(G$25,0))*1440/$E$18*$B$12 -> 1228655.9 | H47: =(H45*$D$18)*DAY(EOMONTH(H$25,0))*1440/$E$18*$B$12 -> 1457048.8 | I47: =(I45*$D$18)*DAY(EOMONTH(I$25,0))*1440/$E$18*$B$12 -> 1804110.5 | ... M47: =(M45*$D$18)*DAY(EOMONTH(M$25,0))*1440/$E$18*$B$12 -> 3159675
A48: Starter | AI diagnoses | B48: =(B45*$D$18)*Inputs!$B$8*$B$13*Inputs!$B$9*$F$18 -> 2.592 | C48: =(C45*$D$18)*Inputs!$B$8*$B$13*Inputs!$B$9*$F$18 -> 7.93152 | D48: =(D45*$D$18)*Inputs!$B$8*$B$13*Inputs!$B$9*$F$18 -> 13.601779 | E48: =(E45*$D$18)*Inputs!$B$8*$B$13*Inputs!$B$9*$F$18 -> 19.64398 | F48: =(F45*$D$18)*Inputs!$B$8*$B$13*Inputs!$B$9*$F$18 -> 26.10312 | G48: =(G45*$D$18)*Inputs!$B$8*$B$13*Inputs!$B$9*$F$18 -> 33.028384 | H48: =(H45*$D$18)*Inputs!$B$8*$B$13*Inputs!$B$9*$F$18 -> 40.473577 | I48: =(I45*$D$18)*Inputs!$B$8*$B$13*Inputs!$B$9*$F$18 -> 48.497595 | ... M48: =(M45*$D$18)*Inputs!$B$8*$B$13*Inputs!$B$9*$F$18 -> 87.768749
A49: Starter | Variable service expense | B49: =B47/1000*(Inputs!$B$19+Inputs!$B$20+Inputs!$B$21+Inputs!$B$22+Inputs!$B$23+Inputs!$B$24)+B48*((((Inputs!$B$10*Inputs!$B$15+Inputs!$B$11*Inputs!$B$16)*(1-Inputs!$B$14)+(Inputs!$B$10*Inputs!$B$17+Inputs!$B$11*Inputs!$B$18)*Inputs!$B$14)/1000000*Inputs!$B$12)*$B$11+Inputs!$B$12*Inputs!$B$13)+(B45*$D$18)*Inputs!$B$25*Inputs!$B$26+((B45*$D$18)*Inputs!$B$8*$B$13)*Inputs!$B$27*Inputs!$B$28+B46*(Inputs!$B$29+Inputs!$B$31)+B44*Inputs!$B$30+B45*Inputs!$B$32 -> 21.594793 | C49: =C47/1000*(Inputs!$B$19+Inputs!$B$20+Inputs!$B$21+Inputs!$B$22+Inputs!$B$23+Inputs!$B$24)+C48*((((Inputs!$B$10*Inputs!$B$15+Inputs!$B$11*Inputs!$B$16)*(1-Inputs!$B$14)+(Inputs!$B$10*Inputs!$B$17+Inputs!$B$11*Inputs!$B$18)*Inputs!$B$14)/1000000*Inputs!$B$12)*$B$11+Inputs!$B$12*Inputs!$B$13)+(C45*$D$18)*Inputs!$B$25*Inputs!$B$26+((C45*$D$18)*Inputs!$B$8*$B$13)*Inputs!$B$27*Inputs!$B$28+C46*(Inputs!$B$29+Inputs!$B$31)+C44*Inputs!$B$30+C45*Inputs!$B$32 -> 62.302036 | D49: =D47/1000*(Inputs!$B$19+Inputs!$B$20+Inputs!$B$21+Inputs!$B$22+Inputs!$B$23+Inputs!$B$24)+D48*((((Inputs!$B$10*Inputs!$B$15+Inputs!$B$11*Inputs!$B$16)*(1-Inputs!$B$14)+(Inputs!$B$10*Inputs!$B$17+Inputs!$B$11*Inputs!$B$18)*Inputs!$B$14)/1000000*Inputs!$B$12)*$B$11+Inputs!$B$12*Inputs!$B$13)+(D45*$D$18)*Inputs!$B$25*Inputs!$B$26+((D45*$D$18)*Inputs!$B$8*$B$13)*Inputs!$B$27*Inputs!$B$28+D46*(Inputs!$B$29+Inputs!$B$31)+D44*Inputs!$B$30+D45*Inputs!$B$32 -> 108.87124 | E49: =E47/1000*(Inputs!$B$19+Inputs!$B$20+Inputs!$B$21+Inputs!$B$22+Inputs!$B$23+Inputs!$B$24)+E48*((((Inputs!$B$10*Inputs!$B$15+Inputs!$B$11*Inputs!$B$16)*(1-Inputs!$B$14)+(Inputs!$B$10*Inputs!$B$17+Inputs!$B$11*Inputs!$B$18)*Inputs!$B$14)/1000000*Inputs!$B$12)*$B$11+Inputs!$B$12*Inputs!$B$13)+(E45*$D$18)*Inputs!$B$25*Inputs!$B$26+((E45*$D$18)*Inputs!$B$8*$B$13)*Inputs!$B$27*Inputs!$B$28+E46*(Inputs!$B$29+Inputs!$B$31)+E44*Inputs!$B$30+E45*Inputs!$B$32 -> 156.77516 | F49: =F47/1000*(Inputs!$B$19+Inputs!$B$20+Inputs!$B$21+Inputs!$B$22+Inputs!$B$23+Inputs!$B$24)+F48*((((Inputs!$B$10*Inputs!$B$15+Inputs!$B$11*Inputs!$B$16)*(1-Inputs!$B$14)+(Inputs!$B$10*Inputs!$B$17+Inputs!$B$11*Inputs!$B$18)*Inputs!$B$14)/1000000*Inputs!$B$12)*$B$11+Inputs!$B$12*Inputs!$B$13)+(F45*$D$18)*Inputs!$B$25*Inputs!$B$26+((F45*$D$18)*Inputs!$B$8*$B$13)*Inputs!$B$27*Inputs!$B$28+F46*(Inputs!$B$29+Inputs!$B$31)+F44*Inputs!$B$30+F45*Inputs!$B$32 -> 192.01369 | G49: =G47/1000*(Inputs!$B$19+Inputs!$B$20+Inputs!$B$21+Inputs!$B$22+Inputs!$B$23+Inputs!$B$24)+G48*((((Inputs!$B$10*Inputs!$B$15+Inputs!$B$11*Inputs!$B$16)*(1-Inputs!$B$14)+(Inputs!$B$10*Inputs!$B$17+Inputs!$B$11*Inputs!$B$18)*Inputs!$B$14)/1000000*Inputs!$B$12)*$B$11+Inputs!$B$12*Inputs!$B$13)+(G45*$D$18)*Inputs!$B$25*Inputs!$B$26+((G45*$D$18)*Inputs!$B$8*$B$13)*Inputs!$B$27*Inputs!$B$28+G46*(Inputs!$B$29+Inputs!$B$31)+G44*Inputs!$B$30+G45*Inputs!$B$32 -> 262.90235 | H49: =H47/1000*(Inputs!$B$19+Inputs!$B$20+Inputs!$B$21+Inputs!$B$22+Inputs!$B$23+Inputs!$B$24)+H48*((((Inputs!$B$10*Inputs!$B$15+Inputs!$B$11*Inputs!$B$16)*(1-Inputs!$B$14)+(Inputs!$B$10*Inputs!$B$17+Inputs!$B$11*Inputs!$B$18)*Inputs!$B$14)/1000000*Inputs!$B$12)*$B$11+Inputs!$B$12*Inputs!$B$13)+(H45*$D$18)*Inputs!$B$25*Inputs!$B$26+((H45*$D$18)*Inputs!$B$8*$B$13)*Inputs!$B$27*Inputs!$B$28+H46*(Inputs!$B$29+Inputs!$B$31)+H44*Inputs!$B$30+H45*Inputs!$B$32 -> 313.68607 | I49: =I47/1000*(Inputs!$B$19+Inputs!$B$20+Inputs!$B$21+Inputs!$B$22+Inputs!$B$23+Inputs!$B$24)+I48*((((Inputs!$B$10*Inputs!$B$15+Inputs!$B$11*Inputs!$B$16)*(1-Inputs!$B$14)+(Inputs!$B$10*Inputs!$B$17+Inputs!$B$11*Inputs!$B$18)*Inputs!$B$14)/1000000*Inputs!$B$12)*$B$11+Inputs!$B$12*Inputs!$B$13)+(I45*$D$18)*Inputs!$B$25*Inputs!$B$26+((I45*$D$18)*Inputs!$B$8*$B$13)*Inputs!$B$27*Inputs!$B$28+I46*(Inputs!$B$29+Inputs!$B$31)+I44*Inputs!$B$30+I45*Inputs!$B$32 -> 385.57704 | ... M49: =M47/1000*(Inputs!$B$19+Inputs!$B$20+Inputs!$B$21+Inputs!$B$22+Inputs!$B$23+Inputs!$B$24)+M48*((((Inputs!$B$10*Inputs!$B$15+Inputs!$B$11*Inputs!$B$16)*(1-Inputs!$B$14)+(Inputs!$B$10*Inputs!$B$17+Inputs!$B$11*Inputs!$B$18)*Inputs!$B$14)/1000000*Inputs!$B$12)*$B$11+Inputs!$B$12*Inputs!$B$13)+(M45*$D$18)*Inputs!$B$25*Inputs!$B$26+((M45*$D$18)*Inputs!$B$8*$B$13)*Inputs!$B$27*Inputs!$B$28+M46*(Inputs!$B$29+Inputs!$B$31)+M44*Inputs!$B$30+M45*Inputs!$B$32 -> 679.1527
A51: Pro | Opening accounts | B51: =0 -> 0 | C51: =B54 -> 3.6 | D51: =C54 -> 7.416 | E51: =D54 -> 11.47536 | F51: =E54 -> 15.807946 | G51: =F54 -> 20.446388 | H51: =G54 -> 25.426368 | I51: =H54 -> 30.786933 | J51: =I54 -> 36.570837 | ... M51: =L54 -> 56.95399
A52: Pro | New accounts | B52: =B27*$C$19 -> 3.6 | C52: =C27*$C$19 -> 3.96 | D52: =D27*$C$19 -> 4.356 | E52: =E27*$C$19 -> 4.7916 | F52: =F27*$C$19 -> 5.27076 | G52: =G27*$C$19 -> 5.797836 | H52: =H27*$C$19 -> 6.3776196 | I52: =I27*$C$19 -> 7.0153816 | ... M52: =M27*$C$19 -> 10.27122
A53: Pro | Churned accounts | B53: =B51*$B$7 -> 0 | C53: =C51*$B$7 -> 0.144 | D53: =D51*$B$7 -> 0.29664 | E53: =E51*$B$7 -> 0.4590144 | F53: =F51*$B$7 -> 0.63231782 | G53: =G51*$B$7 -> 0.81785551 | H53: =H51*$B$7 -> 1.0170547 | I53: =I51*$B$7 -> 1.2314773 | ... M53: =M51*$B$7 -> 2.2781596
A54: Pro | Ending accounts | B54: =B51+B52-B53 -> 3.6 | C54: =C51+C52-C53 -> 7.416 | D54: =D51+D52-D53 -> 11.47536 | E54: =E51+E52-E53 -> 15.807946 | F54: =F51+F52-F53 -> 20.446388 | G54: =G51+G52-G53 -> 25.426368 | H54: =H51+H52-H53 -> 30.786933 | I54: =I51+I52-I53 -> 36.570837 | ... M54: =M51+M52-M53 -> 64.94705
A55: Pro | Average accounts | B55: =(B51+B54)/2 -> 1.8 | C55: =(C51+C54)/2 -> 5.508 | D55: =(D51+D54)/2 -> 9.44568 | E55: =(E51+E54)/2 -> 13.641653 | F55: =(F51+F54)/2 -> 18.127167 | G55: =(G51+G54)/2 -> 22.936378 | H55: =(H51+H54)/2 -> 28.106651 | I55: =(I51+I54)/2 -> 33.678885 | ... M55: =(M51+M54)/2 -> 60.95052
A56: Pro | Revenue | B56: =B55*$B$19 -> 52.2 | C56: =C55*$B$19 -> 159.732 | D56: =D55*$B$19 -> 273.92472 | E56: =E55*$B$19 -> 395.60793 | F56: =F55*$B$19 -> 525.68783 | G56: =G55*$B$19 -> 665.15496 | H56: =H55*$B$19 -> 815.09287 | I56: =I55*$B$19 -> 976.68767 | ... M56: =M55*$B$19 -> 1767.5651
A57: Pro | Monitoring checks | B57: =(B55*$D$19)*DAY(EOMONTH(B$25,0))*1440/$E$19*$B$12 -> 160704 | C57: =(C55*$D$19)*DAY(EOMONTH(C$25,0))*1440/$E$19*$B$12 -> 475891.2 | D57: =(D55*$D$19)*DAY(EOMONTH(D$25,0))*1440/$E$19*$B$12 -> 843310.31 | E57: =(E55*$D$19)*DAY(EOMONTH(E$25,0))*1440/$E$19*$B$12 -> 1217926.8 | F57: =(F55*$D$19)*DAY(EOMONTH(F$25,0))*1440/$E$19*$B$12 -> 1461774.7 | G57: =(G55*$D$19)*DAY(EOMONTH(G$25,0))*1440/$E$19*$B$12 -> 2047759.8 | H57: =(H55*$D$19)*DAY(EOMONTH(H$25,0))*1440/$E$19*$B$12 -> 2428414.6 | I57: =(I55*$D$19)*DAY(EOMONTH(I$25,0))*1440/$E$19*$B$12 -> 3006850.9 | ... M57: =(M55*$D$19)*DAY(EOMONTH(M$25,0))*1440/$E$19*$B$12 -> 5266124.9
A58: Pro | AI diagnoses | B58: =(B55*$D$19)*Inputs!$B$8*$B$13*Inputs!$B$9*$F$19 -> 4.32 | C58: =(C55*$D$19)*Inputs!$B$8*$B$13*Inputs!$B$9*$F$19 -> 13.2192 | D58: =(D55*$D$19)*Inputs!$B$8*$B$13*Inputs!$B$9*$F$19 -> 22.669632 | E58: =(E55*$D$19)*Inputs!$B$8*$B$13*Inputs!$B$9*$F$19 -> 32.739967 | F58: =(F55*$D$19)*Inputs!$B$8*$B$13*Inputs!$B$9*$F$19 -> 43.5052 | G58: =(G55*$D$19)*Inputs!$B$8*$B$13*Inputs!$B$9*$F$19 -> 55.047307 | H58: =(H55*$D$19)*Inputs!$B$8*$B$13*Inputs!$B$9*$F$19 -> 67.455962 | I58: =(I55*$D$19)*Inputs!$B$8*$B$13*Inputs!$B$9*$F$19 -> 80.829325 | ... M58: =(M55*$D$19)*Inputs!$B$8*$B$13*Inputs!$B$9*$F$19 -> 146.28125
A59: Pro | Variable service expense | B59: =B57/1000*(Inputs!$B$19+Inputs!$B$20+Inputs!$B$21+Inputs!$B$22+Inputs!$B$23+Inputs!$B$24)+B58*((((Inputs!$B$10*Inputs!$B$15+Inputs!$B$11*Inputs!$B$16)*(1-Inputs!$B$14)+(Inputs!$B$10*Inputs!$B$17+Inputs!$B$11*Inputs!$B$18)*Inputs!$B$14)/1000000*Inputs!$B$12)*$B$11+Inputs!$B$12*Inputs!$B$13)+(B55*$D$19)*Inputs!$B$25*Inputs!$B$26+((B55*$D$19)*Inputs!$B$8*$B$13)*Inputs!$B$27*Inputs!$B$28+B56*(Inputs!$B$29+Inputs!$B$31)+B54*Inputs!$B$30+B55*Inputs!$B$32 -> 31.306522 | C59: =C57/1000*(Inputs!$B$19+Inputs!$B$20+Inputs!$B$21+Inputs!$B$22+Inputs!$B$23+Inputs!$B$24)+C58*((((Inputs!$B$10*Inputs!$B$15+Inputs!$B$11*Inputs!$B$16)*(1-Inputs!$B$14)+(Inputs!$B$10*Inputs!$B$17+Inputs!$B$11*Inputs!$B$18)*Inputs!$B$14)/1000000*Inputs!$B$12)*$B$11+Inputs!$B$12*Inputs!$B$13)+(C55*$D$19)*Inputs!$B$25*Inputs!$B$26+((C55*$D$19)*Inputs!$B$8*$B$13)*Inputs!$B$27*Inputs!$B$28+C56*(Inputs!$B$29+Inputs!$B$31)+C54*Inputs!$B$30+C55*Inputs!$B$32 -> 92.021239 | D59: =D57/1000*(Inputs!$B$19+Inputs!$B$20+Inputs!$B$21+Inputs!$B$22+Inputs!$B$23+Inputs!$B$24)+D58*((((Inputs!$B$10*Inputs!$B$15+Inputs!$B$11*Inputs!$B$16)*(1-Inputs!$B$14)+(Inputs!$B$10*Inputs!$B$17+Inputs!$B$11*Inputs!$B$18)*Inputs!$B$14)/1000000*Inputs!$B$12)*$B$11+Inputs!$B$12*Inputs!$B$13)+(D55*$D$19)*Inputs!$B$25*Inputs!$B$26+((D55*$D$19)*Inputs!$B$8*$B$13)*Inputs!$B$27*Inputs!$B$28+D56*(Inputs!$B$29+Inputs!$B$31)+D54*Inputs!$B$30+D55*Inputs!$B$32 -> 162.0593 | E59: =E57/1000*(Inputs!$B$19+Inputs!$B$20+Inputs!$B$21+Inputs!$B$22+Inputs!$B$23+Inputs!$B$24)+E58*((((Inputs!$B$10*Inputs!$B$15+Inputs!$B$11*Inputs!$B$16)*(1-Inputs!$B$14)+(Inputs!$B$10*Inputs!$B$17+Inputs!$B$11*Inputs!$B$18)*Inputs!$B$14)/1000000*Inputs!$B$12)*$B$11+Inputs!$B$12*Inputs!$B$13)+(E55*$D$19)*Inputs!$B$25*Inputs!$B$26+((E55*$D$19)*Inputs!$B$8*$B$13)*Inputs!$B$27*Inputs!$B$28+E56*(Inputs!$B$29+Inputs!$B$31)+E54*Inputs!$B$30+E55*Inputs!$B$32 -> 233.82 | F59: =F57/1000*(Inputs!$B$19+Inputs!$B$20+Inputs!$B$21+Inputs!$B$22+Inputs!$B$23+Inputs!$B$24)+F58*((((Inputs!$B$10*Inputs!$B$15+Inputs!$B$11*Inputs!$B$16)*(1-Inputs!$B$14)+(Inputs!$B$10*Inputs!$B$17+Inputs!$B$11*Inputs!$B$18)*Inputs!$B$14)/1000000*Inputs!$B$12)*$B$11+Inputs!$B$12*Inputs!$B$13)+(F55*$D$19)*Inputs!$B$25*Inputs!$B$26+((F55*$D$19)*Inputs!$B$8*$B$13)*Inputs!$B$27*Inputs!$B$28+F56*(Inputs!$B$29+Inputs!$B$31)+F54*Inputs!$B$30+F55*Inputs!$B$32 -> 283.9094 | G59: =G57/1000*(Inputs!$B$19+Inputs!$B$20+Inputs!$B$21+Inputs!$B$22+Inputs!$B$23+Inputs!$B$24)+G58*((((Inputs!$B$10*Inputs!$B$15+Inputs!$B$11*Inputs!$B$16)*(1-Inputs!$B$14)+(Inputs!$B$10*Inputs!$B$17+Inputs!$B$11*Inputs!$B$18)*Inputs!$B$14)/1000000*Inputs!$B$12)*$B$11+Inputs!$B$12*Inputs!$B$13)+(G55*$D$19)*Inputs!$B$25*Inputs!$B$26+((G55*$D$19)*Inputs!$B$8*$B$13)*Inputs!$B$27*Inputs!$B$28+G56*(Inputs!$B$29+Inputs!$B$31)+G54*Inputs!$B$30+G55*Inputs!$B$32 -> 392.78731 | H59: =H57/1000*(Inputs!$B$19+Inputs!$B$20+Inputs!$B$21+Inputs!$B$22+Inputs!$B$23+Inputs!$B$24)+H58*((((Inputs!$B$10*Inputs!$B$15+Inputs!$B$11*Inputs!$B$16)*(1-Inputs!$B$14)+(Inputs!$B$10*Inputs!$B$17+Inputs!$B$11*Inputs!$B$18)*Inputs!$B$14)/1000000*Inputs!$B$12)*$B$11+Inputs!$B$12*Inputs!$B$13)+(H55*$D$19)*Inputs!$B$25*Inputs!$B$26+((H55*$D$19)*Inputs!$B$8*$B$13)*Inputs!$B$27*Inputs!$B$28+H56*(Inputs!$B$29+Inputs!$B$31)+H54*Inputs!$B$30+H55*Inputs!$B$32 -> 467.45633 | I59: =I57/1000*(Inputs!$B$19+Inputs!$B$20+Inputs!$B$21+Inputs!$B$22+Inputs!$B$23+Inputs!$B$24)+I58*((((Inputs!$B$10*Inputs!$B$15+Inputs!$B$11*Inputs!$B$16)*(1-Inputs!$B$14)+(Inputs!$B$10*Inputs!$B$17+Inputs!$B$11*Inputs!$B$18)*Inputs!$B$14)/1000000*Inputs!$B$12)*$B$11+Inputs!$B$12*Inputs!$B$13)+(I55*$D$19)*Inputs!$B$25*Inputs!$B$26+((I55*$D$19)*Inputs!$B$8*$B$13)*Inputs!$B$27*Inputs!$B$28+I56*(Inputs!$B$29+Inputs!$B$31)+I54*Inputs!$B$30+I55*Inputs!$B$32 -> 576.52434 | ... M59: =M57/1000*(Inputs!$B$19+Inputs!$B$20+Inputs!$B$21+Inputs!$B$22+Inputs!$B$23+Inputs!$B$24)+M58*((((Inputs!$B$10*Inputs!$B$15+Inputs!$B$11*Inputs!$B$16)*(1-Inputs!$B$14)+(Inputs!$B$10*Inputs!$B$17+Inputs!$B$11*Inputs!$B$18)*Inputs!$B$14)/1000000*Inputs!$B$12)*$B$11+Inputs!$B$12*Inputs!$B$13)+(M55*$D$19)*Inputs!$B$25*Inputs!$B$26+((M55*$D$19)*Inputs!$B$8*$B$13)*Inputs!$B$27*Inputs!$B$28+M56*(Inputs!$B$29+Inputs!$B$31)+M54*Inputs!$B$30+M55*Inputs!$B$32 -> 1013.1551
A61: Business | Opening accounts | B61: =0 -> 0 | C61: =B64 -> 1.2 | D61: =C64 -> 2.472 | E61: =D64 -> 3.82512 | F61: =E64 -> 5.2693152 | G61: =F64 -> 6.8154626 | H61: =G64 -> 8.4754561 | I61: =H64 -> 10.262311 | J61: =I64 -> 12.190279 | ... M61: =L64 -> 18.984663
A62: Business | New accounts | B62: =B27*$C$20 -> 1.2 | C62: =C27*$C$20 -> 1.32 | D62: =D27*$C$20 -> 1.452 | E62: =E27*$C$20 -> 1.5972 | F62: =F27*$C$20 -> 1.75692 | G62: =G27*$C$20 -> 1.932612 | H62: =H27*$C$20 -> 2.1258732 | I62: =I27*$C$20 -> 2.3384605 | ... M62: =M27*$C$20 -> 3.42374
A63: Business | Churned accounts | B63: =B61*$B$7 -> 0 | C63: =C61*$B$7 -> 0.048 | D63: =D61*$B$7 -> 0.09888 | E63: =E61*$B$7 -> 0.1530048 | F63: =F61*$B$7 -> 0.21077261 | G63: =G61*$B$7 -> 0.2726185 | H63: =H61*$B$7 -> 0.33901824 | I63: =I61*$B$7 -> 0.41049244 | ... M63: =M61*$B$7 -> 0.75938653
A64: Business | Ending accounts | B64: =B61+B62-B63 -> 1.2 | C64: =C61+C62-C63 -> 2.472 | D64: =D61+D62-D63 -> 3.82512 | E64: =E61+E62-E63 -> 5.2693152 | F64: =F61+F62-F63 -> 6.8154626 | G64: =G61+G62-G63 -> 8.4754561 | H64: =H61+H62-H63 -> 10.262311 | I64: =I61+I62-I63 -> 12.190279 | ... M64: =M61+M62-M63 -> 21.649017
A65: Business | Average accounts | B65: =(B61+B64)/2 -> 0.6 | C65: =(C61+C64)/2 -> 1.836 | D65: =(D61+D64)/2 -> 3.14856 | E65: =(E61+E64)/2 -> 4.5472176 | F65: =(F61+F64)/2 -> 6.0423889 | G65: =(G61+G64)/2 -> 7.6454593 | H65: =(H61+H64)/2 -> 9.3688836 | I65: =(I61+I64)/2 -> 11.226295 | ... M65: =(M61+M64)/2 -> 20.31684
A66: Business | Revenue | B66: =B65*$B$20 -> 59.4 | C66: =C65*$B$20 -> 181.764 | D66: =D65*$B$20 -> 311.70744 | E66: =E65*$B$20 -> 450.17454 | F66: =F65*$B$20 -> 598.1965 | G66: =G65*$B$20 -> 756.90047 | H66: =H65*$B$20 -> 927.51947 | I66: =I65*$B$20 -> 1111.4032 | ... M66: =M65*$B$20 -> 2011.3672
A67: Business | Monitoring checks | B67: =(B65*$D$20)*DAY(EOMONTH(B$25,0))*1440/$E$20*$B$12 -> 160704 | C67: =(C65*$D$20)*DAY(EOMONTH(C$25,0))*1440/$E$20*$B$12 -> 475891.2 | D67: =(D65*$D$20)*DAY(EOMONTH(D$25,0))*1440/$E$20*$B$12 -> 843310.31 | E67: =(E65*$D$20)*DAY(EOMONTH(E$25,0))*1440/$E$20*$B$12 -> 1217926.8 | F67: =(F65*$D$20)*DAY(EOMONTH(F$25,0))*1440/$E$20*$B$12 -> 1461774.7 | G67: =(G65*$D$20)*DAY(EOMONTH(G$25,0))*1440/$E$20*$B$12 -> 2047759.8 | H67: =(H65*$D$20)*DAY(EOMONTH(H$25,0))*1440/$E$20*$B$12 -> 2428414.6 | I67: =(I65*$D$20)*DAY(EOMONTH(I$25,0))*1440/$E$20*$B$12 -> 3006850.9 | ... M67: =(M65*$D$20)*DAY(EOMONTH(M$25,0))*1440/$E$20*$B$12 -> 5266124.9
A68: Business | AI diagnoses | B68: =(B65*$D$20)*Inputs!$B$8*$B$13*Inputs!$B$9*$F$20 -> 4.32 | C68: =(C65*$D$20)*Inputs!$B$8*$B$13*Inputs!$B$9*$F$20 -> 13.2192 | D68: =(D65*$D$20)*Inputs!$B$8*$B$13*Inputs!$B$9*$F$20 -> 22.669632 | E68: =(E65*$D$20)*Inputs!$B$8*$B$13*Inputs!$B$9*$F$20 -> 32.739967 | F68: =(F65*$D$20)*Inputs!$B$8*$B$13*Inputs!$B$9*$F$20 -> 43.5052 | G68: =(G65*$D$20)*Inputs!$B$8*$B$13*Inputs!$B$9*$F$20 -> 55.047307 | H68: =(H65*$D$20)*Inputs!$B$8*$B$13*Inputs!$B$9*$F$20 -> 67.455962 | I68: =(I65*$D$20)*Inputs!$B$8*$B$13*Inputs!$B$9*$F$20 -> 80.829325 | ... M68: =(M65*$D$20)*Inputs!$B$8*$B$13*Inputs!$B$9*$F$20 -> 146.28125
A69: Business | Variable service expense | B69: =B67/1000*(Inputs!$B$19+Inputs!$B$20+Inputs!$B$21+Inputs!$B$22+Inputs!$B$23+Inputs!$B$24)+B68*((((Inputs!$B$10*Inputs!$B$15+Inputs!$B$11*Inputs!$B$16)*(1-Inputs!$B$14)+(Inputs!$B$10*Inputs!$B$17+Inputs!$B$11*Inputs!$B$18)*Inputs!$B$14)/1000000*Inputs!$B$12)*$B$11+Inputs!$B$12*Inputs!$B$13)+(B65*$D$20)*Inputs!$B$25*Inputs!$B$26+((B65*$D$20)*Inputs!$B$8*$B$13)*Inputs!$B$27*Inputs!$B$28+B66*(Inputs!$B$29+Inputs!$B$31)+B64*Inputs!$B$30+B65*Inputs!$B$32 -> 30.245722 | C69: =C67/1000*(Inputs!$B$19+Inputs!$B$20+Inputs!$B$21+Inputs!$B$22+Inputs!$B$23+Inputs!$B$24)+C68*((((Inputs!$B$10*Inputs!$B$15+Inputs!$B$11*Inputs!$B$16)*(1-Inputs!$B$14)+(Inputs!$B$10*Inputs!$B$17+Inputs!$B$11*Inputs!$B$18)*Inputs!$B$14)/1000000*Inputs!$B$12)*$B$11+Inputs!$B$12*Inputs!$B$13)+(C65*$D$20)*Inputs!$B$25*Inputs!$B$26+((C65*$D$20)*Inputs!$B$8*$B$13)*Inputs!$B$27*Inputs!$B$28+C66*(Inputs!$B$29+Inputs!$B$31)+C64*Inputs!$B$30+C65*Inputs!$B$32 -> 89.495191 | D69: =D67/1000*(Inputs!$B$19+Inputs!$B$20+Inputs!$B$21+Inputs!$B$22+Inputs!$B$23+Inputs!$B$24)+D68*((((Inputs!$B$10*Inputs!$B$15+Inputs!$B$11*Inputs!$B$16)*(1-Inputs!$B$14)+(Inputs!$B$10*Inputs!$B$17+Inputs!$B$11*Inputs!$B$18)*Inputs!$B$14)/1000000*Inputs!$B$12)*$B$11+Inputs!$B$12*Inputs!$B$13)+(D65*$D$20)*Inputs!$B$25*Inputs!$B$26+((D65*$D$20)*Inputs!$B$8*$B$13)*Inputs!$B$27*Inputs!$B$28+D66*(Inputs!$B$29+Inputs!$B$31)+D64*Inputs!$B$30+D65*Inputs!$B$32 -> 157.97585 | E69: =E67/1000*(Inputs!$B$19+Inputs!$B$20+Inputs!$B$21+Inputs!$B$22+Inputs!$B$23+Inputs!$B$24)+E68*((((Inputs!$B$10*Inputs!$B$15+Inputs!$B$11*Inputs!$B$16)*(1-Inputs!$B$14)+(Inputs!$B$10*Inputs!$B$17+Inputs!$B$11*Inputs!$B$18)*Inputs!$B$14)/1000000*Inputs!$B$12)*$B$11+Inputs!$B$12*Inputs!$B$13)+(E65*$D$20)*Inputs!$B$25*Inputs!$B$26+((E65*$D$20)*Inputs!$B$8*$B$13)*Inputs!$B$27*Inputs!$B$28+E66*(Inputs!$B$29+Inputs!$B$31)+E64*Inputs!$B$30+E65*Inputs!$B$32 -> 228.07559 | F69: =F67/1000*(Inputs!$B$19+Inputs!$B$20+Inputs!$B$21+Inputs!$B$22+Inputs!$B$23+Inputs!$B$24)+F68*((((Inputs!$B$10*Inputs!$B$15+Inputs!$B$11*Inputs!$B$16)*(1-Inputs!$B$14)+(Inputs!$B$10*Inputs!$B$17+Inputs!$B$11*Inputs!$B$18)*Inputs!$B$14)/1000000*Inputs!$B$12)*$B$11+Inputs!$B$12*Inputs!$B$13)+(F65*$D$20)*Inputs!$B$25*Inputs!$B$26+((F65*$D$20)*Inputs!$B$8*$B$13)*Inputs!$B$27*Inputs!$B$28+F66*(Inputs!$B$29+Inputs!$B$31)+F64*Inputs!$B$30+F65*Inputs!$B$32 -> 276.38804 | G69: =G67/1000*(Inputs!$B$19+Inputs!$B$20+Inputs!$B$21+Inputs!$B$22+Inputs!$B$23+Inputs!$B$24)+G68*((((Inputs!$B$10*Inputs!$B$15+Inputs!$B$11*Inputs!$B$16)*(1-Inputs!$B$14)+(Inputs!$B$10*Inputs!$B$17+Inputs!$B$11*Inputs!$B$18)*Inputs!$B$14)/1000000*Inputs!$B$12)*$B$11+Inputs!$B$12*Inputs!$B$13)+(G65*$D$20)*Inputs!$B$25*Inputs!$B$26+((G65*$D$20)*Inputs!$B$8*$B$13)*Inputs!$B$27*Inputs!$B$28+G66*(Inputs!$B$29+Inputs!$B$31)+G64*Inputs!$B$30+G65*Inputs!$B$32 -> 383.35942 | H69: =H67/1000*(Inputs!$B$19+Inputs!$B$20+Inputs!$B$21+Inputs!$B$22+Inputs!$B$23+Inputs!$B$24)+H68*((((Inputs!$B$10*Inputs!$B$15+Inputs!$B$11*Inputs!$B$16)*(1-Inputs!$B$14)+(Inputs!$B$10*Inputs!$B$17+Inputs!$B$11*Inputs!$B$18)*Inputs!$B$14)/1000000*Inputs!$B$12)*$B$11+Inputs!$B$12*Inputs!$B$13)+(H65*$D$20)*Inputs!$B$25*Inputs!$B$26+((H65*$D$20)*Inputs!$B$8*$B$13)*Inputs!$B$27*Inputs!$B$28+H66*(Inputs!$B$29+Inputs!$B$31)+H64*Inputs!$B$30+H65*Inputs!$B$32 -> 455.97742 | I69: =I67/1000*(Inputs!$B$19+Inputs!$B$20+Inputs!$B$21+Inputs!$B$22+Inputs!$B$23+Inputs!$B$24)+I68*((((Inputs!$B$10*Inputs!$B$15+Inputs!$B$11*Inputs!$B$16)*(1-Inputs!$B$14)+(Inputs!$B$10*Inputs!$B$17+Inputs!$B$11*Inputs!$B$18)*Inputs!$B$14)/1000000*Inputs!$B$12)*$B$11+Inputs!$B$12*Inputs!$B$13)+(I65*$D$20)*Inputs!$B$25*Inputs!$B$26+((I65*$D$20)*Inputs!$B$8*$B$13)*Inputs!$B$27*Inputs!$B$28+I66*(Inputs!$B$29+Inputs!$B$31)+I64*Inputs!$B$30+I65*Inputs!$B$32 -> 562.83363 | ... M69: =M67/1000*(Inputs!$B$19+Inputs!$B$20+Inputs!$B$21+Inputs!$B$22+Inputs!$B$23+Inputs!$B$24)+M68*((((Inputs!$B$10*Inputs!$B$15+Inputs!$B$11*Inputs!$B$16)*(1-Inputs!$B$14)+(Inputs!$B$10*Inputs!$B$17+Inputs!$B$11*Inputs!$B$18)*Inputs!$B$14)/1000000*Inputs!$B$12)*$B$11+Inputs!$B$12*Inputs!$B$13)+(M65*$D$20)*Inputs!$B$25*Inputs!$B$26+((M65*$D$20)*Inputs!$B$8*$B$13)*Inputs!$B$27*Inputs!$B$28+M66*(Inputs!$B$29+Inputs!$B$31)+M64*Inputs!$B$30+M65*Inputs!$B$32 -> 988.6257
A73: Paying customers ending | B73: =B44+B54+B64 -> 12 | C73: =C44+C54+C64 -> 24.72 | D73: =D44+D54+D64 -> 38.2512 | E73: =E44+E54+E64 -> 52.693152 | F73: =F44+F54+F64 -> 68.154626 | G73: =G44+G54+G64 -> 84.754561 | H73: =H44+H54+H64 -> 102.62311 | I73: =I44+I54+I64 -> 121.90279 | ... M73: =M44+M54+M64 -> 216.49017
A74: Paying customers average | B74: =B45+B55+B65 -> 6 | C74: =C45+C55+C65 -> 18.36 | D74: =D45+D55+D65 -> 31.4856 | E74: =E45+E55+E65 -> 45.472176 | F74: =F45+F55+F65 -> 60.423889 | G74: =G45+G55+G65 -> 76.454593 | H74: =H45+H55+H65 -> 93.688836 | I74: =I45+I55+I65 -> 112.26295 | ... M74: =M45+M55+M65 -> 203.1684
A75: Free customers ending | B75: =B34 -> 138 | C75: =C34 -> 269.1 | D75: =D34 -> 395.715 | E75: =E34 -> 520.03575 | F75: =F34 -> 644.07619 | G75: =G34 -> 769.71514 | H75: =H34 -> 898.73329 | I75: =I34 -> 1032.8463 | ... M75: =M34 -> 1653.895
A76: Exit MRR | B76: =B44*$B$18+B54*$B$19+B64*$B$20 -> 288 | C76: =C44*$B$18+C54*$B$19+C64*$B$20 -> 593.28 | D76: =D44*$B$18+D54*$B$19+D64*$B$20 -> 918.0288 | E76: =E44*$B$18+E54*$B$19+E64*$B$20 -> 1264.6356 | F76: =F44*$B$18+F54*$B$19+F64*$B$20 -> 1635.711 | G76: =G44*$B$18+G54*$B$19+G64*$B$20 -> 2034.1095 | H76: =H44*$B$18+H54*$B$19+H64*$B$20 -> 2462.9547 | I76: =I44*$B$18+I54*$B$19+I64*$B$20 -> 2925.667 | ... M76: =M44*$B$18+M54*$B$19+M64*$B$20 -> 5195.764
A77: Revenue | B77: =B36+B46+B56+B66 -> 144 | C77: =C36+C46+C56+C66 -> 440.64 | D77: =D36+D46+D56+D66 -> 755.6544 | E77: =E36+E46+E56+E66 -> 1091.3322 | F77: =F36+F46+F56+F66 -> 1450.1733 | G77: =G36+G46+G56+G66 -> 1834.9102 | H77: =H36+H46+H56+H66 -> 2248.5321 | I77: =I36+I46+I56+I66 -> 2694.3108 | ... M77: =M36+M46+M56+M66 -> 4876.0416
A78: Monitoring checks | B78: =B37+B47+B57+B67 -> 623174.4 | C78: =C37+C47+C57+C67 -> 1823541.1 | D78: =D37+D47+D57+D67 -> 3181851.5 | E78: =E37+E47+E57+E67 -> 4529246.7 | F78: =F37+F47+F57+F67 -> 5365180.7 | G78: =G37+G47+G57+G67 -> 7427897.1 | H78: =H37+H47+H57+H67 -> 8716443.7 | I78: =I37+I47+I57+I67 -> 10692003 | ... M78: =M37+M47+M57+M67 -> 18208401
A79: AI diagnoses | B79: =B38+B48+B58+B68 -> 11.232 | C79: =C38+C48+C58+C68 -> 34.36992 | D79: =D38+D48+D58+D68 -> 58.941043 | E79: =E38+E48+E58+E68 -> 85.123913 | F79: =F38+F48+F58+F68 -> 113.11352 | G79: =G38+G48+G58+G68 -> 143.123 | H79: =H38+H48+H58+H68 -> 175.3855 | I79: =I38+I48+I58+I68 -> 210.15624 | ... M79: =M38+M48+M58+M68 -> 380.33124
A80: Variable cost of revenue | B80: =B39+B49+B59+B69 -> 118.24872 | C80: =C39+C49+C59+C69 -> 344.04649 | D80: =D39+D49+D59+D69 -> 598.00873 | E80: =E39+E49+E59+E69 -> 851.60111 | F80: =F39+F49+F59+F69 -> 1019.9172 | G80: =G39+G49+G59+G69 -> 1398.661 | H80: =H39+H49+H59+H69 -> 1647.8918 | I80: =I39+I49+I59+I69 -> 2016.2516 | ... M80: =M39+M49+M59+M69 -> 3453.1255
A81: Fixed platform cost | B81: =Inputs!$B$33+Inputs!$B$34+Inputs!$B$35+Inputs!$B$36+Inputs!$B$37+Inputs!$B$38+Inputs!$B$39 -> 100 | C81: =Inputs!$B$33+Inputs!$B$34+Inputs!$B$35+Inputs!$B$36+Inputs!$B$37+Inputs!$B$38+Inputs!$B$39 -> 100 | D81: =Inputs!$B$33+Inputs!$B$34+Inputs!$B$35+Inputs!$B$36+Inputs!$B$37+Inputs!$B$38+Inputs!$B$39 -> 100 | E81: =Inputs!$B$33+Inputs!$B$34+Inputs!$B$35+Inputs!$B$36+Inputs!$B$37+Inputs!$B$38+Inputs!$B$39 -> 100 | F81: =Inputs!$B$33+Inputs!$B$34+Inputs!$B$35+Inputs!$B$36+Inputs!$B$37+Inputs!$B$38+Inputs!$B$39 -> 100 | G81: =Inputs!$B$33+Inputs!$B$34+Inputs!$B$35+Inputs!$B$36+Inputs!$B$37+Inputs!$B$38+Inputs!$B$39 -> 100 | H81: =Inputs!$B$33+Inputs!$B$34+Inputs!$B$35+Inputs!$B$36+Inputs!$B$37+Inputs!$B$38+Inputs!$B$39 -> 100 | I81: =Inputs!$B$33+Inputs!$B$34+Inputs!$B$35+Inputs!$B$36+Inputs!$B$37+Inputs!$B$38+Inputs!$B$39 -> 100 | ... M81: =Inputs!$B$33+Inputs!$B$34+Inputs!$B$35+Inputs!$B$36+Inputs!$B$37+Inputs!$B$38+Inputs!$B$39 -> 100
A82: Capacity scaling cost | B82: =MAX(0,ROUNDUP((B35*$D$17+B45*$D$18+B55*$D$19+B65*$D$20)/Inputs!$B$40,0)-1)*Inputs!$B$41 -> 0 | C82: =MAX(0,ROUNDUP((C35*$D$17+C45*$D$18+C55*$D$19+C65*$D$20)/Inputs!$B$40,0)-1)*Inputs!$B$41 -> 0 | D82: =MAX(0,ROUNDUP((D35*$D$17+D45*$D$18+D55*$D$19+D65*$D$20)/Inputs!$B$40,0)-1)*Inputs!$B$41 -> 100 | E82: =MAX(0,ROUNDUP((E35*$D$17+E45*$D$18+E55*$D$19+E65*$D$20)/Inputs!$B$40,0)-1)*Inputs!$B$41 -> 100 | F82: =MAX(0,ROUNDUP((F35*$D$17+F45*$D$18+F55*$D$19+F65*$D$20)/Inputs!$B$40,0)-1)*Inputs!$B$41 -> 200 | G82: =MAX(0,ROUNDUP((G35*$D$17+G45*$D$18+G55*$D$19+G65*$D$20)/Inputs!$B$40,0)-1)*Inputs!$B$41 -> 200 | H82: =MAX(0,ROUNDUP((H35*$D$17+H45*$D$18+H55*$D$19+H65*$D$20)/Inputs!$B$40,0)-1)*Inputs!$B$41 -> 300 | I82: =MAX(0,ROUNDUP((I35*$D$17+I45*$D$18+I55*$D$19+I65*$D$20)/Inputs!$B$40,0)-1)*Inputs!$B$41 -> 300 | ... M82: =MAX(0,ROUNDUP((M35*$D$17+M45*$D$18+M55*$D$19+M65*$D$20)/Inputs!$B$40,0)-1)*Inputs!$B$41 -> 600
A83: Total cost of revenue | B83: =B80+B81+B82 -> 218.24872 | C83: =C80+C81+C82 -> 444.04649 | D83: =D80+D81+D82 -> 798.00873 | E83: =E80+E81+E82 -> 1051.6011 | F83: =F80+F81+F82 -> 1319.9172 | G83: =G80+G81+G82 -> 1698.661 | H83: =H80+H81+H82 -> 2047.8918 | I83: =I80+I81+I82 -> 2416.2516 | ... M83: =M80+M81+M82 -> 4153.1255
A84: Gross profit | B84: =B77-B83 -> -74.248716 | C84: =C77-C83 -> -3.406487 | D84: =D77-D83 -> -42.35433 | E84: =E77-E83 -> 39.731113 | F84: =F77-F83 -> 130.25616 | G84: =G77-G83 -> 136.24919 | H84: =H77-H83 -> 200.64023 | I84: =I77-I83 -> 278.05924 | ... M84: =M77-M83 -> 722.9161
A85: Gross margin | B85: =IFERROR(B84/B77,0) -> -0.51561608 | C85: =IFERROR(C84/C77,0) -> -0.0077307711 | D85: =IFERROR(D84/D77,0) -> -0.056049869 | E85: =IFERROR(E84/E77,0) -> 0.036406066 | F85: =IFERROR(F84/F77,0) -> 0.089821094 | G85: =IFERROR(G84/G77,0) -> 0.074253874 | H85: =IFERROR(H84/H77,0) -> 0.089231652 | I85: =IFERROR(I84/I77,0) -> 0.10320236 | ... M85: =IFERROR(M84/M77,0) -> 0.1482588
A86: Acquisition expense | B86: =B27*$B$9 -> 480 | C86: =C27*$B$9 -> 528 | D86: =D27*$B$9 -> 580.8 | E86: =E27*$B$9 -> 638.88 | F86: =F27*$B$9 -> 702.768 | G86: =G27*$B$9 -> 773.0448 | H86: =H27*$B$9 -> 850.34928 | I86: =I27*$B$9 -> 935.38421 | ... M86: =M27*$B$9 -> 1369.496
A87: Contractors | B87: =IF(COLUMN()-1>=Inputs!$B$44,Inputs!$B$43,0) -> 0 | C87: =IF(COLUMN()-1>=Inputs!$B$44,Inputs!$B$43,0) -> 0 | D87: =IF(COLUMN()-1>=Inputs!$B$44,Inputs!$B$43,0) -> 0 | E87: =IF(COLUMN()-1>=Inputs!$B$44,Inputs!$B$43,0) -> 1500 | F87: =IF(COLUMN()-1>=Inputs!$B$44,Inputs!$B$43,0) -> 1500 | G87: =IF(COLUMN()-1>=Inputs!$B$44,Inputs!$B$43,0) -> 1500 | H87: =IF(COLUMN()-1>=Inputs!$B$44,Inputs!$B$43,0) -> 1500 | I87: =IF(COLUMN()-1>=Inputs!$B$44,Inputs!$B$43,0) -> 1500 | ... M87: =IF(COLUMN()-1>=Inputs!$B$44,Inputs!$B$43,0) -> 1500
A88: Staff | B88: =IF(COLUMN()-1>=Inputs!$B$46,$B$10,0) -> 0 | C88: =IF(COLUMN()-1>=Inputs!$B$46,$B$10,0) -> 0 | D88: =IF(COLUMN()-1>=Inputs!$B$46,$B$10,0) -> 0 | E88: =IF(COLUMN()-1>=Inputs!$B$46,$B$10,0) -> 0 | F88: =IF(COLUMN()-1>=Inputs!$B$46,$B$10,0) -> 0 | G88: =IF(COLUMN()-1>=Inputs!$B$46,$B$10,0) -> 0 | H88: =IF(COLUMN()-1>=Inputs!$B$46,$B$10,0) -> 0 | I88: =IF(COLUMN()-1>=Inputs!$B$46,$B$10,0) -> 0 | ... M88: =IF(COLUMN()-1>=Inputs!$B$46,$B$10,0) -> 3000
A89: Founder pay | B89: =Inputs!$B$47 -> 0 | C89: =Inputs!$B$47 -> 0 | D89: =Inputs!$B$47 -> 0 | E89: =Inputs!$B$47 -> 0 | F89: =Inputs!$B$47 -> 0 | G89: =Inputs!$B$47 -> 0 | H89: =Inputs!$B$47 -> 0 | I89: =Inputs!$B$47 -> 0 | ... M89: =Inputs!$B$47 -> 0
A90: Administration | B90: =Inputs!$B$42 -> 150 | C90: =Inputs!$B$42 -> 150 | D90: =Inputs!$B$42 -> 150 | E90: =Inputs!$B$42 -> 150 | F90: =Inputs!$B$42 -> 150 | G90: =Inputs!$B$42 -> 150 | H90: =Inputs!$B$42 -> 150 | I90: =Inputs!$B$42 -> 150 | ... M90: =Inputs!$B$42 -> 150
A91: Total operating expense | B91: =B86+B87+B88+B89+B90 -> 630 | C91: =C86+C87+C88+C89+C90 -> 678 | D91: =D86+D87+D88+D89+D90 -> 730.8 | E91: =E86+E87+E88+E89+E90 -> 2288.88 | F91: =F86+F87+F88+F89+F90 -> 2352.768 | G91: =G86+G87+G88+G89+G90 -> 2423.0448 | H91: =H86+H87+H88+H89+H90 -> 2500.3493 | I91: =I86+I87+I88+I89+I90 -> 2585.3842 | ... M91: =M86+M87+M88+M89+M90 -> 6019.496
A92: Operating profit / net cash flow | B92: =B84-B91 -> -704.24872 | C92: =C84-C91 -> -681.40649 | D92: =D84-D91 -> -773.15433 | E92: =E84-E91 -> -2249.1489 | F92: =F84-F91 -> -2222.5118 | G92: =G84-G91 -> -2286.7956 | H92: =H84-H91 -> -2299.7091 | I92: =I84-I91 -> -2307.325 | ... M92: =M84-M91 -> -5296.5799
A93: Cumulative cash flow | B93: =0+B92 -> -704.24872 | C93: =B93+C92 -> -1385.6552 | D93: =C93+D92 -> -2158.8095 | E93: =D93+E92 -> -4407.9584 | F93: =E93+F92 -> -6630.4703 | G93: =F93+G92 -> -8917.2659 | H93: =G93+H92 -> -11216.975 | I93: =H93+I92 -> -13524.3 | J93: =I93+J92 -> -18817.304 | ... M93: =L93+M92 -> -34783.516
A94: Cash from editable starting cash | B94: =Inputs!$B$49+B93 -> 14295.751 | C94: =Inputs!$B$49+C93 -> 13614.345 | D94: =Inputs!$B$49+D93 -> 12841.19 | E94: =Inputs!$B$49+E93 -> 10592.042 | F94: =Inputs!$B$49+F93 -> 8369.5297 | G94: =Inputs!$B$49+G93 -> 6082.7341 | H94: =Inputs!$B$49+H93 -> 3783.0251 | I94: =Inputs!$B$49+I93 -> 1475.7001 | ... M94: =Inputs!$B$49+M93 -> -19783.516
A95: Cash from $5k | B95: =Inputs!$B$54+B93 -> 4295.7513 | C95: =Inputs!$B$54+C93 -> 3614.3448 | D95: =Inputs!$B$54+D93 -> 2841.1905 | E95: =Inputs!$B$54+E93 -> 592.04158 | F95: =Inputs!$B$54+F93 -> -1630.4703 | G95: =Inputs!$B$54+G93 -> -3917.2659 | H95: =Inputs!$B$54+H93 -> -6216.9749 | I95: =Inputs!$B$54+I93 -> -8524.2999 | ... M95: =Inputs!$B$54+M93 -> -29783.516
A96: Cash from $15k | B96: =Inputs!$B$55+B93 -> 14295.751 | C96: =Inputs!$B$55+C93 -> 13614.345 | D96: =Inputs!$B$55+D93 -> 12841.19 | E96: =Inputs!$B$55+E93 -> 10592.042 | F96: =Inputs!$B$55+F93 -> 8369.5297 | G96: =Inputs!$B$55+G93 -> 6082.7341 | H96: =Inputs!$B$55+H93 -> 3783.0251 | I96: =Inputs!$B$55+I93 -> 1475.7001 | ... M96: =Inputs!$B$55+M93 -> -19783.516
A97: Cash from $30k | B97: =Inputs!$B$56+B93 -> 29295.751 | C97: =Inputs!$B$56+C93 -> 28614.345 | D97: =Inputs!$B$56+D93 -> 27841.19 | E97: =Inputs!$B$56+E93 -> 25592.042 | F97: =Inputs!$B$56+F93 -> 23369.53 | G97: =Inputs!$B$56+G93 -> 21082.734 | H97: =Inputs!$B$56+H93 -> 18783.025 | I97: =Inputs!$B$56+I93 -> 16475.7 | ... M97: =Inputs!$B$56+M93 -> -4783.5157
A98: ARPPU | B98: =IFERROR(B77/B74,0) -> 24 | C98: =IFERROR(C77/C74,0) -> 24 | D98: =IFERROR(D77/D74,0) -> 24 | E98: =IFERROR(E77/E74,0) -> 24 | F98: =IFERROR(F77/F74,0) -> 24 | G98: =IFERROR(G77/G74,0) -> 24 | H98: =IFERROR(H77/H74,0) -> 24 | I98: =IFERROR(I77/I74,0) -> 24 | ... M98: =IFERROR(M77/M74,0) -> 24
A99: ARPU all accounts | B99: =IFERROR(B77/(B35+B45+B55+B65),0) -> 1.92 | C99: =IFERROR(C77/(C35+C45+C55+C65),0) -> 1.9856699 | D99: =IFERROR(D77/(D35+D45+D55+D65),0) -> 2.0765835 | E99: =IFERROR(E77/(E35+E45+E55+E65),0) -> 2.1681485 | F99: =IFERROR(F77/(F35+F45+F55+F65),0) -> 2.2571499 | G99: =IFERROR(G77/(G35+G45+G55+G65),0) -> 2.342388 | H99: =IFERROR(H77/(H35+H45+H55+H65),0) -> 2.4232142 | I99: =IFERROR(I77/(I35+I45+I55+I65),0) -> 2.4992385 | ... M99: =IFERROR(M77/(M35+M45+M55+M65),0) -> 2.752665
A100: Cost per average paying account | B100: =IFERROR(B83/B74,0) -> 36.374786 | C100: =IFERROR(C83/C74,0) -> 24.185539 | D100: =IFERROR(D83/D74,0) -> 25.345197 | E100: =IFERROR(E83/E74,0) -> 23.126254 | F100: =IFERROR(F83/F74,0) -> 21.844294 | G100: =IFERROR(G83/G74,0) -> 22.217907 | H100: =IFERROR(H83/H74,0) -> 21.85844 | I100: =IFERROR(I83/I74,0) -> 21.523143 | ... M100: =IFERROR(M83/M74,0) -> 20.441789
A101: Gross profit per average paying account | B101: =B98-B100 -> -12.374786 | C101: =C98-C100 -> -0.18553851 | D101: =D98-D100 -> -1.3451969 | E101: =E98-E100 -> 0.87374558 | F101: =F98-F100 -> 2.1557063 | G101: =G98-G100 -> 1.782093 | H101: =H98-H100 -> 2.1415596 | I101: =I98-I100 -> 2.4768567 | ... M101: =M98-M100 -> 3.5582113
A102: LTV fully loaded | B102: =IF(B101>0,B101/$B$7,0) -> 0 | C102: =IF(C101>0,C101/$B$7,0) -> 0 | D102: =IF(D101>0,D101/$B$7,0) -> 0 | E102: =IF(E101>0,E101/$B$7,0) -> 21.84364 | F102: =IF(F101>0,F101/$B$7,0) -> 53.892657 | G102: =IF(G101>0,G101/$B$7,0) -> 44.552324 | H102: =IF(H101>0,H101/$B$7,0) -> 53.538991 | I102: =IF(I101>0,I101/$B$7,0) -> 61.921418 | ... M102: =IF(M101>0,M101/$B$7,0) -> 88.955283
A103: LTV to CAC fully loaded | B103: =IF(B101>0,B102/$B$9,0) -> 0 | C103: =IF(C101>0,C102/$B$9,0) -> 0 | D103: =IF(D101>0,D102/$B$9,0) -> 0 | E103: =IF(E101>0,E102/$B$9,0) -> 0.54609099 | F103: =IF(F101>0,F102/$B$9,0) -> 1.3473164 | G103: =IF(G101>0,G102/$B$9,0) -> 1.1138081 | H103: =IF(H101>0,H102/$B$9,0) -> 1.3384748 | I103: =IF(I101>0,I102/$B$9,0) -> 1.5480354 | ... M103: =IF(M101>0,M102/$B$9,0) -> 2.2238821
A104: CAC payback months | B104: =IF(B101>0,$B$9/B101,0) -> 0 | C104: =IF(C101>0,$B$9/C101,0) -> 0 | D104: =IF(D101>0,$B$9/D101,0) -> 0 | E104: =IF(E101>0,$B$9/E101,0) -> 45.779917 | F104: =IF(F101>0,$B$9/F101,0) -> 18.555404 | G104: =IF(G101>0,$B$9/G101,0) -> 22.445518 | H104: =IF(H101>0,$B$9/H101,0) -> 18.677976 | I104: =IF(I101>0,$B$9/I101,0) -> 16.149501 | ... M104: =IF(M101>0,$B$9/M101,0) -> 11.241603
A105: Cash bridge check | B105: =B94-Inputs!$B$49-B93 -> 0 | C105: =C94-Inputs!$B$49-C93 -> 0 | D105: =D94-Inputs!$B$49-D93 -> 0 | E105: =E94-Inputs!$B$49-E93 -> 0 | F105: =F94-Inputs!$B$49-F93 -> 0 | G105: =G94-Inputs!$B$49-G93 -> 0 | H105: =H94-Inputs!$B$49-H93 -> 0 | I105: =I94-Inputs!$B$49-I93 -> 0 | ... M105: =M94-Inputs!$B$49-M93 -> 0

Sheet Conservative
A1: Conservative — hypothetical 12-month forecast
A4: Initial monthly signups | B4: 80
A5: Monthly signup growth | B5: 0.05
A6: Paid conversion rate | B6: 0.04
A7: Monthly paid churn | B7: 0.07
A8: Monthly free churn | B8: 0.2
A9: Blended acquisition CAC | B9: 60
A10: Staff monthly budget | B10: =Inputs!$B$45 -> 3000
A11: AI cost stress multiplier | B11: =Inputs!$B$50 -> 1
A12: Monitoring frequency multiplier | B12: =Inputs!$B$51 -> 1
A13: Incident volume multiplier | B13: =Inputs!$B$52 -> 1
A17: Free | B17: =Pricing!B2 -> 0 | C17: =Pricing!C2 -> 0 | D17: =Pricing!D2 -> 1 | E17: =Pricing!E2 -> 15 | F17: =Pricing!F2 -> 0
A18: Starter | B18: =Pricing!B3 -> 9 | C18: 0.75 | D18: =Pricing!D3 -> 3 | E18: =Pricing!E3 -> 5 | F18: =Pricing!F3 -> 1
A19: Pro | B19: =Pricing!B4 -> 29 | C19: 0.22 | D19: =Pricing!D4 -> 10 | E19: =Pricing!E4 -> 5 | F19: =Pricing!F4 -> 1
A20: Business | B20: =Pricing!B5 -> 99 | C20: 0.03 | D20: =Pricing!D5 -> 30 | E20: =Pricing!E5 -> 5 | F20: =Pricing!F5 -> 1
B25: 46296 | C25: 46327 | D25: 46357 | E25: 46388 | F25: 46419 | G25: 46447 | H25: 46478 | I25: 46508 | J25: 46539 | K25: 46569 | L25: 46600 | M25: 46631
A26: New signups | B26: =$B$4 -> 80 | C26: =B26*(1+$B$5) -> 84 | D26: =C26*(1+$B$5) -> 88.2 | E26: =D26*(1+$B$5) -> 92.61 | F26: =E26*(1+$B$5) -> 97.2405 | G26: =F26*(1+$B$5) -> 102.10252 | H26: =G26*(1+$B$5) -> 107.20765 | I26: =H26*(1+$B$5) -> 112.56803 | J26: =I26*(1+$B$5) -> 118.19644 | ... M26: =L26*(1+$B$5) -> 136.82715
A27: New paid | B27: =B26*$B$6 -> 3.2 | C27: =C26*$B$6 -> 3.36 | D27: =D26*$B$6 -> 3.528 | E27: =E26*$B$6 -> 3.7044 | F27: =F26*$B$6 -> 3.88962 | G27: =G26*$B$6 -> 4.084101 | H27: =H26*$B$6 -> 4.2883061 | I27: =I26*$B$6 -> 4.5027214 | ... M27: =M26*$B$6 -> 5.4730859
A28: New free | B28: =B26-B27 -> 76.8 | C28: =C26-C27 -> 80.64 | D28: =D26-D27 -> 84.672 | E28: =E26-E27 -> 88.9056 | F28: =F26-F27 -> 93.35088 | G28: =G26-G27 -> 98.018424 | H28: =H26-H27 -> 102.91935 | I28: =I26-I27 -> 108.06531 | ... M28: =M26-M27 -> 131.35406
A31: Free | Opening accounts | B31: =0 -> 0 | C31: =B34 -> 76.8 | D31: =C34 -> 142.08 | E31: =D34 -> 198.336 | F31: =E34 -> 247.5744 | G31: =F34 -> 291.4104 | H31: =G34 -> 331.14674 | I31: =H34 -> 367.83674 | J31: =I34 -> 402.3347 | ... M31: =L34 -> 499.02797
A32: Free | New accounts | B32: =B28 -> 76.8 | C32: =C28 -> 80.64 | D32: =D28 -> 84.672 | E32: =E28 -> 88.9056 | F32: =F28 -> 93.35088 | G32: =G28 -> 98.018424 | H32: =H28 -> 102.91935 | I32: =I28 -> 108.06531 | ... M32: =M28 -> 131.35406
A33: Free | Churned accounts | B33: =B31*$B$8 -> 0 | C33: =C31*$B$8 -> 15.36 | D33: =D31*$B$8 -> 28.416 | E33: =E31*$B$8 -> 39.6672 | F33: =F31*$B$8 -> 49.51488 | G33: =G31*$B$8 -> 58.28208 | H33: =H31*$B$8 -> 66.229349 | I33: =I31*$B$8 -> 73.567348 | ... M33: =M31*$B$8 -> 99.805594
A34: Free | Ending accounts | B34: =B31+B32-B33 -> 76.8 | C34: =C31+C32-C33 -> 142.08 | D34: =D31+D32-D33 -> 198.336 | E34: =E31+E32-E33 -> 247.5744 | F34: =F31+F32-F33 -> 291.4104 | G34: =G31+G32-G33 -> 331.14674 | H34: =H31+H32-H33 -> 367.83674 | I34: =I31+I32-I33 -> 402.3347 | ... M34: =M31+M32-M33 -> 530.57644
A35: Free | Average accounts | B35: =(B31+B34)/2 -> 38.4 | C35: =(C31+C34)/2 -> 109.44 | D35: =(D31+D34)/2 -> 170.208 | E35: =(E31+E34)/2 -> 222.9552 | F35: =(F31+F34)/2 -> 269.4924 | G35: =(G31+G34)/2 -> 311.27857 | H35: =(H31+H34)/2 -> 349.49174 | I35: =(I31+I34)/2 -> 385.08572 | ... M35: =(M31+M34)/2 -> 514.80221
A36: Free | Revenue | B36: =B35*$B$17 -> 0 | C36: =C35*$B$17 -> 0 | D36: =D35*$B$17 -> 0 | E36: =E35*$B$17 -> 0 | F36: =F35*$B$17 -> 0 | G36: =G35*$B$17 -> 0 | H36: =H35*$B$17 -> 0 | I36: =I35*$B$17 -> 0 | ... M36: =M35*$B$17 -> 0
A37: Free | Monitoring checks | B37: =(B35*$D$17)*DAY(EOMONTH(B$25,0))*1440/$E$17*$B$12 -> 114278.4 | C37: =(C35*$D$17)*DAY(EOMONTH(C$25,0))*1440/$E$17*$B$12 -> 315187.2 | D37: =(D35*$D$17)*DAY(EOMONTH(D$25,0))*1440/$E$17*$B$12 -> 506539.01 | E37: =(E35*$D$17)*DAY(EOMONTH(E$25,0))*1440/$E$17*$B$12 -> 663514.68 | F37: =(F35*$D$17)*DAY(EOMONTH(F$25,0))*1440/$E$17*$B$12 -> 724395.57 | G37: =(G35*$D$17)*DAY(EOMONTH(G$25,0))*1440/$E$17*$B$12 -> 926365.03 | H37: =(H35*$D$17)*DAY(EOMONTH(H$25,0))*1440/$E$17*$B$12 -> 1006536.2 | I37: =(I35*$D$17)*DAY(EOMONTH(I$25,0))*1440/$E$17*$B$12 -> 1146015.1 | ... M37: =(M35*$D$17)*DAY(EOMONTH(M$25,0))*1440/$E$17*$B$12 -> 1482630.4
A38: Free | AI diagnoses | B38: =(B35*$D$17)*Inputs!$B$8*$B$13*Inputs!$B$9*$F$17 -> 0 | C38: =(C35*$D$17)*Inputs!$B$8*$B$13*Inputs!$B$9*$F$17 -> 0 | D38: =(D35*$D$17)*Inputs!$B$8*$B$13*Inputs!$B$9*$F$17 -> 0 | E38: =(E35*$D$17)*Inputs!$B$8*$B$13*Inputs!$B$9*$F$17 -> 0 | F38: =(F35*$D$17)*Inputs!$B$8*$B$13*Inputs!$B$9*$F$17 -> 0 | G38: =(G35*$D$17)*Inputs!$B$8*$B$13*Inputs!$B$9*$F$17 -> 0 | H38: =(H35*$D$17)*Inputs!$B$8*$B$13*Inputs!$B$9*$F$17 -> 0 | I38: =(I35*$D$17)*Inputs!$B$8*$B$13*Inputs!$B$9*$F$17 -> 0 | ... M38: =(M35*$D$17)*Inputs!$B$8*$B$13*Inputs!$B$9*$F$17 -> 0
A39: Free | Variable service expense | B39: =B37/1000*(Inputs!$B$19+Inputs!$B$20+Inputs!$B$21+Inputs!$B$22+Inputs!$B$23+Inputs!$B$24)+B38*((((Inputs!$B$10*Inputs!$B$15+Inputs!$B$11*Inputs!$B$16)*(1-Inputs!$B$14)+(Inputs!$B$10*Inputs!$B$17+Inputs!$B$11*Inputs!$B$18)*Inputs!$B$14)/1000000*Inputs!$B$12)*$B$11+Inputs!$B$12*Inputs!$B$13)+(B35*$D$17)*Inputs!$B$25*Inputs!$B$26+((B35*$D$17)*Inputs!$B$8*$B$13)*Inputs!$B$27*Inputs!$B$28+B36*(Inputs!$B$29+Inputs!$B$31) -> 19.534848 | C39: =C37/1000*(Inputs!$B$19+Inputs!$B$20+Inputs!$B$21+Inputs!$B$22+Inputs!$B$23+Inputs!$B$24)+C38*((((Inputs!$B$10*Inputs!$B$15+Inputs!$B$11*Inputs!$B$16)*(1-Inputs!$B$14)+(Inputs!$B$10*Inputs!$B$17+Inputs!$B$11*Inputs!$B$18)*Inputs!$B$14)/1000000*Inputs!$B$12)*$B$11+Inputs!$B$12*Inputs!$B$13)+(C35*$D$17)*Inputs!$B$25*Inputs!$B$26+((C35*$D$17)*Inputs!$B$8*$B$13)*Inputs!$B$27*Inputs!$B$28+C36*(Inputs!$B$29+Inputs!$B$31) -> 53.888256 | D39: =D37/1000*(Inputs!$B$19+Inputs!$B$20+Inputs!$B$21+Inputs!$B$22+Inputs!$B$23+Inputs!$B$24)+D38*((((Inputs!$B$10*Inputs!$B$15+Inputs!$B$11*Inputs!$B$16)*(1-Inputs!$B$14)+(Inputs!$B$10*Inputs!$B$17+Inputs!$B$11*Inputs!$B$18)*Inputs!$B$14)/1000000*Inputs!$B$12)*$B$11+Inputs!$B$12*Inputs!$B$13)+(D35*$D$17)*Inputs!$B$25*Inputs!$B$26+((D35*$D$17)*Inputs!$B$8*$B$13)*Inputs!$B$27*Inputs!$B$28+D36*(Inputs!$B$29+Inputs!$B$31) -> 86.588214 | E39: =E37/1000*(Inputs!$B$19+Inputs!$B$20+Inputs!$B$21+Inputs!$B$22+Inputs!$B$23+Inputs!$B$24)+E38*((((Inputs!$B$10*Inputs!$B$15+Inputs!$B$11*Inputs!$B$16)*(1-Inputs!$B$14)+(Inputs!$B$10*Inputs!$B$17+Inputs!$B$11*Inputs!$B$18)*Inputs!$B$14)/1000000*Inputs!$B$12)*$B$11+Inputs!$B$12*Inputs!$B$13)+(E35*$D$17)*Inputs!$B$25*Inputs!$B$26+((E35*$D$17)*Inputs!$B$8*$B$13)*Inputs!$B$27*Inputs!$B$28+E36*(Inputs!$B$29+Inputs!$B$31) -> 113.42177 | F39: =F37/1000*(Inputs!$B$19+Inputs!$B$20+Inputs!$B$21+Inputs!$B$22+Inputs!$B$23+Inputs!$B$24)+F38*((((Inputs!$B$10*Inputs!$B$15+Inputs!$B$11*Inputs!$B$16)*(1-Inputs!$B$14)+(Inputs!$B$10*Inputs!$B$17+Inputs!$B$11*Inputs!$B$18)*Inputs!$B$14)/1000000*Inputs!$B$12)*$B$11+Inputs!$B$12*Inputs!$B$13)+(F35*$D$17)*Inputs!$B$25*Inputs!$B$26+((F35*$D$17)*Inputs!$B$8*$B$13)*Inputs!$B$27*Inputs!$B$28+F36*(Inputs!$B$29+Inputs!$B$31) -> 123.90183 | G39: =G37/1000*(Inputs!$B$19+Inputs!$B$20+Inputs!$B$21+Inputs!$B$22+Inputs!$B$23+Inputs!$B$24)+G38*((((Inputs!$B$10*Inputs!$B$15+Inputs!$B$11*Inputs!$B$16)*(1-Inputs!$B$14)+(Inputs!$B$10*Inputs!$B$17+Inputs!$B$11*Inputs!$B$18)*Inputs!$B$14)/1000000*Inputs!$B$12)*$B$11+Inputs!$B$12*Inputs!$B$13)+(G35*$D$17)*Inputs!$B$25*Inputs!$B$26+((G35*$D$17)*Inputs!$B$8*$B$13)*Inputs!$B$27*Inputs!$B$28+G36*(Inputs!$B$29+Inputs!$B$31) -> 158.35364 | H39: =H37/1000*(Inputs!$B$19+Inputs!$B$20+Inputs!$B$21+Inputs!$B$22+Inputs!$B$23+Inputs!$B$24)+H38*((((Inputs!$B$10*Inputs!$B$15+Inputs!$B$11*Inputs!$B$16)*(1-Inputs!$B$14)+(Inputs!$B$10*Inputs!$B$17+Inputs!$B$11*Inputs!$B$18)*Inputs!$B$14)/1000000*Inputs!$B$12)*$B$11+Inputs!$B$12*Inputs!$B$13)+(H35*$D$17)*Inputs!$B$25*Inputs!$B$26+((H35*$D$17)*Inputs!$B$8*$B$13)*Inputs!$B$27*Inputs!$B$28+H36*(Inputs!$B$29+Inputs!$B$31) -> 172.08973 | I39: =I37/1000*(Inputs!$B$19+Inputs!$B$20+Inputs!$B$21+Inputs!$B$22+Inputs!$B$23+Inputs!$B$24)+I38*((((Inputs!$B$10*Inputs!$B$15+Inputs!$B$11*Inputs!$B$16)*(1-Inputs!$B$14)+(Inputs!$B$10*Inputs!$B$17+Inputs!$B$11*Inputs!$B$18)*Inputs!$B$14)/1000000*Inputs!$B$12)*$B$11+Inputs!$B$12*Inputs!$B$13)+(I35*$D$17)*Inputs!$B$25*Inputs!$B$26+((I35*$D$17)*Inputs!$B$8*$B$13)*Inputs!$B$27*Inputs!$B$28+I36*(Inputs!$B$29+Inputs!$B$31) -> 195.90081 | ... M39: =M37/1000*(Inputs!$B$19+Inputs!$B$20+Inputs!$B$21+Inputs!$B$22+Inputs!$B$23+Inputs!$B$24)+M38*((((Inputs!$B$10*Inputs!$B$15+Inputs!$B$11*Inputs!$B$16)*(1-Inputs!$B$14)+(Inputs!$B$10*Inputs!$B$17+Inputs!$B$11*Inputs!$B$18)*Inputs!$B$14)/1000000*Inputs!$B$12)*$B$11+Inputs!$B$12*Inputs!$B$13)+(M35*$D$17)*Inputs!$B$25*Inputs!$B$26+((M35*$D$17)*Inputs!$B$8*$B$13)*Inputs!$B$27*Inputs!$B$28+M36*(Inputs!$B$29+Inputs!$B$31) -> 253.48861
A41: Starter | Opening accounts | B41: =0 -> 0 | C41: =B44 -> 2.4 | D41: =C44 -> 4.752 | E41: =D44 -> 7.06536 | F41: =E44 -> 9.3490848 | G41: =F44 -> 11.611864 | H41: =G44 -> 13.862109 | I41: =H44 -> 16.107991 | J41: =I44 -> 18.357473 | ... M41: =L44 -> 25.204716
A42: Starter | New accounts | B42: =B27*$C$18 -> 2.4 | C42: =C27*$C$18 -> 2.52 | D42: =D27*$C$18 -> 2.646 | E42: =E27*$C$18 -> 2.7783 | F42: =F27*$C$18 -> 2.917215 | G42: =G27*$C$18 -> 3.0630757 | H42: =H27*$C$18 -> 3.2162295 | I42: =I27*$C$18 -> 3.377041 | ... M42: =M27*$C$18 -> 4.1048145
A43: Starter | Churned accounts | B43: =B41*$B$7 -> 0 | C43: =C41*$B$7 -> 0.168 | D43: =D41*$B$7 -> 0.33264 | E43: =E41*$B$7 -> 0.4945752 | F43: =F41*$B$7 -> 0.65443594 | G43: =G41*$B$7 -> 0.81283047 | H43: =H41*$B$7 -> 0.97034764 | I43: =I41*$B$7 -> 1.1275594 | ... M43: =M41*$B$7 -> 1.7643301
A44: Starter | Ending accounts | B44: =B41+B42-B43 -> 2.4 | C44: =C41+C42-C43 -> 4.752 | D44: =D41+D42-D43 -> 7.06536 | E44: =E41+E42-E43 -> 9.3490848 | F44: =F41+F42-F43 -> 11.611864 | G44: =G41+G42-G43 -> 13.862109 | H44: =H41+H42-H43 -> 16.107991 | I44: =I41+I42-I43 -> 18.357473 | ... M44: =M41+M42-M43 -> 27.545201
A45: Starter | Average accounts | B45: =(B41+B44)/2 -> 1.2 | C45: =(C41+C44)/2 -> 3.576 | D45: =(D41+D44)/2 -> 5.90868 | E45: =(E41+E44)/2 -> 8.2072224 | F45: =(F41+F44)/2 -> 10.480474 | G45: =(G41+G44)/2 -> 12.736987 | H45: =(H41+H44)/2 -> 14.98505 | I45: =(I41+I44)/2 -> 17.232732 | ... M45: =(M41+M44)/2 -> 26.374958
A46: Starter | Revenue | B46: =B45*$B$18 -> 10.8 | C46: =C45*$B$18 -> 32.184 | D46: =D45*$B$18 -> 53.17812 | E46: =E45*$B$18 -> 73.865002 | F46: =F45*$B$18 -> 94.324269 | G46: =G45*$B$18 -> 114.63288 | H46: =H45*$B$18 -> 134.86545 | I46: =I45*$B$18 -> 155.09459 | ... M46: =M45*$B$18 -> 237.37463
A47: Starter | Monitoring checks | B47: =(B45*$D$18)*DAY(EOMONTH(B$25,0))*1440/$E$18*$B$12 -> 32140.8 | C47: =(C45*$D$18)*DAY(EOMONTH(C$25,0))*1440/$E$18*$B$12 -> 92689.92 | D47: =(D45*$D$18)*DAY(EOMONTH(D$25,0))*1440/$E$18*$B$12 -> 158258.09 | E47: =(E45*$D$18)*DAY(EOMONTH(E$25,0))*1440/$E$18*$B$12 -> 219822.24 | F47: =(F45*$D$18)*DAY(EOMONTH(F$25,0))*1440/$E$18*$B$12 -> 253543.64 | G47: =(G45*$D$18)*DAY(EOMONTH(G$25,0))*1440/$E$18*$B$12 -> 341147.45 | H47: =(H45*$D$18)*DAY(EOMONTH(H$25,0))*1440/$E$18*$B$12 -> 388412.5 | I47: =(I45*$D$18)*DAY(EOMONTH(I$25,0))*1440/$E$18*$B$12 -> 461561.49 | ... M47: =(M45*$D$18)*DAY(EOMONTH(M$25,0))*1440/$E$18*$B$12 -> 683638.92
A48: Starter | AI diagnoses | B48: =(B45*$D$18)*Inputs!$B$8*$B$13*Inputs!$B$9*$F$18 -> 0.864 | C48: =(C45*$D$18)*Inputs!$B$8*$B$13*Inputs!$B$9*$F$18 -> 2.57472 | D48: =(D45*$D$18)*Inputs!$B$8*$B$13*Inputs!$B$9*$F$18 -> 4.2542496 | E48: =(E45*$D$18)*Inputs!$B$8*$B$13*Inputs!$B$9*$F$18 -> 5.9092001 | F48: =(F45*$D$18)*Inputs!$B$8*$B$13*Inputs!$B$9*$F$18 -> 7.5459415 | G48: =(G45*$D$18)*Inputs!$B$8*$B$13*Inputs!$B$9*$F$18 -> 9.1706303 | H48: =(H45*$D$18)*Inputs!$B$8*$B$13*Inputs!$B$9*$F$18 -> 10.789236 | I48: =(I45*$D$18)*Inputs!$B$8*$B$13*Inputs!$B$9*$F$18 -> 12.407567 | ... M48: =(M45*$D$18)*Inputs!$B$8*$B$13*Inputs!$B$9*$F$18 -> 18.98997
A49: Starter | Variable service expense | B49: =B47/1000*(Inputs!$B$19+Inputs!$B$20+Inputs!$B$21+Inputs!$B$22+Inputs!$B$23+Inputs!$B$24)+B48*((((Inputs!$B$10*Inputs!$B$15+Inputs!$B$11*Inputs!$B$16)*(1-Inputs!$B$14)+(Inputs!$B$10*Inputs!$B$17+Inputs!$B$11*Inputs!$B$18)*Inputs!$B$14)/1000000*Inputs!$B$12)*$B$11+Inputs!$B$12*Inputs!$B$13)+(B45*$D$18)*Inputs!$B$25*Inputs!$B$26+((B45*$D$18)*Inputs!$B$8*$B$13)*Inputs!$B$27*Inputs!$B$28+B46*(Inputs!$B$29+Inputs!$B$31)+B44*Inputs!$B$30+B45*Inputs!$B$32 -> 7.1982643 | C49: =C47/1000*(Inputs!$B$19+Inputs!$B$20+Inputs!$B$21+Inputs!$B$22+Inputs!$B$23+Inputs!$B$24)+C48*((((Inputs!$B$10*Inputs!$B$15+Inputs!$B$11*Inputs!$B$16)*(1-Inputs!$B$14)+(Inputs!$B$10*Inputs!$B$17+Inputs!$B$11*Inputs!$B$18)*Inputs!$B$14)/1000000*Inputs!$B$12)*$B$11+Inputs!$B$12*Inputs!$B$13)+(C45*$D$18)*Inputs!$B$25*Inputs!$B$26+((C45*$D$18)*Inputs!$B$8*$B$13)*Inputs!$B$27*Inputs!$B$28+C46*(Inputs!$B$29+Inputs!$B$31)+C44*Inputs!$B$30+C45*Inputs!$B$32 -> 20.205585 | D49: =D47/1000*(Inputs!$B$19+Inputs!$B$20+Inputs!$B$21+Inputs!$B$22+Inputs!$B$23+Inputs!$B$24)+D48*((((Inputs!$B$10*Inputs!$B$15+Inputs!$B$11*Inputs!$B$16)*(1-Inputs!$B$14)+(Inputs!$B$10*Inputs!$B$17+Inputs!$B$11*Inputs!$B$18)*Inputs!$B$14)/1000000*Inputs!$B$12)*$B$11+Inputs!$B$12*Inputs!$B$13)+(D45*$D$18)*Inputs!$B$25*Inputs!$B$26+((D45*$D$18)*Inputs!$B$8*$B$13)*Inputs!$B$27*Inputs!$B$28+D46*(Inputs!$B$29+Inputs!$B$31)+D44*Inputs!$B$30+D45*Inputs!$B$32 -> 34.017934 | E49: =E47/1000*(Inputs!$B$19+Inputs!$B$20+Inputs!$B$21+Inputs!$B$22+Inputs!$B$23+Inputs!$B$24)+E48*((((Inputs!$B$10*Inputs!$B$15+Inputs!$B$11*Inputs!$B$16)*(1-Inputs!$B$14)+(Inputs!$B$10*Inputs!$B$17+Inputs!$B$11*Inputs!$B$18)*Inputs!$B$14)/1000000*Inputs!$B$12)*$B$11+Inputs!$B$12*Inputs!$B$13)+(E45*$D$18)*Inputs!$B$25*Inputs!$B$26+((E45*$D$18)*Inputs!$B$8*$B$13)*Inputs!$B$27*Inputs!$B$28+E46*(Inputs!$B$29+Inputs!$B$31)+E44*Inputs!$B$30+E45*Inputs!$B$32 -> 47.111855 | F49: =F47/1000*(Inputs!$B$19+Inputs!$B$20+Inputs!$B$21+Inputs!$B$22+Inputs!$B$23+Inputs!$B$24)+F48*((((Inputs!$B$10*Inputs!$B$15+Inputs!$B$11*Inputs!$B$16)*(1-Inputs!$B$14)+(Inputs!$B$10*Inputs!$B$17+Inputs!$B$11*Inputs!$B$18)*Inputs!$B$14)/1000000*Inputs!$B$12)*$B$11+Inputs!$B$12*Inputs!$B$13)+(F45*$D$18)*Inputs!$B$25*Inputs!$B$26+((F45*$D$18)*Inputs!$B$8*$B$13)*Inputs!$B$27*Inputs!$B$28+F46*(Inputs!$B$29+Inputs!$B$31)+F44*Inputs!$B$30+F45*Inputs!$B$32 -> 55.444845 | G49: =G47/1000*(Inputs!$B$19+Inputs!$B$20+Inputs!$B$21+Inputs!$B$22+Inputs!$B$23+Inputs!$B$24)+G48*((((Inputs!$B$10*Inputs!$B$15+Inputs!$B$11*Inputs!$B$16)*(1-Inputs!$B$14)+(Inputs!$B$10*Inputs!$B$17+Inputs!$B$11*Inputs!$B$18)*Inputs!$B$14)/1000000*Inputs!$B$12)*$B$11+Inputs!$B$12*Inputs!$B$13)+(G45*$D$18)*Inputs!$B$25*Inputs!$B$26+((G45*$D$18)*Inputs!$B$8*$B$13)*Inputs!$B$27*Inputs!$B$28+G46*(Inputs!$B$29+Inputs!$B$31)+G44*Inputs!$B$30+G45*Inputs!$B$32 -> 72.919937 | H49: =H47/1000*(Inputs!$B$19+Inputs!$B$20+Inputs!$B$21+Inputs!$B$22+Inputs!$B$23+Inputs!$B$24)+H48*((((Inputs!$B$10*Inputs!$B$15+Inputs!$B$11*Inputs!$B$16)*(1-Inputs!$B$14)+(Inputs!$B$10*Inputs!$B$17+Inputs!$B$11*Inputs!$B$18)*Inputs!$B$14)/1000000*Inputs!$B$12)*$B$11+Inputs!$B$12*Inputs!$B$13)+(H45*$D$18)*Inputs!$B$25*Inputs!$B$26+((H45*$D$18)*Inputs!$B$8*$B$13)*Inputs!$B$27*Inputs!$B$28+H46*(Inputs!$B$29+Inputs!$B$31)+H44*Inputs!$B$30+H45*Inputs!$B$32 -> 83.528989 | I49: =I47/1000*(Inputs!$B$19+Inputs!$B$20+Inputs!$B$21+Inputs!$B$22+Inputs!$B$23+Inputs!$B$24)+I48*((((Inputs!$B$10*Inputs!$B$15+Inputs!$B$11*Inputs!$B$16)*(1-Inputs!$B$14)+(Inputs!$B$10*Inputs!$B$17+Inputs!$B$11*Inputs!$B$18)*Inputs!$B$14)/1000000*Inputs!$B$12)*$B$11+Inputs!$B$12*Inputs!$B$13)+(I45*$D$18)*Inputs!$B$25*Inputs!$B$26+((I45*$D$18)*Inputs!$B$8*$B$13)*Inputs!$B$27*Inputs!$B$28+I46*(Inputs!$B$29+Inputs!$B$31)+I44*Inputs!$B$30+I45*Inputs!$B$32 -> 98.539068 | ... M49: =M47/1000*(Inputs!$B$19+Inputs!$B$20+Inputs!$B$21+Inputs!$B$22+Inputs!$B$23+Inputs!$B$24)+M48*((((Inputs!$B$10*Inputs!$B$15+Inputs!$B$11*Inputs!$B$16)*(1-Inputs!$B$14)+(Inputs!$B$10*Inputs!$B$17+Inputs!$B$11*Inputs!$B$18)*Inputs!$B$14)/1000000*Inputs!$B$12)*$B$11+Inputs!$B$12*Inputs!$B$13)+(M45*$D$18)*Inputs!$B$25*Inputs!$B$26+((M45*$D$18)*Inputs!$B$8*$B$13)*Inputs!$B$27*Inputs!$B$28+M46*(Inputs!$B$29+Inputs!$B$31)+M44*Inputs!$B$30+M45*Inputs!$B$32 -> 146.77623
A51: Pro | Opening accounts | B51: =0 -> 0 | C51: =B54 -> 0.704 | D51: =C54 -> 1.39392 | E51: =D54 -> 2.0725056 | F51: =E54 -> 2.7423982 | G51: =F54 -> 3.4061467 | H51: =G54 -> 4.0662187 | I51: =H54 -> 4.7250107 | J51: =I54 -> 5.3848587 | ... M51: =L54 -> 7.3933834
A52: Pro | New accounts | B52: =B27*$C$19 -> 0.704 | C52: =C27*$C$19 -> 0.7392 | D52: =D27*$C$19 -> 0.77616 | E52: =E27*$C$19 -> 0.814968 | F52: =F27*$C$19 -> 0.8557164 | G52: =G27*$C$19 -> 0.89850222 | H52: =H27*$C$19 -> 0.94342733 | I52: =I27*$C$19 -> 0.9905987 | ... M52: =M27*$C$19 -> 1.2040789
A53: Pro | Churned accounts | B53: =B51*$B$7 -> 0 | C53: =C51*$B$7 -> 0.04928 | D53: =D51*$B$7 -> 0.0975744 | E53: =E51*$B$7 -> 0.14507539 | F53: =F51*$B$7 -> 0.19196787 | G53: =G51*$B$7 -> 0.23843027 | H53: =H51*$B$7 -> 0.28463531 | I53: =I51*$B$7 -> 0.33075075 | ... M53: =M51*$B$7 -> 0.51753684
A54: Pro | Ending accounts | B54: =B51+B52-B53 -> 0.704 | C54: =C51+C52-C53 -> 1.39392 | D54: =D51+D52-D53 -> 2.0725056 | E54: =E51+E52-E53 -> 2.7423982 | F54: =F51+F52-F53 -> 3.4061467 | G54: =G51+G52-G53 -> 4.0662187 | H54: =H51+H52-H53 -> 4.7250107 | I54: =I51+I52-I53 -> 5.3848587 | ... M54: =M51+M52-M53 -> 8.0799255
A55: Pro | Average accounts | B55: =(B51+B54)/2 -> 0.352 | C55: =(C51+C54)/2 -> 1.04896 | D55: =(D51+D54)/2 -> 1.7332128 | E55: =(E51+E54)/2 -> 2.4074519 | F55: =(F51+F54)/2 -> 3.0742725 | G55: =(G51+G54)/2 -> 3.7361827 | H55: =(H51+H54)/2 -> 4.3956147 | I55: =(I51+I54)/2 -> 5.0549347 | ... M55: =(M51+M54)/2 -> 7.7366545
A56: Pro | Revenue | B56: =B55*$B$19 -> 10.208 | C56: =C55*$B$19 -> 30.41984 | D56: =D55*$B$19 -> 50.263171 | E56: =E55*$B$19 -> 69.816105 | F56: =F55*$B$19 -> 89.153902 | G56: =G55*$B$19 -> 108.3493 | H56: =H55*$B$19 -> 127.47283 | I56: =I55*$B$19 -> 146.59311 | ... M56: =M55*$B$19 -> 224.36298
A57: Pro | Monitoring checks | B57: =(B55*$D$19)*DAY(EOMONTH(B$25,0))*1440/$E$19*$B$12 -> 31426.56 | C57: =(C55*$D$19)*DAY(EOMONTH(C$25,0))*1440/$E$19*$B$12 -> 90630.144 | D57: =(D55*$D$19)*DAY(EOMONTH(D$25,0))*1440/$E$19*$B$12 -> 154741.24 | E57: =(E55*$D$19)*DAY(EOMONTH(E$25,0))*1440/$E$19*$B$12 -> 214937.31 | F57: =(F55*$D$19)*DAY(EOMONTH(F$25,0))*1440/$E$19*$B$12 -> 247909.33 | G57: =(G55*$D$19)*DAY(EOMONTH(G$25,0))*1440/$E$19*$B$12 -> 333566.39 | H57: =(H55*$D$19)*DAY(EOMONTH(H$25,0))*1440/$E$19*$B$12 -> 379781.11 | I57: =(I55*$D$19)*DAY(EOMONTH(I$25,0))*1440/$E$19*$B$12 -> 451304.57 | ... M57: =(M55*$D$19)*DAY(EOMONTH(M$25,0))*1440/$E$19*$B$12 -> 668446.95
A58: Pro | AI diagnoses | B58: =(B55*$D$19)*Inputs!$B$8*$B$13*Inputs!$B$9*$F$19 -> 0.8448 | C58: =(C55*$D$19)*Inputs!$B$8*$B$13*Inputs!$B$9*$F$19 -> 2.517504 | D58: =(D55*$D$19)*Inputs!$B$8*$B$13*Inputs!$B$9*$F$19 -> 4.1597107 | E58: =(E55*$D$19)*Inputs!$B$8*$B$13*Inputs!$B$9*$F$19 -> 5.7778846 | F58: =(F55*$D$19)*Inputs!$B$8*$B$13*Inputs!$B$9*$F$19 -> 7.3782539 | G58: =(G55*$D$19)*Inputs!$B$8*$B$13*Inputs!$B$9*$F$19 -> 8.9668385 | H58: =(H55*$D$19)*Inputs!$B$8*$B$13*Inputs!$B$9*$F$19 -> 10.549475 | I58: =(I55*$D$19)*Inputs!$B$8*$B$13*Inputs!$B$9*$F$19 -> 12.131843 | ... M58: =(M55*$D$19)*Inputs!$B$8*$B$13*Inputs!$B$9*$F$19 -> 18.567971
A59: Pro | Variable service expense | B59: =B57/1000*(Inputs!$B$19+Inputs!$B$20+Inputs!$B$21+Inputs!$B$22+Inputs!$B$23+Inputs!$B$24)+B58*((((Inputs!$B$10*Inputs!$B$15+Inputs!$B$11*Inputs!$B$16)*(1-Inputs!$B$14)+(Inputs!$B$10*Inputs!$B$17+Inputs!$B$11*Inputs!$B$18)*Inputs!$B$14)/1000000*Inputs!$B$12)*$B$11+Inputs!$B$12*Inputs!$B$13)+(B55*$D$19)*Inputs!$B$25*Inputs!$B$26+((B55*$D$19)*Inputs!$B$8*$B$13)*Inputs!$B$27*Inputs!$B$28+B56*(Inputs!$B$29+Inputs!$B$31)+B54*Inputs!$B$30+B55*Inputs!$B$32 -> 6.1221642 | C59: =C57/1000*(Inputs!$B$19+Inputs!$B$20+Inputs!$B$21+Inputs!$B$22+Inputs!$B$23+Inputs!$B$24)+C58*((((Inputs!$B$10*Inputs!$B$15+Inputs!$B$11*Inputs!$B$16)*(1-Inputs!$B$14)+(Inputs!$B$10*Inputs!$B$17+Inputs!$B$11*Inputs!$B$18)*Inputs!$B$14)/1000000*Inputs!$B$12)*$B$11+Inputs!$B$12*Inputs!$B$13)+(C55*$D$19)*Inputs!$B$25*Inputs!$B$26+((C55*$D$19)*Inputs!$B$8*$B$13)*Inputs!$B$27*Inputs!$B$28+C56*(Inputs!$B$29+Inputs!$B$31)+C54*Inputs!$B$30+C55*Inputs!$B$32 -> 17.519279 | D59: =D57/1000*(Inputs!$B$19+Inputs!$B$20+Inputs!$B$21+Inputs!$B$22+Inputs!$B$23+Inputs!$B$24)+D58*((((Inputs!$B$10*Inputs!$B$15+Inputs!$B$11*Inputs!$B$16)*(1-Inputs!$B$14)+(Inputs!$B$10*Inputs!$B$17+Inputs!$B$11*Inputs!$B$18)*Inputs!$B$14)/1000000*Inputs!$B$12)*$B$11+Inputs!$B$12*Inputs!$B$13)+(D55*$D$19)*Inputs!$B$25*Inputs!$B$26+((D55*$D$19)*Inputs!$B$8*$B$13)*Inputs!$B$27*Inputs!$B$28+D56*(Inputs!$B$29+Inputs!$B$31)+D54*Inputs!$B$30+D55*Inputs!$B$32 -> 29.726748 | E59: =E57/1000*(Inputs!$B$19+Inputs!$B$20+Inputs!$B$21+Inputs!$B$22+Inputs!$B$23+Inputs!$B$24)+E58*((((Inputs!$B$10*Inputs!$B$15+Inputs!$B$11*Inputs!$B$16)*(1-Inputs!$B$14)+(Inputs!$B$10*Inputs!$B$17+Inputs!$B$11*Inputs!$B$18)*Inputs!$B$14)/1000000*Inputs!$B$12)*$B$11+Inputs!$B$12*Inputs!$B$13)+(E55*$D$19)*Inputs!$B$25*Inputs!$B$26+((E55*$D$19)*Inputs!$B$8*$B$13)*Inputs!$B$27*Inputs!$B$28+E56*(Inputs!$B$29+Inputs!$B$31)+E54*Inputs!$B$30+E55*Inputs!$B$32 -> 41.249884 | F59: =F57/1000*(Inputs!$B$19+Inputs!$B$20+Inputs!$B$21+Inputs!$B$22+Inputs!$B$23+Inputs!$B$24)+F58*((((Inputs!$B$10*Inputs!$B$15+Inputs!$B$11*Inputs!$B$16)*(1-Inputs!$B$14)+(Inputs!$B$10*Inputs!$B$17+Inputs!$B$11*Inputs!$B$18)*Inputs!$B$14)/1000000*Inputs!$B$12)*$B$11+Inputs!$B$12*Inputs!$B$13)+(F55*$D$19)*Inputs!$B$25*Inputs!$B$26+((F55*$D$19)*Inputs!$B$8*$B$13)*Inputs!$B$27*Inputs!$B$28+F56*(Inputs!$B$29+Inputs!$B$31)+F54*Inputs!$B$30+F55*Inputs!$B$32 -> 48.13111 | G59: =G57/1000*(Inputs!$B$19+Inputs!$B$20+Inputs!$B$21+Inputs!$B$22+Inputs!$B$23+Inputs!$B$24)+G58*((((Inputs!$B$10*Inputs!$B$15+Inputs!$B$11*Inputs!$B$16)*(1-Inputs!$B$14)+(Inputs!$B$10*Inputs!$B$17+Inputs!$B$11*Inputs!$B$18)*Inputs!$B$14)/1000000*Inputs!$B$12)*$B$11+Inputs!$B$12*Inputs!$B$13)+(G55*$D$19)*Inputs!$B$25*Inputs!$B$26+((G55*$D$19)*Inputs!$B$8*$B$13)*Inputs!$B$27*Inputs!$B$28+G56*(Inputs!$B$29+Inputs!$B$31)+G54*Inputs!$B$30+G55*Inputs!$B$32 -> 63.959759 | H59: =H57/1000*(Inputs!$B$19+Inputs!$B$20+Inputs!$B$21+Inputs!$B$22+Inputs!$B$23+Inputs!$B$24)+H58*((((Inputs!$B$10*Inputs!$B$15+Inputs!$B$11*Inputs!$B$16)*(1-Inputs!$B$14)+(Inputs!$B$10*Inputs!$B$17+Inputs!$B$11*Inputs!$B$18)*Inputs!$B$14)/1000000*Inputs!$B$12)*$B$11+Inputs!$B$12*Inputs!$B$13)+(H55*$D$19)*Inputs!$B$25*Inputs!$B$26+((H55*$D$19)*Inputs!$B$8*$B$13)*Inputs!$B$27*Inputs!$B$28+H56*(Inputs!$B$29+Inputs!$B$31)+H54*Inputs!$B$30+H55*Inputs!$B$32 -> 73.078823 | I59: =I57/1000*(Inputs!$B$19+Inputs!$B$20+Inputs!$B$21+Inputs!$B$22+Inputs!$B$23+Inputs!$B$24)+I58*((((Inputs!$B$10*Inputs!$B$15+Inputs!$B$11*Inputs!$B$16)*(1-Inputs!$B$14)+(Inputs!$B$10*Inputs!$B$17+Inputs!$B$11*Inputs!$B$18)*Inputs!$B$14)/1000000*Inputs!$B$12)*$B$11+Inputs!$B$12*Inputs!$B$13)+(I55*$D$19)*Inputs!$B$25*Inputs!$B$26+((I55*$D$19)*Inputs!$B$8*$B$13)*Inputs!$B$27*Inputs!$B$28+I56*(Inputs!$B$29+Inputs!$B$31)+I54*Inputs!$B$30+I55*Inputs!$B$32 -> 86.500509 | ... M59: =M57/1000*(Inputs!$B$19+Inputs!$B$20+Inputs!$B$21+Inputs!$B$22+Inputs!$B$23+Inputs!$B$24)+M58*((((Inputs!$B$10*Inputs!$B$15+Inputs!$B$11*Inputs!$B$16)*(1-Inputs!$B$14)+(Inputs!$B$10*Inputs!$B$17+Inputs!$B$11*Inputs!$B$18)*Inputs!$B$14)/1000000*Inputs!$B$12)*$B$11+Inputs!$B$12*Inputs!$B$13)+(M55*$D$19)*Inputs!$B$25*Inputs!$B$26+((M55*$D$19)*Inputs!$B$8*$B$13)*Inputs!$B$27*Inputs!$B$28+M56*(Inputs!$B$29+Inputs!$B$31)+M54*Inputs!$B$30+M55*Inputs!$B$32 -> 128.55397
A61: Business | Opening accounts | B61: =0 -> 0 | C61: =B64 -> 0.096 | D61: =C64 -> 0.19008 | E61: =D64 -> 0.2826144 | F61: =E64 -> 0.37396339 | G61: =F64 -> 0.46447455 | H61: =G64 -> 0.55448437 | I61: =H64 -> 0.64431964 | J61: =I64 -> 0.73429891 | ... M61: =L64 -> 1.0081886
A62: Business | New accounts | B62: =B27*$C$20 -> 0.096 | C62: =C27*$C$20 -> 0.1008 | D62: =D27*$C$20 -> 0.10584 | E62: =E27*$C$20 -> 0.111132 | F62: =F27*$C$20 -> 0.1166886 | G62: =G27*$C$20 -> 0.12252303 | H62: =H27*$C$20 -> 0.12864918 | I62: =I27*$C$20 -> 0.13508164 | ... M62: =M27*$C$20 -> 0.16419258
A63: Business | Churned accounts | B63: =B61*$B$7 -> 0 | C63: =C61*$B$7 -> 0.00672 | D63: =D61*$B$7 -> 0.0133056 | E63: =E61*$B$7 -> 0.019783008 | F63: =F61*$B$7 -> 0.026177437 | G63: =G61*$B$7 -> 0.032513219 | H63: =H61*$B$7 -> 0.038813906 | I63: =I61*$B$7 -> 0.045102375 | ... M63: =M61*$B$7 -> 0.070573205
A64: Business | Ending accounts | B64: =B61+B62-B63 -> 0.096 | C64: =C61+C62-C63 -> 0.19008 | D64: =D61+D62-D63 -> 0.2826144 | E64: =E61+E62-E63 -> 0.37396339 | F64: =F61+F62-F63 -> 0.46447455 | G64: =G61+G62-G63 -> 0.55448437 | H64: =H61+H62-H63 -> 0.64431964 | I64: =I61+I62-I63 -> 0.73429891 | ... M64: =M61+M62-M63 -> 1.101808
A65: Business | Average accounts | B65: =(B61+B64)/2 -> 0.048 | C65: =(C61+C64)/2 -> 0.14304 | D65: =(D61+D64)/2 -> 0.2363472 | E65: =(E61+E64)/2 -> 0.3282889 | F65: =(F61+F64)/2 -> 0.41921897 | G65: =(G61+G64)/2 -> 0.50947946 | H65: =(H61+H64)/2 -> 0.599402 | I65: =(I61+I64)/2 -> 0.68930927 | ... M65: =(M61+M64)/2 -> 1.0549983
A66: Business | Revenue | B66: =B65*$B$20 -> 4.752 | C66: =C65*$B$20 -> 14.16096 | D66: =D65*$B$20 -> 23.398373 | E66: =E65*$B$20 -> 32.500601 | F66: =F65*$B$20 -> 41.502678 | G66: =G65*$B$20 -> 50.438467 | H66: =H65*$B$20 -> 59.340798 | I66: =I65*$B$20 -> 68.241618 | ... M66: =M65*$B$20 -> 104.44484
A67: Business | Monitoring checks | B67: =(B65*$D$20)*DAY(EOMONTH(B$25,0))*1440/$E$20*$B$12 -> 12856.32 | C67: =(C65*$D$20)*DAY(EOMONTH(C$25,0))*1440/$E$20*$B$12 -> 37075.968 | D67: =(D65*$D$20)*DAY(EOMONTH(D$25,0))*1440/$E$20*$B$12 -> 63303.234 | E67: =(E65*$D$20)*DAY(EOMONTH(E$25,0))*1440/$E$20*$B$12 -> 87928.898 | F67: =(F65*$D$20)*DAY(EOMONTH(F$25,0))*1440/$E$20*$B$12 -> 101417.45 | G67: =(G65*$D$20)*DAY(EOMONTH(G$25,0))*1440/$E$20*$B$12 -> 136458.98 | H67: =(H65*$D$20)*DAY(EOMONTH(H$25,0))*1440/$E$20*$B$12 -> 155365 | I67: =(I65*$D$20)*DAY(EOMONTH(I$25,0))*1440/$E$20*$B$12 -> 184624.6 | ... M67: =(M65*$D$20)*DAY(EOMONTH(M$25,0))*1440/$E$20*$B$12 -> 273455.57
A68: Business | AI diagnoses | B68: =(B65*$D$20)*Inputs!$B$8*$B$13*Inputs!$B$9*$F$20 -> 0.3456 | C68: =(C65*$D$20)*Inputs!$B$8*$B$13*Inputs!$B$9*$F$20 -> 1.029888 | D68: =(D65*$D$20)*Inputs!$B$8*$B$13*Inputs!$B$9*$F$20 -> 1.7016998 | E68: =(E65*$D$20)*Inputs!$B$8*$B$13*Inputs!$B$9*$F$20 -> 2.3636801 | F68: =(F65*$D$20)*Inputs!$B$8*$B$13*Inputs!$B$9*$F$20 -> 3.0183766 | G68: =(G65*$D$20)*Inputs!$B$8*$B$13*Inputs!$B$9*$F$20 -> 3.6682521 | H68: =(H65*$D$20)*Inputs!$B$8*$B$13*Inputs!$B$9*$F$20 -> 4.3156944 | I68: =(I65*$D$20)*Inputs!$B$8*$B$13*Inputs!$B$9*$F$20 -> 4.9630268 | ... M68: =(M65*$D$20)*Inputs!$B$8*$B$13*Inputs!$B$9*$F$20 -> 7.595988
A69: Business | Variable service expense | B69: =B67/1000*(Inputs!$B$19+Inputs!$B$20+Inputs!$B$21+Inputs!$B$22+Inputs!$B$23+Inputs!$B$24)+B68*((((Inputs!$B$10*Inputs!$B$15+Inputs!$B$11*Inputs!$B$16)*(1-Inputs!$B$14)+(Inputs!$B$10*Inputs!$B$17+Inputs!$B$11*Inputs!$B$18)*Inputs!$B$14)/1000000*Inputs!$B$12)*$B$11+Inputs!$B$12*Inputs!$B$13)+(B65*$D$20)*Inputs!$B$25*Inputs!$B$26+((B65*$D$20)*Inputs!$B$8*$B$13)*Inputs!$B$27*Inputs!$B$28+B66*(Inputs!$B$29+Inputs!$B$31)+B64*Inputs!$B$30+B65*Inputs!$B$32 -> 2.4196577 | C69: =C67/1000*(Inputs!$B$19+Inputs!$B$20+Inputs!$B$21+Inputs!$B$22+Inputs!$B$23+Inputs!$B$24)+C68*((((Inputs!$B$10*Inputs!$B$15+Inputs!$B$11*Inputs!$B$16)*(1-Inputs!$B$14)+(Inputs!$B$10*Inputs!$B$17+Inputs!$B$11*Inputs!$B$18)*Inputs!$B$14)/1000000*Inputs!$B$12)*$B$11+Inputs!$B$12*Inputs!$B$13)+(C65*$D$20)*Inputs!$B$25*Inputs!$B$26+((C65*$D$20)*Inputs!$B$8*$B$13)*Inputs!$B$27*Inputs!$B$28+C66*(Inputs!$B$29+Inputs!$B$31)+C64*Inputs!$B$30+C65*Inputs!$B$32 -> 6.9716829 | D69: =D67/1000*(Inputs!$B$19+Inputs!$B$20+Inputs!$B$21+Inputs!$B$22+Inputs!$B$23+Inputs!$B$24)+D68*((((Inputs!$B$10*Inputs!$B$15+Inputs!$B$11*Inputs!$B$16)*(1-Inputs!$B$14)+(Inputs!$B$10*Inputs!$B$17+Inputs!$B$11*Inputs!$B$18)*Inputs!$B$14)/1000000*Inputs!$B$12)*$B$11+Inputs!$B$12*Inputs!$B$13)+(D65*$D$20)*Inputs!$B$25*Inputs!$B$26+((D65*$D$20)*Inputs!$B$8*$B$13)*Inputs!$B$27*Inputs!$B$28+D66*(Inputs!$B$29+Inputs!$B$31)+D64*Inputs!$B$30+D65*Inputs!$B$32 -> 11.857129 | E69: =E67/1000*(Inputs!$B$19+Inputs!$B$20+Inputs!$B$21+Inputs!$B$22+Inputs!$B$23+Inputs!$B$24)+E68*((((Inputs!$B$10*Inputs!$B$15+Inputs!$B$11*Inputs!$B$16)*(1-Inputs!$B$14)+(Inputs!$B$10*Inputs!$B$17+Inputs!$B$11*Inputs!$B$18)*Inputs!$B$14)/1000000*Inputs!$B$12)*$B$11+Inputs!$B$12*Inputs!$B$13)+(E65*$D$20)*Inputs!$B$25*Inputs!$B$26+((E65*$D$20)*Inputs!$B$8*$B$13)*Inputs!$B$27*Inputs!$B$28+E66*(Inputs!$B$29+Inputs!$B$31)+E64*Inputs!$B$30+E65*Inputs!$B$32 -> 16.464107 | F69: =F67/1000*(Inputs!$B$19+Inputs!$B$20+Inputs!$B$21+Inputs!$B$22+Inputs!$B$23+Inputs!$B$24)+F68*((((Inputs!$B$10*Inputs!$B$15+Inputs!$B$11*Inputs!$B$16)*(1-Inputs!$B$14)+(Inputs!$B$10*Inputs!$B$17+Inputs!$B$11*Inputs!$B$18)*Inputs!$B$14)/1000000*Inputs!$B$12)*$B$11+Inputs!$B$12*Inputs!$B$13)+(F65*$D$20)*Inputs!$B$25*Inputs!$B$26+((F65*$D$20)*Inputs!$B$8*$B$13)*Inputs!$B$27*Inputs!$B$28+F66*(Inputs!$B$29+Inputs!$B$31)+F64*Inputs!$B$30+F65*Inputs!$B$32 -> 19.173198 | G69: =G67/1000*(Inputs!$B$19+Inputs!$B$20+Inputs!$B$21+Inputs!$B$22+Inputs!$B$23+Inputs!$B$24)+G68*((((Inputs!$B$10*Inputs!$B$15+Inputs!$B$11*Inputs!$B$16)*(1-Inputs!$B$14)+(Inputs!$B$10*Inputs!$B$17+Inputs!$B$11*Inputs!$B$18)*Inputs!$B$14)/1000000*Inputs!$B$12)*$B$11+Inputs!$B$12*Inputs!$B$13)+(G65*$D$20)*Inputs!$B$25*Inputs!$B$26+((G65*$D$20)*Inputs!$B$8*$B$13)*Inputs!$B$27*Inputs!$B$28+G66*(Inputs!$B$29+Inputs!$B$31)+G64*Inputs!$B$30+G65*Inputs!$B$32 -> 25.543281 | H69: =H67/1000*(Inputs!$B$19+Inputs!$B$20+Inputs!$B$21+Inputs!$B$22+Inputs!$B$23+Inputs!$B$24)+H68*((((Inputs!$B$10*Inputs!$B$15+Inputs!$B$11*Inputs!$B$16)*(1-Inputs!$B$14)+(Inputs!$B$10*Inputs!$B$17+Inputs!$B$11*Inputs!$B$18)*Inputs!$B$14)/1000000*Inputs!$B$12)*$B$11+Inputs!$B$12*Inputs!$B$13)+(H65*$D$20)*Inputs!$B$25*Inputs!$B$26+((H65*$D$20)*Inputs!$B$8*$B$13)*Inputs!$B$27*Inputs!$B$28+H66*(Inputs!$B$29+Inputs!$B$31)+H64*Inputs!$B$30+H65*Inputs!$B$32 -> 29.16883 | I69: =I67/1000*(Inputs!$B$19+Inputs!$B$20+Inputs!$B$21+Inputs!$B$22+Inputs!$B$23+Inputs!$B$24)+I68*((((Inputs!$B$10*Inputs!$B$15+Inputs!$B$11*Inputs!$B$16)*(1-Inputs!$B$14)+(Inputs!$B$10*Inputs!$B$17+Inputs!$B$11*Inputs!$B$18)*Inputs!$B$14)/1000000*Inputs!$B$12)*$B$11+Inputs!$B$12*Inputs!$B$13)+(I65*$D$20)*Inputs!$B$25*Inputs!$B$26+((I65*$D$20)*Inputs!$B$8*$B$13)*Inputs!$B$27*Inputs!$B$28+I66*(Inputs!$B$29+Inputs!$B$31)+I64*Inputs!$B$30+I65*Inputs!$B$32 -> 34.554465 | ... M69: =M67/1000*(Inputs!$B$19+Inputs!$B$20+Inputs!$B$21+Inputs!$B$22+Inputs!$B$23+Inputs!$B$24)+M68*((((Inputs!$B$10*Inputs!$B$15+Inputs!$B$11*Inputs!$B$16)*(1-Inputs!$B$14)+(Inputs!$B$10*Inputs!$B$17+Inputs!$B$11*Inputs!$B$18)*Inputs!$B$14)/1000000*Inputs!$B$12)*$B$11+Inputs!$B$12*Inputs!$B$13)+(M65*$D$20)*Inputs!$B$25*Inputs!$B$26+((M65*$D$20)*Inputs!$B$8*$B$13)*Inputs!$B$27*Inputs!$B$28+M66*(Inputs!$B$29+Inputs!$B$31)+M64*Inputs!$B$30+M65*Inputs!$B$32 -> 51.329938
A73: Paying customers ending | B73: =B44+B54+B64 -> 3.2 | C73: =C44+C54+C64 -> 6.336 | D73: =D44+D54+D64 -> 9.42048 | E73: =E44+E54+E64 -> 12.465446 | F73: =F44+F54+F64 -> 15.482485 | G73: =G44+G54+G64 -> 18.482812 | H73: =H44+H54+H64 -> 21.477321 | I73: =I44+I54+I64 -> 24.47663 | ... M73: =M44+M54+M64 -> 36.726934
A74: Paying customers average | B74: =B45+B55+B65 -> 1.6 | C74: =C45+C55+C65 -> 4.768 | D74: =D45+D55+D65 -> 7.87824 | E74: =E45+E55+E65 -> 10.942963 | F74: =F45+F55+F65 -> 13.973966 | G74: =G45+G55+G65 -> 16.982649 | H74: =H45+H55+H65 -> 19.980067 | I74: =I45+I55+I65 -> 22.976976 | ... M74: =M45+M55+M65 -> 35.166611
A75: Free customers ending | B75: =B34 -> 76.8 | C75: =C34 -> 142.08 | D75: =D34 -> 198.336 | E75: =E34 -> 247.5744 | F75: =F34 -> 291.4104 | G75: =G34 -> 331.14674 | H75: =H34 -> 367.83674 | I75: =I34 -> 402.3347 | ... M75: =M34 -> 530.57644
A76: Exit MRR | B76: =B44*$B$18+B54*$B$19+B64*$B$20 -> 51.52 | C76: =C44*$B$18+C54*$B$19+C64*$B$20 -> 102.0096 | D76: =D44*$B$18+D54*$B$19+D64*$B$20 -> 151.66973 | E76: =E44*$B$18+E54*$B$19+E64*$B$20 -> 200.69369 | F76: =F44*$B$18+F54*$B$19+F64*$B$20 -> 249.26801 | G76: =G44*$B$18+G54*$B$19+G64*$B$20 -> 297.57328 | H76: =H44*$B$18+H54*$B$19+H64*$B$20 -> 345.78487 | I76: =I44*$B$18+I54*$B$19+I64*$B$20 -> 394.07375 | ... M76: =M44*$B$18+M54*$B$19+M64*$B$20 -> 591.30364
A77: Revenue | B77: =B36+B46+B56+B66 -> 25.76 | C77: =C36+C46+C56+C66 -> 76.7648 | D77: =D36+D46+D56+D66 -> 126.83966 | E77: =E36+E46+E56+E66 -> 176.18171 | F77: =F36+F46+F56+F66 -> 224.98085 | G77: =G36+G46+G56+G66 -> 273.42064 | H77: =H36+H46+H56+H66 -> 321.67908 | I77: =I36+I46+I56+I66 -> 369.92931 | ... M77: =M36+M46+M56+M66 -> 566.18244
A78: Monitoring checks | B78: =B37+B47+B57+B67 -> 190702.08 | C78: =C37+C47+C57+C67 -> 535583.23 | D78: =D37+D47+D57+D67 -> 882841.57 | E78: =E37+E47+E57+E67 -> 1186203.1 | F78: =F37+F47+F57+F67 -> 1327266 | G78: =G37+G47+G57+G67 -> 1737537.8 | H78: =H37+H47+H57+H67 -> 1930094.8 | I78: =I37+I47+I57+I67 -> 2243505.8 | ... M78: =M37+M47+M57+M67 -> 3108171.8
A79: AI diagnoses | B79: =B38+B48+B58+B68 -> 2.0544 | C79: =C38+C48+C58+C68 -> 6.122112 | D79: =D38+D48+D58+D68 -> 10.11566 | E79: =E38+E48+E58+E68 -> 14.050765 | F79: =F38+F48+F58+F68 -> 17.942572 | G79: =G38+G48+G58+G68 -> 21.805721 | H79: =H38+H48+H58+H68 -> 25.654406 | I79: =I38+I48+I58+I68 -> 29.502437 | ... M79: =M38+M48+M58+M68 -> 45.153929
A80: Variable cost of revenue | B80: =B39+B49+B59+B69 -> 35.274934 | C80: =C39+C49+C59+C69 -> 98.584802 | D80: =D39+D49+D59+D69 -> 162.19002 | E80: =E39+E49+E59+E69 -> 218.24762 | F80: =F39+F49+F59+F69 -> 246.65098 | G80: =G39+G49+G59+G69 -> 320.77661 | H80: =H39+H49+H59+H69 -> 357.86638 | I80: =I39+I49+I59+I69 -> 415.49485 | ... M80: =M39+M49+M59+M69 -> 580.14875
A81: Fixed platform cost | B81: =Inputs!$B$33+Inputs!$B$34+Inputs!$B$35+Inputs!$B$36+Inputs!$B$37+Inputs!$B$38+Inputs!$B$39 -> 100 | C81: =Inputs!$B$33+Inputs!$B$34+Inputs!$B$35+Inputs!$B$36+Inputs!$B$37+Inputs!$B$38+Inputs!$B$39 -> 100 | D81: =Inputs!$B$33+Inputs!$B$34+Inputs!$B$35+Inputs!$B$36+Inputs!$B$37+Inputs!$B$38+Inputs!$B$39 -> 100 | E81: =Inputs!$B$33+Inputs!$B$34+Inputs!$B$35+Inputs!$B$36+Inputs!$B$37+Inputs!$B$38+Inputs!$B$39 -> 100 | F81: =Inputs!$B$33+Inputs!$B$34+Inputs!$B$35+Inputs!$B$36+Inputs!$B$37+Inputs!$B$38+Inputs!$B$39 -> 100 | G81: =Inputs!$B$33+Inputs!$B$34+Inputs!$B$35+Inputs!$B$36+Inputs!$B$37+Inputs!$B$38+Inputs!$B$39 -> 100 | H81: =Inputs!$B$33+Inputs!$B$34+Inputs!$B$35+Inputs!$B$36+Inputs!$B$37+Inputs!$B$38+Inputs!$B$39 -> 100 | I81: =Inputs!$B$33+Inputs!$B$34+Inputs!$B$35+Inputs!$B$36+Inputs!$B$37+Inputs!$B$38+Inputs!$B$39 -> 100 | ... M81: =Inputs!$B$33+Inputs!$B$34+Inputs!$B$35+Inputs!$B$36+Inputs!$B$37+Inputs!$B$38+Inputs!$B$39 -> 100
A82: Capacity scaling cost | B82: =MAX(0,ROUNDUP((B35*$D$17+B45*$D$18+B55*$D$19+B65*$D$20)/Inputs!$B$40,0)-1)*Inputs!$B$41 -> 0 | C82: =MAX(0,ROUNDUP((C35*$D$17+C45*$D$18+C55*$D$19+C65*$D$20)/Inputs!$B$40,0)-1)*Inputs!$B$41 -> 0 | D82: =MAX(0,ROUNDUP((D35*$D$17+D45*$D$18+D55*$D$19+D65*$D$20)/Inputs!$B$40,0)-1)*Inputs!$B$41 -> 0 | E82: =MAX(0,ROUNDUP((E35*$D$17+E45*$D$18+E55*$D$19+E65*$D$20)/Inputs!$B$40,0)-1)*Inputs!$B$41 -> 0 | F82: =MAX(0,ROUNDUP((F35*$D$17+F45*$D$18+F55*$D$19+F65*$D$20)/Inputs!$B$40,0)-1)*Inputs!$B$41 -> 0 | G82: =MAX(0,ROUNDUP((G35*$D$17+G45*$D$18+G55*$D$19+G65*$D$20)/Inputs!$B$40,0)-1)*Inputs!$B$41 -> 0 | H82: =MAX(0,ROUNDUP((H35*$D$17+H45*$D$18+H55*$D$19+H65*$D$20)/Inputs!$B$40,0)-1)*Inputs!$B$41 -> 0 | I82: =MAX(0,ROUNDUP((I35*$D$17+I45*$D$18+I55*$D$19+I65*$D$20)/Inputs!$B$40,0)-1)*Inputs!$B$41 -> 100 | ... M82: =MAX(0,ROUNDUP((M35*$D$17+M45*$D$18+M55*$D$19+M65*$D$20)/Inputs!$B$40,0)-1)*Inputs!$B$41 -> 100
A83: Total cost of revenue | B83: =B80+B81+B82 -> 135.27493 | C83: =C80+C81+C82 -> 198.5848 | D83: =D80+D81+D82 -> 262.19002 | E83: =E80+E81+E82 -> 318.24762 | F83: =F80+F81+F82 -> 346.65098 | G83: =G80+G81+G82 -> 420.77661 | H83: =H80+H81+H82 -> 457.86638 | I83: =I80+I81+I82 -> 615.49485 | ... M83: =M80+M81+M82 -> 780.14875
A84: Gross profit | B84: =B77-B83 -> -109.51493 | C84: =C77-C83 -> -121.82 | D84: =D77-D83 -> -135.35036 | E84: =E77-E83 -> -142.06591 | F84: =F77-F83 -> -121.67013 | G84: =G77-G83 -> -147.35597 | H84: =H77-H83 -> -136.1873 | I84: =I77-I83 -> -245.56554 | ... M84: =M77-M83 -> -213.96631
A85: Gross margin | B85: =IFERROR(B84/B77,0) -> -4.2513561 | C85: =IFERROR(C84/C77,0) -> -1.5869253 | D85: =IFERROR(D84/D77,0) -> -1.0670981 | E85: =IFERROR(E84/E77,0) -> -0.80636015 | F85: =IFERROR(F84/F77,0) -> -0.54080217 | G85: =IFERROR(G84/G77,0) -> -0.53893505 | H85: =IFERROR(H84/H77,0) -> -0.42336388 | I85: =IFERROR(I84/I77,0) -> -0.66381747 | ... M85: =IFERROR(M84/M77,0) -> -0.37791054
A86: Acquisition expense | B86: =B27*$B$9 -> 192 | C86: =C27*$B$9 -> 201.6 | D86: =D27*$B$9 -> 211.68 | E86: =E27*$B$9 -> 222.264 | F86: =F27*$B$9 -> 233.3772 | G86: =G27*$B$9 -> 245.04606 | H86: =H27*$B$9 -> 257.29836 | I86: =I27*$B$9 -> 270.16328 | ... M86: =M27*$B$9 -> 328.38516
A87: Contractors | B87: =IF(COLUMN()-1>=Inputs!$B$44,Inputs!$B$43,0) -> 0 | C87: =IF(COLUMN()-1>=Inputs!$B$44,Inputs!$B$43,0) -> 0 | D87: =IF(COLUMN()-1>=Inputs!$B$44,Inputs!$B$43,0) -> 0 | E87: =IF(COLUMN()-1>=Inputs!$B$44,Inputs!$B$43,0) -> 1500 | F87: =IF(COLUMN()-1>=Inputs!$B$44,Inputs!$B$43,0) -> 1500 | G87: =IF(COLUMN()-1>=Inputs!$B$44,Inputs!$B$43,0) -> 1500 | H87: =IF(COLUMN()-1>=Inputs!$B$44,Inputs!$B$43,0) -> 1500 | I87: =IF(COLUMN()-1>=Inputs!$B$44,Inputs!$B$43,0) -> 1500 | ... M87: =IF(COLUMN()-1>=Inputs!$B$44,Inputs!$B$43,0) -> 1500
A88: Staff | B88: =IF(COLUMN()-1>=Inputs!$B$46,$B$10,0) -> 0 | C88: =IF(COLUMN()-1>=Inputs!$B$46,$B$10,0) -> 0 | D88: =IF(COLUMN()-1>=Inputs!$B$46,$B$10,0) -> 0 | E88: =IF(COLUMN()-1>=Inputs!$B$46,$B$10,0) -> 0 | F88: =IF(COLUMN()-1>=Inputs!$B$46,$B$10,0) -> 0 | G88: =IF(COLUMN()-1>=Inputs!$B$46,$B$10,0) -> 0 | H88: =IF(COLUMN()-1>=Inputs!$B$46,$B$10,0) -> 0 | I88: =IF(COLUMN()-1>=Inputs!$B$46,$B$10,0) -> 0 | ... M88: =IF(COLUMN()-1>=Inputs!$B$46,$B$10,0) -> 3000
A89: Founder pay | B89: =Inputs!$B$47 -> 0 | C89: =Inputs!$B$47 -> 0 | D89: =Inputs!$B$47 -> 0 | E89: =Inputs!$B$47 -> 0 | F89: =Inputs!$B$47 -> 0 | G89: =Inputs!$B$47 -> 0 | H89: =Inputs!$B$47 -> 0 | I89: =Inputs!$B$47 -> 0 | ... M89: =Inputs!$B$47 -> 0
A90: Administration | B90: =Inputs!$B$42 -> 150 | C90: =Inputs!$B$42 -> 150 | D90: =Inputs!$B$42 -> 150 | E90: =Inputs!$B$42 -> 150 | F90: =Inputs!$B$42 -> 150 | G90: =Inputs!$B$42 -> 150 | H90: =Inputs!$B$42 -> 150 | I90: =Inputs!$B$42 -> 150 | ... M90: =Inputs!$B$42 -> 150
A91: Total operating expense | B91: =B86+B87+B88+B89+B90 -> 342 | C91: =C86+C87+C88+C89+C90 -> 351.6 | D91: =D86+D87+D88+D89+D90 -> 361.68 | E91: =E86+E87+E88+E89+E90 -> 1872.264 | F91: =F86+F87+F88+F89+F90 -> 1883.3772 | G91: =G86+G87+G88+G89+G90 -> 1895.0461 | H91: =H86+H87+H88+H89+H90 -> 1907.2984 | I91: =I86+I87+I88+I89+I90 -> 1920.1633 | ... M91: =M86+M87+M88+M89+M90 -> 4978.3852
A92: Operating profit / net cash flow | B92: =B84-B91 -> -451.51493 | C92: =C84-C91 -> -473.42 | D92: =D84-D91 -> -497.03036 | E92: =E84-E91 -> -2014.3299 | F92: =F84-F91 -> -2005.0473 | G92: =G84-G91 -> -2042.402 | H92: =H84-H91 -> -2043.4857 | I92: =I84-I91 -> -2165.7288 | ... M92: =M84-M91 -> -5192.3515
A93: Cumulative cash flow | B93: =0+B92 -> -451.51493 | C93: =B93+C92 -> -924.93494 | D93: =C93+D92 -> -1421.9653 | E93: =D93+E92 -> -3436.2952 | F93: =E93+F92 -> -5441.3425 | G93: =F93+G92 -> -7483.7446 | H93: =G93+H92 -> -9527.2302 | I93: =H93+I92 -> -11692.959 | J93: =I93+J92 -> -16855.993 | ... M93: =L93+M92 -> -32434.479
A94: Cash from editable starting cash | B94: =Inputs!$B$49+B93 -> 14548.485 | C94: =Inputs!$B$49+C93 -> 14075.065 | D94: =Inputs!$B$49+D93 -> 13578.035 | E94: =Inputs!$B$49+E93 -> 11563.705 | F94: =Inputs!$B$49+F93 -> 9558.6575 | G94: =Inputs!$B$49+G93 -> 7516.2554 | H94: =Inputs!$B$49+H93 -> 5472.7698 | I94: =Inputs!$B$49+I93 -> 3307.041 | ... M94: =Inputs!$B$49+M93 -> -17434.479
A95: Cash from $5k | B95: =Inputs!$B$54+B93 -> 4548.4851 | C95: =Inputs!$B$54+C93 -> 4075.0651 | D95: =Inputs!$B$54+D93 -> 3578.0347 | E95: =Inputs!$B$54+E93 -> 1563.7048 | F95: =Inputs!$B$54+F93 -> -441.34254 | G95: =Inputs!$B$54+G93 -> -2483.7446 | H95: =Inputs!$B$54+H93 -> -4527.2302 | I95: =Inputs!$B$54+I93 -> -6692.959 | ... M95: =Inputs!$B$54+M93 -> -27434.479
A96: Cash from $15k | B96: =Inputs!$B$55+B93 -> 14548.485 | C96: =Inputs!$B$55+C93 -> 14075.065 | D96: =Inputs!$B$55+D93 -> 13578.035 | E96: =Inputs!$B$55+E93 -> 11563.705 | F96: =Inputs!$B$55+F93 -> 9558.6575 | G96: =Inputs!$B$55+G93 -> 7516.2554 | H96: =Inputs!$B$55+H93 -> 5472.7698 | I96: =Inputs!$B$55+I93 -> 3307.041 | ... M96: =Inputs!$B$55+M93 -> -17434.479
A97: Cash from $30k | B97: =Inputs!$B$56+B93 -> 29548.485 | C97: =Inputs!$B$56+C93 -> 29075.065 | D97: =Inputs!$B$56+D93 -> 28578.035 | E97: =Inputs!$B$56+E93 -> 26563.705 | F97: =Inputs!$B$56+F93 -> 24558.657 | G97: =Inputs!$B$56+G93 -> 22516.255 | H97: =Inputs!$B$56+H93 -> 20472.77 | I97: =Inputs!$B$56+I93 -> 18307.041 | ... M97: =Inputs!$B$56+M93 -> -2434.4789
A98: ARPPU | B98: =IFERROR(B77/B74,0) -> 16.1 | C98: =IFERROR(C77/C74,0) -> 16.1 | D98: =IFERROR(D77/D74,0) -> 16.1 | E98: =IFERROR(E77/E74,0) -> 16.1 | F98: =IFERROR(F77/F74,0) -> 16.1 | G98: =IFERROR(G77/G74,0) -> 16.1 | H98: =IFERROR(H77/H74,0) -> 16.1 | I98: =IFERROR(I77/I74,0) -> 16.1 | ... M98: =IFERROR(M77/M74,0) -> 16.1
A99: ARPU all accounts | B99: =IFERROR(B77/(B35+B45+B55+B65),0) -> 0.644 | C99: =IFERROR(C77/(C35+C45+C55+C65),0) -> 0.67214906 | D99: =IFERROR(D77/(D35+D45+D55+D65),0) -> 0.71223731 | E99: =IFERROR(E77/(E35+E45+E55+E65),0) -> 0.75324109 | F99: =IFERROR(F77/(F35+F45+F55+F65),0) -> 0.7936774 | G99: =IFERROR(G77/(G35+G45+G55+G65),0) -> 0.83293617 | H99: =IFERROR(H77/(H35+H45+H55+H65),0) -> 0.87064579 | I99: =IFERROR(I77/(I35+I45+I55+I65),0) -> 0.90655017 | ... M99: =IFERROR(M77/(M35+M45+M55+M65),0) -> 1.029481
A100: Cost per average paying account | B100: =IFERROR(B83/B74,0) -> 84.546834 | C100: =IFERROR(C83/C74,0) -> 41.649497 | D100: =IFERROR(D83/D74,0) -> 33.280279 | E100: =IFERROR(E83/E74,0) -> 29.082398 | F100: =IFERROR(F83/F74,0) -> 24.806915 | G100: =IFERROR(G83/G74,0) -> 24.776854 | H100: =IFERROR(H83/H74,0) -> 22.916158 | I100: =IFERROR(I83/I74,0) -> 26.787461 | ... M100: =IFERROR(M83/M74,0) -> 22.18436
A101: Gross profit per average paying account | B101: =B98-B100 -> -68.446834 | C101: =C98-C100 -> -25.549497 | D101: =D98-D100 -> -17.180279 | E101: =E98-E100 -> -12.982398 | F101: =F98-F100 -> -8.7069149 | G101: =G98-G100 -> -8.6768543 | H101: =H98-H100 -> -6.8161584 | I101: =I98-I100 -> -10.687461 | ... M101: =M98-M100 -> -6.0843597
A102: LTV fully loaded | B102: =IF(B101>0,B101/$B$7,0) -> 0 | C102: =IF(C101>0,C101/$B$7,0) -> 0 | D102: =IF(D101>0,D101/$B$7,0) -> 0 | E102: =IF(E101>0,E101/$B$7,0) -> 0 | F102: =IF(F101>0,F101/$B$7,0) -> 0 | G102: =IF(G101>0,G101/$B$7,0) -> 0 | H102: =IF(H101>0,H101/$B$7,0) -> 0 | I102: =IF(I101>0,I101/$B$7,0) -> 0 | ... M102: =IF(M101>0,M101/$B$7,0) -> 0
A103: LTV to CAC fully loaded | B103: =IF(B101>0,B102/$B$9,0) -> 0 | C103: =IF(C101>0,C102/$B$9,0) -> 0 | D103: =IF(D101>0,D102/$B$9,0) -> 0 | E103: =IF(E101>0,E102/$B$9,0) -> 0 | F103: =IF(F101>0,F102/$B$9,0) -> 0 | G103: =IF(G101>0,G102/$B$9,0) -> 0 | H103: =IF(H101>0,H102/$B$9,0) -> 0 | I103: =IF(I101>0,I102/$B$9,0) -> 0 | ... M103: =IF(M101>0,M102/$B$9,0) -> 0
A104: CAC payback months | B104: =IF(B101>0,$B$9/B101,0) -> 0 | C104: =IF(C101>0,$B$9/C101,0) -> 0 | D104: =IF(D101>0,$B$9/D101,0) -> 0 | E104: =IF(E101>0,$B$9/E101,0) -> 0 | F104: =IF(F101>0,$B$9/F101,0) -> 0 | G104: =IF(G101>0,$B$9/G101,0) -> 0 | H104: =IF(H101>0,$B$9/H101,0) -> 0 | I104: =IF(I101>0,$B$9/I101,0) -> 0 | ... M104: =IF(M101>0,$B$9/M101,0) -> 0
A105: Cash bridge check | B105: =B94-Inputs!$B$49-B93 -> 0 | C105: =C94-Inputs!$B$49-C93 -> 0 | D105: =D94-Inputs!$B$49-D93 -> 0 | E105: =E94-Inputs!$B$49-E93 -> 0 | F105: =F94-Inputs!$B$49-F93 -> 0 | G105: =G94-Inputs!$B$49-G93 -> 0 | H105: =H94-Inputs!$B$49-H93 -> 0 | I105: =I94-Inputs!$B$49-I93 -> 0 | ... M105: =M94-Inputs!$B$49-M93 -> 0

Sheet Optimistic
A1: Optimistic — hypothetical 12-month forecast
A4: Initial monthly signups | B4: 300
A5: Monthly signup growth | B5: 0.15
A6: Paid conversion rate | B6: 0.12
A7: Monthly paid churn | B7: 0.025
A8: Monthly free churn | B8: 0.1
A9: Blended acquisition CAC | B9: 30
A10: Staff monthly budget | B10: =Inputs!$B$45 -> 3000
A11: AI cost stress multiplier | B11: =Inputs!$B$50 -> 1
A12: Monitoring frequency multiplier | B12: =Inputs!$B$51 -> 1
A13: Incident volume multiplier | B13: =Inputs!$B$52 -> 1
A17: Free | B17: =Pricing!B2 -> 0 | C17: =Pricing!C2 -> 0 | D17: =Pricing!D2 -> 1 | E17: =Pricing!E2 -> 15 | F17: =Pricing!F2 -> 0
A18: Starter | B18: =Pricing!B3 -> 9 | C18: 0.45 | D18: =Pricing!D3 -> 3 | E18: =Pricing!E3 -> 5 | F18: =Pricing!F3 -> 1
A19: Pro | B19: =Pricing!B4 -> 29 | C19: 0.4 | D19: =Pricing!D4 -> 10 | E19: =Pricing!E4 -> 5 | F19: =Pricing!F4 -> 1
A20: Business | B20: =Pricing!B5 -> 99 | C20: 0.15 | D20: =Pricing!D5 -> 30 | E20: =Pricing!E5 -> 5 | F20: =Pricing!F5 -> 1
B25: 46296 | C25: 46327 | D25: 46357 | E25: 46388 | F25: 46419 | G25: 46447 | H25: 46478 | I25: 46508 | J25: 46539 | K25: 46569 | L25: 46600 | M25: 46631
A26: New signups | B26: =$B$4 -> 300 | C26: =B26*(1+$B$5) -> 345 | D26: =C26*(1+$B$5) -> 396.75 | E26: =D26*(1+$B$5) -> 456.2625 | F26: =E26*(1+$B$5) -> 524.70187 | G26: =F26*(1+$B$5) -> 603.40716 | H26: =G26*(1+$B$5) -> 693.91823 | I26: =H26*(1+$B$5) -> 798.00596 | J26: =I26*(1+$B$5) -> 917.70686 | ... M26: =L26*(1+$B$5) -> 1395.7174
A27: New paid | B27: =B26*$B$6 -> 36 | C27: =C26*$B$6 -> 41.4 | D27: =D26*$B$6 -> 47.61 | E27: =E26*$B$6 -> 54.7515 | F27: =F26*$B$6 -> 62.964225 | G27: =G26*$B$6 -> 72.408859 | H27: =H26*$B$6 -> 83.270188 | I27: =I26*$B$6 -> 95.760716 | ... M27: =M26*$B$6 -> 167.48609
A28: New free | B28: =B26-B27 -> 264 | C28: =C26-C27 -> 303.6 | D28: =D26-D27 -> 349.14 | E28: =E26-E27 -> 401.511 | F28: =F26-F27 -> 461.73765 | G28: =G26-G27 -> 530.9983 | H28: =H26-H27 -> 610.64804 | I28: =I26-I27 -> 702.24525 | ... M28: =M26-M27 -> 1228.2313
A31: Free | Opening accounts | B31: =0 -> 0 | C31: =B34 -> 264 | D31: =C34 -> 541.2 | E31: =D34 -> 836.22 | F31: =E34 -> 1154.109 | G31: =F34 -> 1500.4358 | H31: =G34 -> 1881.3905 | I31: =H34 -> 2303.8995 | J31: =I34 -> 2775.7548 | ... M31: =L34 -> 4581.5413
A32: Free | New accounts | B32: =B28 -> 264 | C32: =C28 -> 303.6 | D32: =D28 -> 349.14 | E32: =E28 -> 401.511 | F32: =F28 -> 461.73765 | G32: =G28 -> 530.9983 | H32: =H28 -> 610.64804 | I32: =I28 -> 702.24525 | ... M32: =M28 -> 1228.2313
A33: Free | Churned accounts | B33: =B31*$B$8 -> 0 | C33: =C31*$B$8 -> 26.4 | D33: =D31*$B$8 -> 54.12 | E33: =E31*$B$8 -> 83.622 | F33: =F31*$B$8 -> 115.4109 | G33: =G31*$B$8 -> 150.04358 | H33: =H31*$B$8 -> 188.13905 | I33: =I31*$B$8 -> 230.38995 | ... M33: =M31*$B$8 -> 458.15413
A34: Free | Ending accounts | B34: =B31+B32-B33 -> 264 | C34: =C31+C32-C33 -> 541.2 | D34: =D31+D32-D33 -> 836.22 | E34: =E31+E32-E33 -> 1154.109 | F34: =F31+F32-F33 -> 1500.4358 | G34: =G31+G32-G33 -> 1881.3905 | H34: =H31+H32-H33 -> 2303.8995 | I34: =I31+I32-I33 -> 2775.7548 | ... M34: =M31+M32-M33 -> 5351.6185
A35: Free | Average accounts | B35: =(B31+B34)/2 -> 132 | C35: =(C31+C34)/2 -> 402.6 | D35: =(D31+D34)/2 -> 688.71 | E35: =(E31+E34)/2 -> 995.1645 | F35: =(F31+F34)/2 -> 1327.2724 | G35: =(G31+G34)/2 -> 1690.9131 | H35: =(H31+H34)/2 -> 2092.645 | I35: =(I31+I34)/2 -> 2539.8271 | ... M35: =(M31+M34)/2 -> 4966.5799
A36: Free | Revenue | B36: =B35*$B$17 -> 0 | C36: =C35*$B$17 -> 0 | D36: =D35*$B$17 -> 0 | E36: =E35*$B$17 -> 0 | F36: =F35*$B$17 -> 0 | G36: =G35*$B$17 -> 0 | H36: =H35*$B$17 -> 0 | I36: =I35*$B$17 -> 0 | ... M36: =M35*$B$17 -> 0
A37: Free | Monitoring checks | B37: =(B35*$D$17)*DAY(EOMONTH(B$25,0))*1440/$E$17*$B$12 -> 392832 | C37: =(C35*$D$17)*DAY(EOMONTH(C$25,0))*1440/$E$17*$B$12 -> 1159488 | D37: =(D35*$D$17)*DAY(EOMONTH(D$25,0))*1440/$E$17*$B$12 -> 2049601 | E37: =(E35*$D$17)*DAY(EOMONTH(E$25,0))*1440/$E$17*$B$12 -> 2961609.6 | F37: =(F35*$D$17)*DAY(EOMONTH(F$25,0))*1440/$E$17*$B$12 -> 3567708.1 | G37: =(G35*$D$17)*DAY(EOMONTH(G$25,0))*1440/$E$17*$B$12 -> 5032157.4 | H37: =(H35*$D$17)*DAY(EOMONTH(H$25,0))*1440/$E$17*$B$12 -> 6026817.5 | I37: =(I35*$D$17)*DAY(EOMONTH(I$25,0))*1440/$E$17*$B$12 -> 7558525.5 | ... M37: =(M35*$D$17)*DAY(EOMONTH(M$25,0))*1440/$E$17*$B$12 -> 14303750
A38: Free | AI diagnoses | B38: =(B35*$D$17)*Inputs!$B$8*$B$13*Inputs!$B$9*$F$17 -> 0 | C38: =(C35*$D$17)*Inputs!$B$8*$B$13*Inputs!$B$9*$F$17 -> 0 | D38: =(D35*$D$17)*Inputs!$B$8*$B$13*Inputs!$B$9*$F$17 -> 0 | E38: =(E35*$D$17)*Inputs!$B$8*$B$13*Inputs!$B$9*$F$17 -> 0 | F38: =(F35*$D$17)*Inputs!$B$8*$B$13*Inputs!$B$9*$F$17 -> 0 | G38: =(G35*$D$17)*Inputs!$B$8*$B$13*Inputs!$B$9*$F$17 -> 0 | H38: =(H35*$D$17)*Inputs!$B$8*$B$13*Inputs!$B$9*$F$17 -> 0 | I38: =(I35*$D$17)*Inputs!$B$8*$B$13*Inputs!$B$9*$F$17 -> 0 | ... M38: =(M35*$D$17)*Inputs!$B$8*$B$13*Inputs!$B$9*$F$17 -> 0
A39: Free | Variable service expense | B39: =B37/1000*(Inputs!$B$19+Inputs!$B$20+Inputs!$B$21+Inputs!$B$22+Inputs!$B$23+Inputs!$B$24)+B38*((((Inputs!$B$10*Inputs!$B$15+Inputs!$B$11*Inputs!$B$16)*(1-Inputs!$B$14)+(Inputs!$B$10*Inputs!$B$17+Inputs!$B$11*Inputs!$B$18)*Inputs!$B$14)/1000000*Inputs!$B$12)*$B$11+Inputs!$B$12*Inputs!$B$13)+(B35*$D$17)*Inputs!$B$25*Inputs!$B$26+((B35*$D$17)*Inputs!$B$8*$B$13)*Inputs!$B$27*Inputs!$B$28+B36*(Inputs!$B$29+Inputs!$B$31) -> 67.15104 | C39: =C37/1000*(Inputs!$B$19+Inputs!$B$20+Inputs!$B$21+Inputs!$B$22+Inputs!$B$23+Inputs!$B$24)+C38*((((Inputs!$B$10*Inputs!$B$15+Inputs!$B$11*Inputs!$B$16)*(1-Inputs!$B$14)+(Inputs!$B$10*Inputs!$B$17+Inputs!$B$11*Inputs!$B$18)*Inputs!$B$14)/1000000*Inputs!$B$12)*$B$11+Inputs!$B$12*Inputs!$B$13)+(C35*$D$17)*Inputs!$B$25*Inputs!$B$26+((C35*$D$17)*Inputs!$B$8*$B$13)*Inputs!$B$27*Inputs!$B$28+C36*(Inputs!$B$29+Inputs!$B$31) -> 198.24024 | D39: =D37/1000*(Inputs!$B$19+Inputs!$B$20+Inputs!$B$21+Inputs!$B$22+Inputs!$B$23+Inputs!$B$24)+D38*((((Inputs!$B$10*Inputs!$B$15+Inputs!$B$11*Inputs!$B$16)*(1-Inputs!$B$14)+(Inputs!$B$10*Inputs!$B$17+Inputs!$B$11*Inputs!$B$18)*Inputs!$B$14)/1000000*Inputs!$B$12)*$B$11+Inputs!$B$12*Inputs!$B$13)+(D35*$D$17)*Inputs!$B$25*Inputs!$B$26+((D35*$D$17)*Inputs!$B$8*$B$13)*Inputs!$B$27*Inputs!$B$28+D36*(Inputs!$B$29+Inputs!$B$31) -> 350.36055 | E39: =E37/1000*(Inputs!$B$19+Inputs!$B$20+Inputs!$B$21+Inputs!$B$22+Inputs!$B$23+Inputs!$B$24)+E38*((((Inputs!$B$10*Inputs!$B$15+Inputs!$B$11*Inputs!$B$16)*(1-Inputs!$B$14)+(Inputs!$B$10*Inputs!$B$17+Inputs!$B$11*Inputs!$B$18)*Inputs!$B$14)/1000000*Inputs!$B$12)*$B$11+Inputs!$B$12*Inputs!$B$13)+(E35*$D$17)*Inputs!$B$25*Inputs!$B$26+((E35*$D$17)*Inputs!$B$8*$B$13)*Inputs!$B$27*Inputs!$B$28+E36*(Inputs!$B$29+Inputs!$B$31) -> 506.26008 | F39: =F37/1000*(Inputs!$B$19+Inputs!$B$20+Inputs!$B$21+Inputs!$B$22+Inputs!$B$23+Inputs!$B$24)+F38*((((Inputs!$B$10*Inputs!$B$15+Inputs!$B$11*Inputs!$B$16)*(1-Inputs!$B$14)+(Inputs!$B$10*Inputs!$B$17+Inputs!$B$11*Inputs!$B$18)*Inputs!$B$14)/1000000*Inputs!$B$12)*$B$11+Inputs!$B$12*Inputs!$B$13)+(F35*$D$17)*Inputs!$B$25*Inputs!$B$26+((F35*$D$17)*Inputs!$B$8*$B$13)*Inputs!$B$27*Inputs!$B$28+F36*(Inputs!$B$29+Inputs!$B$31) -> 610.22675 | G39: =G37/1000*(Inputs!$B$19+Inputs!$B$20+Inputs!$B$21+Inputs!$B$22+Inputs!$B$23+Inputs!$B$24)+G38*((((Inputs!$B$10*Inputs!$B$15+Inputs!$B$11*Inputs!$B$16)*(1-Inputs!$B$14)+(Inputs!$B$10*Inputs!$B$17+Inputs!$B$11*Inputs!$B$18)*Inputs!$B$14)/1000000*Inputs!$B$12)*$B$11+Inputs!$B$12*Inputs!$B$13)+(G35*$D$17)*Inputs!$B$25*Inputs!$B$26+((G35*$D$17)*Inputs!$B$8*$B$13)*Inputs!$B$27*Inputs!$B$28+G36*(Inputs!$B$29+Inputs!$B$31) -> 860.20132 | H39: =H37/1000*(Inputs!$B$19+Inputs!$B$20+Inputs!$B$21+Inputs!$B$22+Inputs!$B$23+Inputs!$B$24)+H38*((((Inputs!$B$10*Inputs!$B$15+Inputs!$B$11*Inputs!$B$16)*(1-Inputs!$B$14)+(Inputs!$B$10*Inputs!$B$17+Inputs!$B$11*Inputs!$B$18)*Inputs!$B$14)/1000000*Inputs!$B$12)*$B$11+Inputs!$B$12*Inputs!$B$13)+(H35*$D$17)*Inputs!$B$25*Inputs!$B$26+((H35*$D$17)*Inputs!$B$8*$B$13)*Inputs!$B$27*Inputs!$B$28+H36*(Inputs!$B$29+Inputs!$B$31) -> 1030.4184 | I39: =I37/1000*(Inputs!$B$19+Inputs!$B$20+Inputs!$B$21+Inputs!$B$22+Inputs!$B$23+Inputs!$B$24)+I38*((((Inputs!$B$10*Inputs!$B$15+Inputs!$B$11*Inputs!$B$16)*(1-Inputs!$B$14)+(Inputs!$B$10*Inputs!$B$17+Inputs!$B$11*Inputs!$B$18)*Inputs!$B$14)/1000000*Inputs!$B$12)*$B$11+Inputs!$B$12*Inputs!$B$13)+(I35*$D$17)*Inputs!$B$25*Inputs!$B$26+((I35*$D$17)*Inputs!$B$8*$B$13)*Inputs!$B$27*Inputs!$B$28+I36*(Inputs!$B$29+Inputs!$B$31) -> 1292.0609 | ... M39: =M37/1000*(Inputs!$B$19+Inputs!$B$20+Inputs!$B$21+Inputs!$B$22+Inputs!$B$23+Inputs!$B$24)+M38*((((Inputs!$B$10*Inputs!$B$15+Inputs!$B$11*Inputs!$B$16)*(1-Inputs!$B$14)+(Inputs!$B$10*Inputs!$B$17+Inputs!$B$11*Inputs!$B$18)*Inputs!$B$14)/1000000*Inputs!$B$12)*$B$11+Inputs!$B$12*Inputs!$B$13)+(M35*$D$17)*Inputs!$B$25*Inputs!$B$26+((M35*$D$17)*Inputs!$B$8*$B$13)*Inputs!$B$27*Inputs!$B$28+M36*(Inputs!$B$29+Inputs!$B$31) -> 2445.544
A41: Starter | Opening accounts | B41: =0 -> 0 | C41: =B44 -> 16.2 | D41: =C44 -> 34.425 | E41: =D44 -> 54.988875 | F41: =E44 -> 78.252328 | G41: =F44 -> 104.62992 | H41: =G44 -> 134.59816 | I41: =H44 -> 168.70479 | J41: =I44 -> 207.57949 | ... M41: =L44 -> 360.60922
A42: Starter | New accounts | B42: =B27*$C$18 -> 16.2 | C42: =C27*$C$18 -> 18.63 | D42: =D27*$C$18 -> 21.4245 | E42: =E27*$C$18 -> 24.638175 | F42: =F27*$C$18 -> 28.333901 | G42: =G27*$C$18 -> 32.583986 | H42: =H27*$C$18 -> 37.471584 | I42: =I27*$C$18 -> 43.092322 | ... M42: =M27*$C$18 -> 75.368741
A43: Starter | Churned accounts | B43: =B41*$B$7 -> 0 | C43: =C41*$B$7 -> 0.405 | D43: =D41*$B$7 -> 0.860625 | E43: =E41*$B$7 -> 1.3747219 | F43: =F41*$B$7 -> 1.9563082 | G43: =G41*$B$7 -> 2.615748 | H43: =H41*$B$7 -> 3.364954 | I43: =I41*$B$7 -> 4.2176197 | ... M43: =M41*$B$7 -> 9.0152306
A44: Starter | Ending accounts | B44: =B41+B42-B43 -> 16.2 | C44: =C41+C42-C43 -> 34.425 | D44: =D41+D42-D43 -> 54.988875 | E44: =E41+E42-E43 -> 78.252328 | F44: =F41+F42-F43 -> 104.62992 | G44: =G41+G42-G43 -> 134.59816 | H44: =H41+H42-H43 -> 168.70479 | I44: =I41+I42-I43 -> 207.57949 | ... M44: =M41+M42-M43 -> 426.96273
A45: Starter | Average accounts | B45: =(B41+B44)/2 -> 8.1 | C45: =(C41+C44)/2 -> 25.3125 | D45: =(D41+D44)/2 -> 44.706938 | E45: =(E41+E44)/2 -> 66.620602 | F45: =(F41+F44)/2 -> 91.441125 | G45: =(G41+G44)/2 -> 119.61404 | H45: =(H41+H44)/2 -> 151.65147 | I45: =(I41+I44)/2 -> 188.14214 | ... M45: =(M41+M44)/2 -> 393.78598
A46: Starter | Revenue | B46: =B45*$B$18 -> 72.9 | C46: =C45*$B$18 -> 227.8125 | D46: =D45*$B$18 -> 402.36244 | E46: =E45*$B$18 -> 599.58541 | F46: =F45*$B$18 -> 822.97012 | G46: =G45*$B$18 -> 1076.5264 | H46: =H45*$B$18 -> 1364.8633 | I46: =I45*$B$18 -> 1693.2793 | ... M46: =M45*$B$18 -> 3544.0738
A47: Starter | Monitoring checks | B47: =(B45*$D$18)*DAY(EOMONTH(B$25,0))*1440/$E$18*$B$12 -> 216950.4 | C47: =(C45*$D$18)*DAY(EOMONTH(C$25,0))*1440/$E$18*$B$12 -> 656100 | D47: =(D45*$D$18)*DAY(EOMONTH(D$25,0))*1440/$E$18*$B$12 -> 1197430.6 | E47: =(E45*$D$18)*DAY(EOMONTH(E$25,0))*1440/$E$18*$B$12 -> 1784366.2 | F47: =(F45*$D$18)*DAY(EOMONTH(F$25,0))*1440/$E$18*$B$12 -> 2212143.7 | G47: =(G45*$D$18)*DAY(EOMONTH(G$25,0))*1440/$E$18*$B$12 -> 3203742.5 | H47: =(H45*$D$18)*DAY(EOMONTH(H$25,0))*1440/$E$18*$B$12 -> 3930806.2 | I47: =(I45*$D$18)*DAY(EOMONTH(I$25,0))*1440/$E$18*$B$12 -> 5039199.1 | ... M47: =(M45*$D$18)*DAY(EOMONTH(M$25,0))*1440/$E$18*$B$12 -> 10206933
A48: Starter | AI diagnoses | B48: =(B45*$D$18)*Inputs!$B$8*$B$13*Inputs!$B$9*$F$18 -> 5.832 | C48: =(C45*$D$18)*Inputs!$B$8*$B$13*Inputs!$B$9*$F$18 -> 18.225 | D48: =(D45*$D$18)*Inputs!$B$8*$B$13*Inputs!$B$9*$F$18 -> 32.188995 | E48: =(E45*$D$18)*Inputs!$B$8*$B$13*Inputs!$B$9*$F$18 -> 47.966833 | F48: =(F45*$D$18)*Inputs!$B$8*$B$13*Inputs!$B$9*$F$18 -> 65.83761 | G48: =(G45*$D$18)*Inputs!$B$8*$B$13*Inputs!$B$9*$F$18 -> 86.122109 | H48: =(H45*$D$18)*Inputs!$B$8*$B$13*Inputs!$B$9*$F$18 -> 109.18906 | I48: =(I45*$D$18)*Inputs!$B$8*$B$13*Inputs!$B$9*$F$18 -> 135.46234 | ... M48: =(M45*$D$18)*Inputs!$B$8*$B$13*Inputs!$B$9*$F$18 -> 283.52591
A49: Starter | Variable service expense | B49: =B47/1000*(Inputs!$B$19+Inputs!$B$20+Inputs!$B$21+Inputs!$B$22+Inputs!$B$23+Inputs!$B$24)+B48*((((Inputs!$B$10*Inputs!$B$15+Inputs!$B$11*Inputs!$B$16)*(1-Inputs!$B$14)+(Inputs!$B$10*Inputs!$B$17+Inputs!$B$11*Inputs!$B$18)*Inputs!$B$14)/1000000*Inputs!$B$12)*$B$11+Inputs!$B$12*Inputs!$B$13)+(B45*$D$18)*Inputs!$B$25*Inputs!$B$26+((B45*$D$18)*Inputs!$B$8*$B$13)*Inputs!$B$27*Inputs!$B$28+B46*(Inputs!$B$29+Inputs!$B$31)+B44*Inputs!$B$30+B45*Inputs!$B$32 -> 48.588284 | C49: =C47/1000*(Inputs!$B$19+Inputs!$B$20+Inputs!$B$21+Inputs!$B$22+Inputs!$B$23+Inputs!$B$24)+C48*((((Inputs!$B$10*Inputs!$B$15+Inputs!$B$11*Inputs!$B$16)*(1-Inputs!$B$14)+(Inputs!$B$10*Inputs!$B$17+Inputs!$B$11*Inputs!$B$18)*Inputs!$B$14)/1000000*Inputs!$B$12)*$B$11+Inputs!$B$12*Inputs!$B$13)+(C45*$D$18)*Inputs!$B$25*Inputs!$B$26+((C45*$D$18)*Inputs!$B$8*$B$13)*Inputs!$B$27*Inputs!$B$28+C46*(Inputs!$B$29+Inputs!$B$31)+C44*Inputs!$B$30+C45*Inputs!$B$32 -> 143.26049 | D49: =D47/1000*(Inputs!$B$19+Inputs!$B$20+Inputs!$B$21+Inputs!$B$22+Inputs!$B$23+Inputs!$B$24)+D48*((((Inputs!$B$10*Inputs!$B$15+Inputs!$B$11*Inputs!$B$16)*(1-Inputs!$B$14)+(Inputs!$B$10*Inputs!$B$17+Inputs!$B$11*Inputs!$B$18)*Inputs!$B$14)/1000000*Inputs!$B$12)*$B$11+Inputs!$B$12*Inputs!$B$13)+(D45*$D$18)*Inputs!$B$25*Inputs!$B$26+((D45*$D$18)*Inputs!$B$8*$B$13)*Inputs!$B$27*Inputs!$B$28+D46*(Inputs!$B$29+Inputs!$B$31)+D44*Inputs!$B$30+D45*Inputs!$B$32 -> 257.84946 | E49: =E47/1000*(Inputs!$B$19+Inputs!$B$20+Inputs!$B$21+Inputs!$B$22+Inputs!$B$23+Inputs!$B$24)+E48*((((Inputs!$B$10*Inputs!$B$15+Inputs!$B$11*Inputs!$B$16)*(1-Inputs!$B$14)+(Inputs!$B$10*Inputs!$B$17+Inputs!$B$11*Inputs!$B$18)*Inputs!$B$14)/1000000*Inputs!$B$12)*$B$11+Inputs!$B$12*Inputs!$B$13)+(E45*$D$18)*Inputs!$B$25*Inputs!$B$26+((E45*$D$18)*Inputs!$B$8*$B$13)*Inputs!$B$27*Inputs!$B$28+E46*(Inputs!$B$29+Inputs!$B$31)+E44*Inputs!$B$30+E45*Inputs!$B$32 -> 383.13059 | F49: =F47/1000*(Inputs!$B$19+Inputs!$B$20+Inputs!$B$21+Inputs!$B$22+Inputs!$B$23+Inputs!$B$24)+F48*((((Inputs!$B$10*Inputs!$B$15+Inputs!$B$11*Inputs!$B$16)*(1-Inputs!$B$14)+(Inputs!$B$10*Inputs!$B$17+Inputs!$B$11*Inputs!$B$18)*Inputs!$B$14)/1000000*Inputs!$B$12)*$B$11+Inputs!$B$12*Inputs!$B$13)+(F45*$D$18)*Inputs!$B$25*Inputs!$B$26+((F45*$D$18)*Inputs!$B$8*$B$13)*Inputs!$B$27*Inputs!$B$28+F46*(Inputs!$B$29+Inputs!$B$31)+F44*Inputs!$B$30+F45*Inputs!$B$32 -> 484.74617 | G49: =G47/1000*(Inputs!$B$19+Inputs!$B$20+Inputs!$B$21+Inputs!$B$22+Inputs!$B$23+Inputs!$B$24)+G48*((((Inputs!$B$10*Inputs!$B$15+Inputs!$B$11*Inputs!$B$16)*(1-Inputs!$B$14)+(Inputs!$B$10*Inputs!$B$17+Inputs!$B$11*Inputs!$B$18)*Inputs!$B$14)/1000000*Inputs!$B$12)*$B$11+Inputs!$B$12*Inputs!$B$13)+(G45*$D$18)*Inputs!$B$25*Inputs!$B$26+((G45*$D$18)*Inputs!$B$8*$B$13)*Inputs!$B$27*Inputs!$B$28+G46*(Inputs!$B$29+Inputs!$B$31)+G44*Inputs!$B$30+G45*Inputs!$B$32 -> 686.12226 | H49: =H47/1000*(Inputs!$B$19+Inputs!$B$20+Inputs!$B$21+Inputs!$B$22+Inputs!$B$23+Inputs!$B$24)+H48*((((Inputs!$B$10*Inputs!$B$15+Inputs!$B$11*Inputs!$B$16)*(1-Inputs!$B$14)+(Inputs!$B$10*Inputs!$B$17+Inputs!$B$11*Inputs!$B$18)*Inputs!$B$14)/1000000*Inputs!$B$12)*$B$11+Inputs!$B$12*Inputs!$B$13)+(H45*$D$18)*Inputs!$B$25*Inputs!$B$26+((H45*$D$18)*Inputs!$B$8*$B$13)*Inputs!$B$27*Inputs!$B$28+H46*(Inputs!$B$29+Inputs!$B$31)+H44*Inputs!$B$30+H45*Inputs!$B$32 -> 847.03548 | I49: =I47/1000*(Inputs!$B$19+Inputs!$B$20+Inputs!$B$21+Inputs!$B$22+Inputs!$B$23+Inputs!$B$24)+I48*((((Inputs!$B$10*Inputs!$B$15+Inputs!$B$11*Inputs!$B$16)*(1-Inputs!$B$14)+(Inputs!$B$10*Inputs!$B$17+Inputs!$B$11*Inputs!$B$18)*Inputs!$B$14)/1000000*Inputs!$B$12)*$B$11+Inputs!$B$12*Inputs!$B$13)+(I45*$D$18)*Inputs!$B$25*Inputs!$B$26+((I45*$D$18)*Inputs!$B$8*$B$13)*Inputs!$B$27*Inputs!$B$28+I46*(Inputs!$B$29+Inputs!$B$31)+I44*Inputs!$B$30+I45*Inputs!$B$32 -> 1077.9693 | ... M49: =M47/1000*(Inputs!$B$19+Inputs!$B$20+Inputs!$B$21+Inputs!$B$22+Inputs!$B$23+Inputs!$B$24)+M48*((((Inputs!$B$10*Inputs!$B$15+Inputs!$B$11*Inputs!$B$16)*(1-Inputs!$B$14)+(Inputs!$B$10*Inputs!$B$17+Inputs!$B$11*Inputs!$B$18)*Inputs!$B$14)/1000000*Inputs!$B$12)*$B$11+Inputs!$B$12*Inputs!$B$13)+(M45*$D$18)*Inputs!$B$25*Inputs!$B$26+((M45*$D$18)*Inputs!$B$8*$B$13)*Inputs!$B$27*Inputs!$B$28+M46*(Inputs!$B$29+Inputs!$B$31)+M44*Inputs!$B$30+M45*Inputs!$B$32 -> 2196.1243
A51: Pro | Opening accounts | B51: =0 -> 0 | C51: =B54 -> 14.4 | D51: =C54 -> 30.6 | E51: =D54 -> 48.879 | F51: =E54 -> 69.557625 | G51: =F54 -> 93.004374 | H51: =G54 -> 119.64281 | I51: =H54 -> 149.95981 | J51: =I54 -> 184.5151 | ... M51: =L54 -> 320.54153
A52: Pro | New accounts | B52: =B27*$C$19 -> 14.4 | C52: =C27*$C$19 -> 16.56 | D52: =D27*$C$19 -> 19.044 | E52: =E27*$C$19 -> 21.9006 | F52: =F27*$C$19 -> 25.18569 | G52: =G27*$C$19 -> 28.963544 | H52: =H27*$C$19 -> 33.308075 | I52: =I27*$C$19 -> 38.304286 | ... M52: =M27*$C$19 -> 66.994436
A53: Pro | Churned accounts | B53: =B51*$B$7 -> 0 | C53: =C51*$B$7 -> 0.36 | D53: =D51*$B$7 -> 0.765 | E53: =E51*$B$7 -> 1.221975 | F53: =F51*$B$7 -> 1.7389406 | G53: =G51*$B$7 -> 2.3251094 | H53: =H51*$B$7 -> 2.9910702 | I53: =I51*$B$7 -> 3.7489953 | ... M53: =M51*$B$7 -> 8.0135383
A54: Pro | Ending accounts | B54: =B51+B52-B53 -> 14.4 | C54: =C51+C52-C53 -> 30.6 | D54: =D51+D52-D53 -> 48.879 | E54: =E51+E52-E53 -> 69.557625 | F54: =F51+F52-F53 -> 93.004374 | G54: =G51+G52-G53 -> 119.64281 | H54: =H51+H52-H53 -> 149.95981 | I54: =I51+I52-I53 -> 184.5151 | ... M54: =M51+M52-M53 -> 379.52243
A55: Pro | Average accounts | B55: =(B51+B54)/2 -> 7.2 | C55: =(C51+C54)/2 -> 22.5 | D55: =(D51+D54)/2 -> 39.7395 | E55: =(E51+E54)/2 -> 59.218313 | F55: =(F51+F54)/2 -> 81.281 | G55: =(G51+G54)/2 -> 106.32359 | H55: =(H51+H54)/2 -> 134.80131 | I55: =(I51+I54)/2 -> 167.23746 | ... M55: =(M51+M54)/2 -> 350.03198
A56: Pro | Revenue | B56: =B55*$B$19 -> 208.8 | C56: =C55*$B$19 -> 652.5 | D56: =D55*$B$19 -> 1152.4455 | E56: =E55*$B$19 -> 1717.3311 | F56: =F55*$B$19 -> 2357.149 | G56: =G55*$B$19 -> 3083.3842 | H56: =H55*$B$19 -> 3909.238 | I56: =I55*$B$19 -> 4849.8863 | ... M56: =M55*$B$19 -> 10150.927
A57: Pro | Monitoring checks | B57: =(B55*$D$19)*DAY(EOMONTH(B$25,0))*1440/$E$19*$B$12 -> 642816 | C57: =(C55*$D$19)*DAY(EOMONTH(C$25,0))*1440/$E$19*$B$12 -> 1944000 | D57: =(D55*$D$19)*DAY(EOMONTH(D$25,0))*1440/$E$19*$B$12 -> 3547942.6 | E57: =(E55*$D$19)*DAY(EOMONTH(E$25,0))*1440/$E$19*$B$12 -> 5287010.9 | F57: =(F55*$D$19)*DAY(EOMONTH(F$25,0))*1440/$E$19*$B$12 -> 6554499.8 | G57: =(G55*$D$19)*DAY(EOMONTH(G$25,0))*1440/$E$19*$B$12 -> 9492570.2 | H57: =(H55*$D$19)*DAY(EOMONTH(H$25,0))*1440/$E$19*$B$12 -> 11646833 | I57: =(I55*$D$19)*DAY(EOMONTH(I$25,0))*1440/$E$19*$B$12 -> 14930960 | ... M57: =(M55*$D$19)*DAY(EOMONTH(M$25,0))*1440/$E$19*$B$12 -> 30242763
A58: Pro | AI diagnoses | B58: =(B55*$D$19)*Inputs!$B$8*$B$13*Inputs!$B$9*$F$19 -> 17.28 | C58: =(C55*$D$19)*Inputs!$B$8*$B$13*Inputs!$B$9*$F$19 -> 54 | D58: =(D55*$D$19)*Inputs!$B$8*$B$13*Inputs!$B$9*$F$19 -> 95.3748 | E58: =(E55*$D$19)*Inputs!$B$8*$B$13*Inputs!$B$9*$F$19 -> 142.12395 | F58: =(F55*$D$19)*Inputs!$B$8*$B$13*Inputs!$B$9*$F$19 -> 195.0744 | G58: =(G55*$D$19)*Inputs!$B$8*$B$13*Inputs!$B$9*$F$19 -> 255.17662 | H58: =(H55*$D$19)*Inputs!$B$8*$B$13*Inputs!$B$9*$F$19 -> 323.52315 | I58: =(I55*$D$19)*Inputs!$B$8*$B$13*Inputs!$B$9*$F$19 -> 401.3699 | ... M58: =(M55*$D$19)*Inputs!$B$8*$B$13*Inputs!$B$9*$F$19 -> 840.07676
A59: Pro | Variable service expense | B59: =B57/1000*(Inputs!$B$19+Inputs!$B$20+Inputs!$B$21+Inputs!$B$22+Inputs!$B$23+Inputs!$B$24)+B58*((((Inputs!$B$10*Inputs!$B$15+Inputs!$B$11*Inputs!$B$16)*(1-Inputs!$B$14)+(Inputs!$B$10*Inputs!$B$17+Inputs!$B$11*Inputs!$B$18)*Inputs!$B$14)/1000000*Inputs!$B$12)*$B$11+Inputs!$B$12*Inputs!$B$13)+(B55*$D$19)*Inputs!$B$25*Inputs!$B$26+((B55*$D$19)*Inputs!$B$8*$B$13)*Inputs!$B$27*Inputs!$B$28+B56*(Inputs!$B$29+Inputs!$B$31)+B54*Inputs!$B$30+B55*Inputs!$B$32 -> 125.22609 | C59: =C57/1000*(Inputs!$B$19+Inputs!$B$20+Inputs!$B$21+Inputs!$B$22+Inputs!$B$23+Inputs!$B$24)+C58*((((Inputs!$B$10*Inputs!$B$15+Inputs!$B$11*Inputs!$B$16)*(1-Inputs!$B$14)+(Inputs!$B$10*Inputs!$B$17+Inputs!$B$11*Inputs!$B$18)*Inputs!$B$14)/1000000*Inputs!$B$12)*$B$11+Inputs!$B$12*Inputs!$B$13)+(C55*$D$19)*Inputs!$B$25*Inputs!$B$26+((C55*$D$19)*Inputs!$B$8*$B$13)*Inputs!$B$27*Inputs!$B$28+C56*(Inputs!$B$29+Inputs!$B$31)+C54*Inputs!$B$30+C55*Inputs!$B$32 -> 375.99552 | D59: =D57/1000*(Inputs!$B$19+Inputs!$B$20+Inputs!$B$21+Inputs!$B$22+Inputs!$B$23+Inputs!$B$24)+D58*((((Inputs!$B$10*Inputs!$B$15+Inputs!$B$11*Inputs!$B$16)*(1-Inputs!$B$14)+(Inputs!$B$10*Inputs!$B$17+Inputs!$B$11*Inputs!$B$18)*Inputs!$B$14)/1000000*Inputs!$B$12)*$B$11+Inputs!$B$12*Inputs!$B$13)+(D55*$D$19)*Inputs!$B$25*Inputs!$B$26+((D55*$D$19)*Inputs!$B$8*$B$13)*Inputs!$B$27*Inputs!$B$28+D56*(Inputs!$B$29+Inputs!$B$31)+D54*Inputs!$B$30+D55*Inputs!$B$32 -> 681.98973 | E59: =E57/1000*(Inputs!$B$19+Inputs!$B$20+Inputs!$B$21+Inputs!$B$22+Inputs!$B$23+Inputs!$B$24)+E58*((((Inputs!$B$10*Inputs!$B$15+Inputs!$B$11*Inputs!$B$16)*(1-Inputs!$B$14)+(Inputs!$B$10*Inputs!$B$17+Inputs!$B$11*Inputs!$B$18)*Inputs!$B$14)/1000000*Inputs!$B$12)*$B$11+Inputs!$B$12*Inputs!$B$13)+(E55*$D$19)*Inputs!$B$25*Inputs!$B$26+((E55*$D$19)*Inputs!$B$8*$B$13)*Inputs!$B$27*Inputs!$B$28+E56*(Inputs!$B$29+Inputs!$B$31)+E54*Inputs!$B$30+E55*Inputs!$B$32 -> 1015.2915 | F59: =F57/1000*(Inputs!$B$19+Inputs!$B$20+Inputs!$B$21+Inputs!$B$22+Inputs!$B$23+Inputs!$B$24)+F58*((((Inputs!$B$10*Inputs!$B$15+Inputs!$B$11*Inputs!$B$16)*(1-Inputs!$B$14)+(Inputs!$B$10*Inputs!$B$17+Inputs!$B$11*Inputs!$B$18)*Inputs!$B$14)/1000000*Inputs!$B$12)*$B$11+Inputs!$B$12*Inputs!$B$13)+(F55*$D$19)*Inputs!$B$25*Inputs!$B$26+((F55*$D$19)*Inputs!$B$8*$B$13)*Inputs!$B$27*Inputs!$B$28+F56*(Inputs!$B$29+Inputs!$B$31)+F54*Inputs!$B$30+F55*Inputs!$B$32 -> 1273.4279 | G59: =G57/1000*(Inputs!$B$19+Inputs!$B$20+Inputs!$B$21+Inputs!$B$22+Inputs!$B$23+Inputs!$B$24)+G58*((((Inputs!$B$10*Inputs!$B$15+Inputs!$B$11*Inputs!$B$16)*(1-Inputs!$B$14)+(Inputs!$B$10*Inputs!$B$17+Inputs!$B$11*Inputs!$B$18)*Inputs!$B$14)/1000000*Inputs!$B$12)*$B$11+Inputs!$B$12*Inputs!$B$13)+(G55*$D$19)*Inputs!$B$25*Inputs!$B$26+((G55*$D$19)*Inputs!$B$8*$B$13)*Inputs!$B$27*Inputs!$B$28+G56*(Inputs!$B$29+Inputs!$B$31)+G54*Inputs!$B$30+G55*Inputs!$B$32 -> 1821.333 | H59: =H57/1000*(Inputs!$B$19+Inputs!$B$20+Inputs!$B$21+Inputs!$B$22+Inputs!$B$23+Inputs!$B$24)+H58*((((Inputs!$B$10*Inputs!$B$15+Inputs!$B$11*Inputs!$B$16)*(1-Inputs!$B$14)+(Inputs!$B$10*Inputs!$B$17+Inputs!$B$11*Inputs!$B$18)*Inputs!$B$14)/1000000*Inputs!$B$12)*$B$11+Inputs!$B$12*Inputs!$B$13)+(H55*$D$19)*Inputs!$B$25*Inputs!$B$26+((H55*$D$19)*Inputs!$B$8*$B$13)*Inputs!$B$27*Inputs!$B$28+H56*(Inputs!$B$29+Inputs!$B$31)+H54*Inputs!$B$30+H55*Inputs!$B$32 -> 2242.6419 | I59: =I57/1000*(Inputs!$B$19+Inputs!$B$20+Inputs!$B$21+Inputs!$B$22+Inputs!$B$23+Inputs!$B$24)+I58*((((Inputs!$B$10*Inputs!$B$15+Inputs!$B$11*Inputs!$B$16)*(1-Inputs!$B$14)+(Inputs!$B$10*Inputs!$B$17+Inputs!$B$11*Inputs!$B$18)*Inputs!$B$14)/1000000*Inputs!$B$12)*$B$11+Inputs!$B$12*Inputs!$B$13)+(I55*$D$19)*Inputs!$B$25*Inputs!$B$26+((I55*$D$19)*Inputs!$B$8*$B$13)*Inputs!$B$27*Inputs!$B$28+I56*(Inputs!$B$29+Inputs!$B$31)+I54*Inputs!$B$30+I55*Inputs!$B$32 -> 2863.6916 | ... M59: =M57/1000*(Inputs!$B$19+Inputs!$B$20+Inputs!$B$21+Inputs!$B$22+Inputs!$B$23+Inputs!$B$24)+M58*((((Inputs!$B$10*Inputs!$B$15+Inputs!$B$11*Inputs!$B$16)*(1-Inputs!$B$14)+(Inputs!$B$10*Inputs!$B$17+Inputs!$B$11*Inputs!$B$18)*Inputs!$B$14)/1000000*Inputs!$B$12)*$B$11+Inputs!$B$12*Inputs!$B$13)+(M55*$D$19)*Inputs!$B$25*Inputs!$B$26+((M55*$D$19)*Inputs!$B$8*$B$13)*Inputs!$B$27*Inputs!$B$28+M56*(Inputs!$B$29+Inputs!$B$31)+M54*Inputs!$B$30+M55*Inputs!$B$32 -> 5820.3973
A61: Business | Opening accounts | B61: =0 -> 0 | C61: =B64 -> 5.4 | D61: =C64 -> 11.475 | E61: =D64 -> 18.329625 | F61: =E64 -> 26.084109 | G61: =F64 -> 34.87664 | H61: =G64 -> 44.866053 | I61: =H64 -> 56.23493 | J61: =I64 -> 69.193164 | ... M61: =L64 -> 120.20307
A62: Business | New accounts | B62: =B27*$C$20 -> 5.4 | C62: =C27*$C$20 -> 6.21 | D62: =D27*$C$20 -> 7.1415 | E62: =E27*$C$20 -> 8.212725 | F62: =F27*$C$20 -> 9.4446337 | G62: =G27*$C$20 -> 10.861329 | H62: =H27*$C$20 -> 12.490528 | I62: =I27*$C$20 -> 14.364107 | ... M62: =M27*$C$20 -> 25.122914
A63: Business | Churned accounts | B63: =B61*$B$7 -> 0 | C63: =C61*$B$7 -> 0.135 | D63: =D61*$B$7 -> 0.286875 | E63: =E61*$B$7 -> 0.45824063 | F63: =F61*$B$7 -> 0.65210273 | G63: =G61*$B$7 -> 0.87191601 | H63: =H61*$B$7 -> 1.1216513 | I63: =I61*$B$7 -> 1.4058732 | ... M63: =M61*$B$7 -> 3.0050769
A64: Business | Ending accounts | B64: =B61+B62-B63 -> 5.4 | C64: =C61+C62-C63 -> 11.475 | D64: =D61+D62-D63 -> 18.329625 | E64: =E61+E62-E63 -> 26.084109 | F64: =F61+F62-F63 -> 34.87664 | G64: =G61+G62-G63 -> 44.866053 | H64: =H61+H62-H63 -> 56.23493 | I64: =I61+I62-I63 -> 69.193164 | ... M64: =M61+M62-M63 -> 142.32091
A65: Business | Average accounts | B65: =(B61+B64)/2 -> 2.7 | C65: =(C61+C64)/2 -> 8.4375 | D65: =(D61+D64)/2 -> 14.902313 | E65: =(E61+E64)/2 -> 22.206867 | F65: =(F61+F64)/2 -> 30.480375 | G65: =(G61+G64)/2 -> 39.871347 | H65: =(H61+H64)/2 -> 50.550492 | I65: =(I61+I64)/2 -> 62.714047 | ... M65: =(M61+M64)/2 -> 131.26199
A66: Business | Revenue | B66: =B65*$B$20 -> 267.3 | C66: =C65*$B$20 -> 835.3125 | D66: =D65*$B$20 -> 1475.3289 | E66: =E65*$B$20 -> 2198.4799 | F66: =F65*$B$20 -> 3017.5571 | G66: =G65*$B$20 -> 3947.2633 | H66: =H65*$B$20 -> 5004.4987 | I66: =I65*$B$20 -> 6208.6907 | ... M66: =M65*$B$20 -> 12994.937
A67: Business | Monitoring checks | B67: =(B65*$D$20)*DAY(EOMONTH(B$25,0))*1440/$E$20*$B$12 -> 723168 | C67: =(C65*$D$20)*DAY(EOMONTH(C$25,0))*1440/$E$20*$B$12 -> 2187000 | D67: =(D65*$D$20)*DAY(EOMONTH(D$25,0))*1440/$E$20*$B$12 -> 3991435.4 | E67: =(E65*$D$20)*DAY(EOMONTH(E$25,0))*1440/$E$20*$B$12 -> 5947887.3 | F67: =(F65*$D$20)*DAY(EOMONTH(F$25,0))*1440/$E$20*$B$12 -> 7373812.3 | G67: =(G65*$D$20)*DAY(EOMONTH(G$25,0))*1440/$E$20*$B$12 -> 10679142 | H67: =(H65*$D$20)*DAY(EOMONTH(H$25,0))*1440/$E$20*$B$12 -> 13102687 | I67: =(I65*$D$20)*DAY(EOMONTH(I$25,0))*1440/$E$20*$B$12 -> 16797330 | ... M67: =(M65*$D$20)*DAY(EOMONTH(M$25,0))*1440/$E$20*$B$12 -> 34023109
A68: Business | AI diagnoses | B68: =(B65*$D$20)*Inputs!$B$8*$B$13*Inputs!$B$9*$F$20 -> 19.44 | C68: =(C65*$D$20)*Inputs!$B$8*$B$13*Inputs!$B$9*$F$20 -> 60.75 | D68: =(D65*$D$20)*Inputs!$B$8*$B$13*Inputs!$B$9*$F$20 -> 107.29665 | E68: =(E65*$D$20)*Inputs!$B$8*$B$13*Inputs!$B$9*$F$20 -> 159.88944 | F68: =(F65*$D$20)*Inputs!$B$8*$B$13*Inputs!$B$9*$F$20 -> 219.4587 | G68: =(G65*$D$20)*Inputs!$B$8*$B$13*Inputs!$B$9*$F$20 -> 287.0737 | H68: =(H65*$D$20)*Inputs!$B$8*$B$13*Inputs!$B$9*$F$20 -> 363.96354 | I68: =(I65*$D$20)*Inputs!$B$8*$B$13*Inputs!$B$9*$F$20 -> 451.54114 | ... M68: =(M65*$D$20)*Inputs!$B$8*$B$13*Inputs!$B$9*$F$20 -> 945.08635
A69: Business | Variable service expense | B69: =B67/1000*(Inputs!$B$19+Inputs!$B$20+Inputs!$B$21+Inputs!$B$22+Inputs!$B$23+Inputs!$B$24)+B68*((((Inputs!$B$10*Inputs!$B$15+Inputs!$B$11*Inputs!$B$16)*(1-Inputs!$B$14)+(Inputs!$B$10*Inputs!$B$17+Inputs!$B$11*Inputs!$B$18)*Inputs!$B$14)/1000000*Inputs!$B$12)*$B$11+Inputs!$B$12*Inputs!$B$13)+(B65*$D$20)*Inputs!$B$25*Inputs!$B$26+((B65*$D$20)*Inputs!$B$8*$B$13)*Inputs!$B$27*Inputs!$B$28+B66*(Inputs!$B$29+Inputs!$B$31)+B64*Inputs!$B$30+B65*Inputs!$B$32 -> 136.10575 | C69: =C67/1000*(Inputs!$B$19+Inputs!$B$20+Inputs!$B$21+Inputs!$B$22+Inputs!$B$23+Inputs!$B$24)+C68*((((Inputs!$B$10*Inputs!$B$15+Inputs!$B$11*Inputs!$B$16)*(1-Inputs!$B$14)+(Inputs!$B$10*Inputs!$B$17+Inputs!$B$11*Inputs!$B$18)*Inputs!$B$14)/1000000*Inputs!$B$12)*$B$11+Inputs!$B$12*Inputs!$B$13)+(C65*$D$20)*Inputs!$B$25*Inputs!$B$26+((C65*$D$20)*Inputs!$B$8*$B$13)*Inputs!$B$27*Inputs!$B$28+C66*(Inputs!$B$29+Inputs!$B$31)+C64*Inputs!$B$30+C65*Inputs!$B$32 -> 411.31746 | D69: =D67/1000*(Inputs!$B$19+Inputs!$B$20+Inputs!$B$21+Inputs!$B$22+Inputs!$B$23+Inputs!$B$24)+D68*((((Inputs!$B$10*Inputs!$B$15+Inputs!$B$11*Inputs!$B$16)*(1-Inputs!$B$14)+(Inputs!$B$10*Inputs!$B$17+Inputs!$B$11*Inputs!$B$18)*Inputs!$B$14)/1000000*Inputs!$B$12)*$B$11+Inputs!$B$12*Inputs!$B$13)+(D65*$D$20)*Inputs!$B$25*Inputs!$B$26+((D65*$D$20)*Inputs!$B$8*$B$13)*Inputs!$B$27*Inputs!$B$28+D66*(Inputs!$B$29+Inputs!$B$31)+D64*Inputs!$B$30+D65*Inputs!$B$32 -> 747.77616 | E69: =E67/1000*(Inputs!$B$19+Inputs!$B$20+Inputs!$B$21+Inputs!$B$22+Inputs!$B$23+Inputs!$B$24)+E68*((((Inputs!$B$10*Inputs!$B$15+Inputs!$B$11*Inputs!$B$16)*(1-Inputs!$B$14)+(Inputs!$B$10*Inputs!$B$17+Inputs!$B$11*Inputs!$B$18)*Inputs!$B$14)/1000000*Inputs!$B$12)*$B$11+Inputs!$B$12*Inputs!$B$13)+(E65*$D$20)*Inputs!$B$25*Inputs!$B$26+((E65*$D$20)*Inputs!$B$8*$B$13)*Inputs!$B$27*Inputs!$B$28+E66*(Inputs!$B$29+Inputs!$B$31)+E64*Inputs!$B$30+E65*Inputs!$B$32 -> 1113.939 | F69: =F67/1000*(Inputs!$B$19+Inputs!$B$20+Inputs!$B$21+Inputs!$B$22+Inputs!$B$23+Inputs!$B$24)+F68*((((Inputs!$B$10*Inputs!$B$15+Inputs!$B$11*Inputs!$B$16)*(1-Inputs!$B$14)+(Inputs!$B$10*Inputs!$B$17+Inputs!$B$11*Inputs!$B$18)*Inputs!$B$14)/1000000*Inputs!$B$12)*$B$11+Inputs!$B$12*Inputs!$B$13)+(F65*$D$20)*Inputs!$B$25*Inputs!$B$26+((F65*$D$20)*Inputs!$B$8*$B$13)*Inputs!$B$27*Inputs!$B$28+F66*(Inputs!$B$29+Inputs!$B$31)+F64*Inputs!$B$30+F65*Inputs!$B$32 -> 1394.3676 | G69: =G67/1000*(Inputs!$B$19+Inputs!$B$20+Inputs!$B$21+Inputs!$B$22+Inputs!$B$23+Inputs!$B$24)+G68*((((Inputs!$B$10*Inputs!$B$15+Inputs!$B$11*Inputs!$B$16)*(1-Inputs!$B$14)+(Inputs!$B$10*Inputs!$B$17+Inputs!$B$11*Inputs!$B$18)*Inputs!$B$14)/1000000*Inputs!$B$12)*$B$11+Inputs!$B$12*Inputs!$B$13)+(G65*$D$20)*Inputs!$B$25*Inputs!$B$26+((G65*$D$20)*Inputs!$B$8*$B$13)*Inputs!$B$27*Inputs!$B$28+G66*(Inputs!$B$29+Inputs!$B$31)+G64*Inputs!$B$30+G65*Inputs!$B$32 -> 1999.4331 | H69: =H67/1000*(Inputs!$B$19+Inputs!$B$20+Inputs!$B$21+Inputs!$B$22+Inputs!$B$23+Inputs!$B$24)+H68*((((Inputs!$B$10*Inputs!$B$15+Inputs!$B$11*Inputs!$B$16)*(1-Inputs!$B$14)+(Inputs!$B$10*Inputs!$B$17+Inputs!$B$11*Inputs!$B$18)*Inputs!$B$14)/1000000*Inputs!$B$12)*$B$11+Inputs!$B$12*Inputs!$B$13)+(H65*$D$20)*Inputs!$B$25*Inputs!$B$26+((H65*$D$20)*Inputs!$B$8*$B$13)*Inputs!$B$27*Inputs!$B$28+H66*(Inputs!$B$29+Inputs!$B$31)+H64*Inputs!$B$30+H65*Inputs!$B$32 -> 2460.5184 | I69: =I67/1000*(Inputs!$B$19+Inputs!$B$20+Inputs!$B$21+Inputs!$B$22+Inputs!$B$23+Inputs!$B$24)+I68*((((Inputs!$B$10*Inputs!$B$15+Inputs!$B$11*Inputs!$B$16)*(1-Inputs!$B$14)+(Inputs!$B$10*Inputs!$B$17+Inputs!$B$11*Inputs!$B$18)*Inputs!$B$14)/1000000*Inputs!$B$12)*$B$11+Inputs!$B$12*Inputs!$B$13)+(I65*$D$20)*Inputs!$B$25*Inputs!$B$26+((I65*$D$20)*Inputs!$B$8*$B$13)*Inputs!$B$27*Inputs!$B$28+I66*(Inputs!$B$29+Inputs!$B$31)+I64*Inputs!$B$30+I65*Inputs!$B$32 -> 3144.5155 | ... M69: =M67/1000*(Inputs!$B$19+Inputs!$B$20+Inputs!$B$21+Inputs!$B$22+Inputs!$B$23+Inputs!$B$24)+M68*((((Inputs!$B$10*Inputs!$B$15+Inputs!$B$11*Inputs!$B$16)*(1-Inputs!$B$14)+(Inputs!$B$10*Inputs!$B$17+Inputs!$B$11*Inputs!$B$18)*Inputs!$B$14)/1000000*Inputs!$B$12)*$B$11+Inputs!$B$12*Inputs!$B$13)+(M65*$D$20)*Inputs!$B$25*Inputs!$B$26+((M65*$D$20)*Inputs!$B$8*$B$13)*Inputs!$B$27*Inputs!$B$28+M66*(Inputs!$B$29+Inputs!$B$31)+M64*Inputs!$B$30+M65*Inputs!$B$32 -> 6387.9976
A73: Paying customers ending | B73: =B44+B54+B64 -> 36 | C73: =C44+C54+C64 -> 76.5 | D73: =D44+D54+D64 -> 122.1975 | E73: =E44+E54+E64 -> 173.89406 | F73: =F44+F54+F64 -> 232.51094 | G73: =G44+G54+G64 -> 299.10702 | H73: =H44+H54+H64 -> 374.89953 | I73: =I44+I54+I64 -> 461.28776 | ... M73: =M44+M54+M64 -> 948.80608
A74: Paying customers average | B74: =B45+B55+B65 -> 18 | C74: =C45+C55+C65 -> 56.25 | D74: =D45+D55+D65 -> 99.34875 | E74: =E45+E55+E65 -> 148.04578 | F74: =F45+F55+F65 -> 203.2025 | G74: =G45+G55+G65 -> 265.80898 | H74: =H45+H55+H65 -> 337.00328 | I74: =I45+I55+I65 -> 418.09365 | ... M74: =M45+M55+M65 -> 875.07995
A75: Free customers ending | B75: =B34 -> 264 | C75: =C34 -> 541.2 | D75: =D34 -> 836.22 | E75: =E34 -> 1154.109 | F75: =F34 -> 1500.4358 | G75: =G34 -> 1881.3905 | H75: =H34 -> 2303.8995 | I75: =I34 -> 2775.7548 | ... M75: =M34 -> 5351.6185
A76: Exit MRR | B76: =B44*$B$18+B54*$B$19+B64*$B$20 -> 1098 | C76: =C44*$B$18+C54*$B$19+C64*$B$20 -> 2333.25 | D76: =D44*$B$18+D54*$B$19+D64*$B$20 -> 3727.0237 | E76: =E44*$B$18+E54*$B$19+E64*$B$20 -> 5303.7689 | F76: =F44*$B$18+F54*$B$19+F64*$B$20 -> 7091.5835 | G76: =G44*$B$18+G54*$B$19+G64*$B$20 -> 9122.7641 | H76: =H44*$B$18+H54*$B$19+H64*$B$20 -> 11434.436 | I76: =I44*$B$18+I54*$B$19+I64*$B$20 -> 14069.277 | ... M76: =M44*$B$18+M54*$B$19+M64*$B$20 -> 28938.585
A77: Revenue | B77: =B36+B46+B56+B66 -> 549 | C77: =C36+C46+C56+C66 -> 1715.625 | D77: =D36+D46+D56+D66 -> 3030.1369 | E77: =E36+E46+E56+E66 -> 4515.3963 | F77: =F36+F46+F56+F66 -> 6197.6762 | G77: =G36+G46+G56+G66 -> 8107.1738 | H77: =H36+H46+H56+H66 -> 10278.6 | I77: =I36+I46+I56+I66 -> 12751.856 | ... M77: =M36+M46+M56+M66 -> 26689.939
A78: Monitoring checks | B78: =B37+B47+B57+B67 -> 1975766.4 | C78: =C37+C47+C57+C67 -> 5946588 | D78: =D37+D47+D57+D67 -> 10786410 | E78: =E37+E47+E57+E67 -> 15980874 | F78: =F37+F47+F57+F67 -> 19708164 | G78: =G37+G47+G57+G67 -> 28407612 | H78: =H37+H47+H57+H67 -> 34707144 | I78: =I37+I47+I57+I67 -> 44326015 | ... M78: =M37+M47+M57+M67 -> 88776555
A79: AI diagnoses | B79: =B38+B48+B58+B68 -> 42.552 | C79: =C38+C48+C58+C68 -> 132.975 | D79: =D38+D48+D58+D68 -> 234.86044 | E79: =E38+E48+E58+E68 -> 349.98023 | F79: =F38+F48+F58+F68 -> 480.37071 | G79: =G38+G48+G58+G68 -> 628.37243 | H79: =H38+H48+H58+H68 -> 796.67575 | I79: =I38+I48+I58+I68 -> 988.37338 | ... M79: =M38+M48+M58+M68 -> 2068.689
A80: Variable cost of revenue | B80: =B39+B49+B59+B69 -> 377.07116 | C80: =C39+C49+C59+C69 -> 1128.8137 | D80: =D39+D49+D59+D69 -> 2037.9759 | E80: =E39+E49+E59+E69 -> 3018.6212 | F80: =F39+F49+F59+F69 -> 3762.7685 | G80: =G39+G49+G59+G69 -> 5367.0897 | H80: =H39+H49+H59+H69 -> 6580.6142 | I80: =I39+I49+I59+I69 -> 8378.2372 | ... M80: =M39+M49+M59+M69 -> 16850.063
A81: Fixed platform cost | B81: =Inputs!$B$33+Inputs!$B$34+Inputs!$B$35+Inputs!$B$36+Inputs!$B$37+Inputs!$B$38+Inputs!$B$39 -> 100 | C81: =Inputs!$B$33+Inputs!$B$34+Inputs!$B$35+Inputs!$B$36+Inputs!$B$37+Inputs!$B$38+Inputs!$B$39 -> 100 | D81: =Inputs!$B$33+Inputs!$B$34+Inputs!$B$35+Inputs!$B$36+Inputs!$B$37+Inputs!$B$38+Inputs!$B$39 -> 100 | E81: =Inputs!$B$33+Inputs!$B$34+Inputs!$B$35+Inputs!$B$36+Inputs!$B$37+Inputs!$B$38+Inputs!$B$39 -> 100 | F81: =Inputs!$B$33+Inputs!$B$34+Inputs!$B$35+Inputs!$B$36+Inputs!$B$37+Inputs!$B$38+Inputs!$B$39 -> 100 | G81: =Inputs!$B$33+Inputs!$B$34+Inputs!$B$35+Inputs!$B$36+Inputs!$B$37+Inputs!$B$38+Inputs!$B$39 -> 100 | H81: =Inputs!$B$33+Inputs!$B$34+Inputs!$B$35+Inputs!$B$36+Inputs!$B$37+Inputs!$B$38+Inputs!$B$39 -> 100 | I81: =Inputs!$B$33+Inputs!$B$34+Inputs!$B$35+Inputs!$B$36+Inputs!$B$37+Inputs!$B$38+Inputs!$B$39 -> 100 | ... M81: =Inputs!$B$33+Inputs!$B$34+Inputs!$B$35+Inputs!$B$36+Inputs!$B$37+Inputs!$B$38+Inputs!$B$39 -> 100
A82: Capacity scaling cost | B82: =MAX(0,ROUNDUP((B35*$D$17+B45*$D$18+B55*$D$19+B65*$D$20)/Inputs!$B$40,0)-1)*Inputs!$B$41 -> 0 | C82: =MAX(0,ROUNDUP((C35*$D$17+C45*$D$18+C55*$D$19+C65*$D$20)/Inputs!$B$40,0)-1)*Inputs!$B$41 -> 100 | D82: =MAX(0,ROUNDUP((D35*$D$17+D45*$D$18+D55*$D$19+D65*$D$20)/Inputs!$B$40,0)-1)*Inputs!$B$41 -> 300 | E82: =MAX(0,ROUNDUP((E35*$D$17+E45*$D$18+E55*$D$19+E65*$D$20)/Inputs!$B$40,0)-1)*Inputs!$B$41 -> 400 | F82: =MAX(0,ROUNDUP((F35*$D$17+F45*$D$18+F55*$D$19+F65*$D$20)/Inputs!$B$40,0)-1)*Inputs!$B$41 -> 600 | G82: =MAX(0,ROUNDUP((G35*$D$17+G45*$D$18+G55*$D$19+G65*$D$20)/Inputs!$B$40,0)-1)*Inputs!$B$41 -> 800 | H82: =MAX(0,ROUNDUP((H35*$D$17+H45*$D$18+H55*$D$19+H65*$D$20)/Inputs!$B$40,0)-1)*Inputs!$B$41 -> 1000 | I82: =MAX(0,ROUNDUP((I35*$D$17+I45*$D$18+I55*$D$19+I65*$D$20)/Inputs!$B$40,0)-1)*Inputs!$B$41 -> 1300 | ... M82: =MAX(0,ROUNDUP((M35*$D$17+M45*$D$18+M55*$D$19+M65*$D$20)/Inputs!$B$40,0)-1)*Inputs!$B$41 -> 2700
A83: Total cost of revenue | B83: =B80+B81+B82 -> 477.07116 | C83: =C80+C81+C82 -> 1328.8137 | D83: =D80+D81+D82 -> 2437.9759 | E83: =E80+E81+E82 -> 3518.6212 | F83: =F80+F81+F82 -> 4462.7685 | G83: =G80+G81+G82 -> 6267.0897 | H83: =H80+H81+H82 -> 7680.6142 | I83: =I80+I81+I82 -> 9778.2372 | ... M83: =M80+M81+M82 -> 19650.063
A84: Gross profit | B84: =B77-B83 -> 71.928842 | C84: =C77-C83 -> 386.81129 | D84: =D77-D83 -> 592.16097 | E84: =E77-E83 -> 996.77516 | F84: =F77-F83 -> 1734.9078 | G84: =G77-G83 -> 1840.0841 | H84: =H77-H83 -> 2597.9858 | I84: =I77-I83 -> 2973.619 | ... M84: =M77-M83 -> 7039.8754
A85: Gross margin | B85: =IFERROR(B84/B77,0) -> 0.13101793 | C85: =IFERROR(C84/C77,0) -> 0.22546378 | D85: =IFERROR(D84/D77,0) -> 0.19542384 | E85: =IFERROR(E84/E77,0) -> 0.22075032 | F85: =IFERROR(F84/F77,0) -> 0.27992875 | G85: =IFERROR(G84/G77,0) -> 0.22696986 | H85: =IFERROR(H84/H77,0) -> 0.25275678 | I85: =IFERROR(I84/I77,0) -> 0.23319107 | ... M85: =IFERROR(M84/M77,0) -> 0.26376514
A86: Acquisition expense | B86: =B27*$B$9 -> 1080 | C86: =C27*$B$9 -> 1242 | D86: =D27*$B$9 -> 1428.3 | E86: =E27*$B$9 -> 1642.545 | F86: =F27*$B$9 -> 1888.9268 | G86: =G27*$B$9 -> 2172.2658 | H86: =H27*$B$9 -> 2498.1056 | I86: =I27*$B$9 -> 2872.8215 | ... M86: =M27*$B$9 -> 5024.5827
A87: Contractors | B87: =IF(COLUMN()-1>=Inputs!$B$44,Inputs!$B$43,0) -> 0 | C87: =IF(COLUMN()-1>=Inputs!$B$44,Inputs!$B$43,0) -> 0 | D87: =IF(COLUMN()-1>=Inputs!$B$44,Inputs!$B$43,0) -> 0 | E87: =IF(COLUMN()-1>=Inputs!$B$44,Inputs!$B$43,0) -> 1500 | F87: =IF(COLUMN()-1>=Inputs!$B$44,Inputs!$B$43,0) -> 1500 | G87: =IF(COLUMN()-1>=Inputs!$B$44,Inputs!$B$43,0) -> 1500 | H87: =IF(COLUMN()-1>=Inputs!$B$44,Inputs!$B$43,0) -> 1500 | I87: =IF(COLUMN()-1>=Inputs!$B$44,Inputs!$B$43,0) -> 1500 | ... M87: =IF(COLUMN()-1>=Inputs!$B$44,Inputs!$B$43,0) -> 1500
A88: Staff | B88: =IF(COLUMN()-1>=Inputs!$B$46,$B$10,0) -> 0 | C88: =IF(COLUMN()-1>=Inputs!$B$46,$B$10,0) -> 0 | D88: =IF(COLUMN()-1>=Inputs!$B$46,$B$10,0) -> 0 | E88: =IF(COLUMN()-1>=Inputs!$B$46,$B$10,0) -> 0 | F88: =IF(COLUMN()-1>=Inputs!$B$46,$B$10,0) -> 0 | G88: =IF(COLUMN()-1>=Inputs!$B$46,$B$10,0) -> 0 | H88: =IF(COLUMN()-1>=Inputs!$B$46,$B$10,0) -> 0 | I88: =IF(COLUMN()-1>=Inputs!$B$46,$B$10,0) -> 0 | ... M88: =IF(COLUMN()-1>=Inputs!$B$46,$B$10,0) -> 3000
A89: Founder pay | B89: =Inputs!$B$47 -> 0 | C89: =Inputs!$B$47 -> 0 | D89: =Inputs!$B$47 -> 0 | E89: =Inputs!$B$47 -> 0 | F89: =Inputs!$B$47 -> 0 | G89: =Inputs!$B$47 -> 0 | H89: =Inputs!$B$47 -> 0 | I89: =Inputs!$B$47 -> 0 | ... M89: =Inputs!$B$47 -> 0
A90: Administration | B90: =Inputs!$B$42 -> 150 | C90: =Inputs!$B$42 -> 150 | D90: =Inputs!$B$42 -> 150 | E90: =Inputs!$B$42 -> 150 | F90: =Inputs!$B$42 -> 150 | G90: =Inputs!$B$42 -> 150 | H90: =Inputs!$B$42 -> 150 | I90: =Inputs!$B$42 -> 150 | ... M90: =Inputs!$B$42 -> 150
A91: Total operating expense | B91: =B86+B87+B88+B89+B90 -> 1230 | C91: =C86+C87+C88+C89+C90 -> 1392 | D91: =D86+D87+D88+D89+D90 -> 1578.3 | E91: =E86+E87+E88+E89+E90 -> 3292.545 | F91: =F86+F87+F88+F89+F90 -> 3538.9268 | G91: =G86+G87+G88+G89+G90 -> 3822.2658 | H91: =H86+H87+H88+H89+H90 -> 4148.1056 | I91: =I86+I87+I88+I89+I90 -> 4522.8215 | ... M91: =M86+M87+M88+M89+M90 -> 9674.5827
A92: Operating profit / net cash flow | B92: =B84-B91 -> -1158.0712 | C92: =C84-C91 -> -1005.1887 | D92: =D84-D91 -> -986.13903 | E92: =E84-E91 -> -2295.7698 | F92: =F84-F91 -> -1804.019 | G92: =G84-G91 -> -1982.1816 | H92: =H84-H91 -> -1550.1198 | I92: =I84-I91 -> -1549.2025 | ... M92: =M84-M91 -> -2634.7073
A93: Cumulative cash flow | B93: =0+B92 -> -1158.0712 | C93: =B93+C92 -> -2163.2599 | D93: =C93+D92 -> -3149.3989 | E93: =D93+E92 -> -5445.1687 | F93: =E93+F92 -> -7249.1877 | G93: =F93+G92 -> -9231.3693 | H93: =G93+H92 -> -10781.489 | I93: =H93+I92 -> -12330.692 | J93: =I93+J92 -> -16315.399 | ... M93: =L93+M92 -> -26468.351
A94: Cash from editable starting cash | B94: =Inputs!$B$49+B93 -> 13841.929 | C94: =Inputs!$B$49+C93 -> 12836.74 | D94: =Inputs!$B$49+D93 -> 11850.601 | E94: =Inputs!$B$49+E93 -> 9554.8313 | F94: =Inputs!$B$49+F93 -> 7750.8123 | G94: =Inputs!$B$49+G93 -> 5768.6307 | H94: =Inputs!$B$49+H93 -> 4218.5108 | I94: =Inputs!$B$49+I93 -> 2669.3084 | ... M94: =Inputs!$B$49+M93 -> -11468.351
A95: Cash from $5k | B95: =Inputs!$B$54+B93 -> 3841.9288 | C95: =Inputs!$B$54+C93 -> 2836.7401 | D95: =Inputs!$B$54+D93 -> 1850.6011 | E95: =Inputs!$B$54+E93 -> -445.16873 | F95: =Inputs!$B$54+F93 -> -2249.1877 | G95: =Inputs!$B$54+G93 -> -4231.3693 | H95: =Inputs!$B$54+H93 -> -5781.4892 | I95: =Inputs!$B$54+I93 -> -7330.6916 | ... M95: =Inputs!$B$54+M93 -> -21468.351
A96: Cash from $15k | B96: =Inputs!$B$55+B93 -> 13841.929 | C96: =Inputs!$B$55+C93 -> 12836.74 | D96: =Inputs!$B$55+D93 -> 11850.601 | E96: =Inputs!$B$55+E93 -> 9554.8313 | F96: =Inputs!$B$55+F93 -> 7750.8123 | G96: =Inputs!$B$55+G93 -> 5768.6307 | H96: =Inputs!$B$55+H93 -> 4218.5108 | I96: =Inputs!$B$55+I93 -> 2669.3084 | ... M96: =Inputs!$B$55+M93 -> -11468.351
A97: Cash from $30k | B97: =Inputs!$B$56+B93 -> 28841.929 | C97: =Inputs!$B$56+C93 -> 27836.74 | D97: =Inputs!$B$56+D93 -> 26850.601 | E97: =Inputs!$B$56+E93 -> 24554.831 | F97: =Inputs!$B$56+F93 -> 22750.812 | G97: =Inputs!$B$56+G93 -> 20768.631 | H97: =Inputs!$B$56+H93 -> 19218.511 | I97: =Inputs!$B$56+I93 -> 17669.308 | ... M97: =Inputs!$B$56+M93 -> 3531.6493
A98: ARPPU | B98: =IFERROR(B77/B74,0) -> 30.5 | C98: =IFERROR(C77/C74,0) -> 30.5 | D98: =IFERROR(D77/D74,0) -> 30.5 | E98: =IFERROR(E77/E74,0) -> 30.5 | F98: =IFERROR(F77/F74,0) -> 30.5 | G98: =IFERROR(G77/G74,0) -> 30.5 | H98: =IFERROR(H77/H74,0) -> 30.5 | I98: =IFERROR(I77/I74,0) -> 30.5 | ... M98: =IFERROR(M77/M74,0) -> 30.5
A99: ARPU all accounts | B99: =IFERROR(B77/(B35+B45+B55+B65),0) -> 3.66 | C99: =IFERROR(C77/(C35+C45+C55+C65),0) -> 3.738967 | D99: =IFERROR(D77/(D35+D45+D55+D65),0) -> 3.8450647 | E99: =IFERROR(E77/(E35+E45+E55+E65),0) -> 3.9497513 | F99: =IFERROR(F77/(F35+F45+F55+F65),0) -> 4.0495119 | G99: =IFERROR(G77/(G35+G45+G55+G65),0) -> 4.1432424 | H99: =IFERROR(H77/(H35+H45+H55+H65),0) -> 4.2304889 | I99: =IFERROR(I77/(I35+I45+I55+I65),0) -> 4.3110878 | ... M99: =IFERROR(M77/(M35+M45+M55+M65),0) -> 4.5688964
A100: Cost per average paying account | B100: =IFERROR(B83/B74,0) -> 26.503953 | C100: =IFERROR(C83/C74,0) -> 23.623355 | D100: =IFERROR(D83/D74,0) -> 24.539573 | E100: =IFERROR(E83/E74,0) -> 23.767115 | F100: =IFERROR(F83/F74,0) -> 21.962173 | G100: =IFERROR(G83/G74,0) -> 23.577419 | H100: =IFERROR(H83/H74,0) -> 22.790918 | I100: =IFERROR(I83/I74,0) -> 23.387672 | ... M100: =IFERROR(M83/M74,0) -> 22.455163
A101: Gross profit per average paying account | B101: =B98-B100 -> 3.9960468 | C101: =C98-C100 -> 6.8766452 | D101: =D98-D100 -> 5.960427 | E101: =E98-E100 -> 6.7328846 | F101: =F98-F100 -> 8.5378269 | G101: =G98-G100 -> 6.9225809 | H101: =H98-H100 -> 7.7090817 | I101: =I98-I100 -> 7.1123276 | ... M101: =M98-M100 -> 8.0448368
A102: LTV fully loaded | B102: =IF(B101>0,B101/$B$7,0) -> 159.84187 | C102: =IF(C101>0,C101/$B$7,0) -> 275.06581 | D102: =IF(D101>0,D101/$B$7,0) -> 238.41708 | E102: =IF(E101>0,E101/$B$7,0) -> 269.31538 | F102: =IF(F101>0,F101/$B$7,0) -> 341.51308 | G102: =IF(G101>0,G101/$B$7,0) -> 276.90323 | H102: =IF(H101>0,H101/$B$7,0) -> 308.36327 | I102: =IF(I101>0,I101/$B$7,0) -> 284.49311 | ... M102: =IF(M101>0,M101/$B$7,0) -> 321.79347
A103: LTV to CAC fully loaded | B103: =IF(B101>0,B102/$B$9,0) -> 5.3280624 | C103: =IF(C101>0,C102/$B$9,0) -> 9.1688603 | D103: =IF(D101>0,D102/$B$9,0) -> 7.947236 | E103: =IF(E101>0,E102/$B$9,0) -> 8.9771795 | F103: =IF(F101>0,F102/$B$9,0) -> 11.383769 | G103: =IF(G101>0,G102/$B$9,0) -> 9.2301078 | H103: =IF(H101>0,H102/$B$9,0) -> 10.278776 | I103: =IF(I101>0,I102/$B$9,0) -> 9.4831035 | ... M103: =IF(M101>0,M102/$B$9,0) -> 10.726449
A104: CAC payback months | B104: =IF(B101>0,$B$9/B101,0) -> 7.5074196 | C104: =IF(C101>0,$B$9/C101,0) -> 4.3625924 | D104: =IF(D101>0,$B$9/D101,0) -> 5.0331964 | E104: =IF(E101>0,$B$9/E101,0) -> 4.4557425 | F104: =IF(F101>0,$B$9/F101,0) -> 3.5137747 | G104: =IF(G101>0,$B$9/G101,0) -> 4.3336439 | H104: =IF(H101>0,$B$9/H101,0) -> 3.8915141 | I104: =IF(I101>0,$B$9/I101,0) -> 4.2180284 | ... M104: =IF(M101>0,$B$9/M101,0) -> 3.7290999
A105: Cash bridge check | B105: =B94-Inputs!$B$49-B93 -> 0 | C105: =C94-Inputs!$B$49-C93 -> 0 | D105: =D94-Inputs!$B$49-D93 -> 0 | E105: =E94-Inputs!$B$49-E93 -> 0 | F105: =F94-Inputs!$B$49-F93 -> 0 | G105: =G94-Inputs!$B$49-G93 -> 0 | H105: =H94-Inputs!$B$49-H93 -> 0 | I105: =I94-Inputs!$B$49-I93 -> 0 | ... M105: =M94-Inputs!$B$49-M93 -> 0

Sheet Guardrailed
A1: Guardrailed — hypothetical 12-month forecast
A4: Initial monthly signups | B4: =Inputs!$B$2 -> 150
A5: Monthly signup growth | B5: =Inputs!$B$3 -> 0.1
A6: Paid conversion rate | B6: =Inputs!$B$4 -> 0.08
A7: Monthly paid churn | B7: =Inputs!$B$5 -> 0.04
A8: Monthly free churn | B8: =Inputs!$B$6 -> 0.15
A9: Blended acquisition CAC | B9: =Inputs!$B$7 -> 40
A10: Staff monthly budget | B10: 0
A11: AI cost stress multiplier | B11: =Inputs!$B$50 -> 1
A12: Monitoring frequency multiplier | B12: =Inputs!$B$51 -> 1
A13: Incident volume multiplier | B13: =Inputs!$B$52 -> 1
A17: Free | B17: =Pricing!B2 -> 0 | C17: =Pricing!C2 -> 0 | D17: 1 | E17: 60 | F17: =Pricing!F2 -> 0
A18: Starter | B18: =Pricing!B3 -> 9 | C18: =Pricing!C3 -> 0.6 | D18: 1 | E18: 15 | F18: =Pricing!F3 -> 1
A19: Pro | B19: =Pricing!B4 -> 29 | C19: =Pricing!C4 -> 0.3 | D19: 3 | E19: 5 | F19: =Pricing!F4 -> 1
A20: Business | B20: =Pricing!B5 -> 99 | C20: =Pricing!C5 -> 0.1 | D20: 10 | E20: 5 | F20: =Pricing!F5 -> 1
B25: 46296 | C25: 46327 | D25: 46357 | E25: 46388 | F25: 46419 | G25: 46447 | H25: 46478 | I25: 46508 | J25: 46539 | K25: 46569 | L25: 46600 | M25: 46631
A26: New signups | B26: =$B$4 -> 150 | C26: =B26*(1+$B$5) -> 165 | D26: =C26*(1+$B$5) -> 181.5 | E26: =D26*(1+$B$5) -> 199.65 | F26: =E26*(1+$B$5) -> 219.615 | G26: =F26*(1+$B$5) -> 241.5765 | H26: =G26*(1+$B$5) -> 265.73415 | I26: =H26*(1+$B$5) -> 292.30757 | J26: =I26*(1+$B$5) -> 321.53832 | ... M26: =L26*(1+$B$5) -> 427.96751
A27: New paid | B27: =B26*$B$6 -> 12 | C27: =C26*$B$6 -> 13.2 | D27: =D26*$B$6 -> 14.52 | E27: =E26*$B$6 -> 15.972 | F27: =F26*$B$6 -> 17.5692 | G27: =G26*$B$6 -> 19.32612 | H27: =H26*$B$6 -> 21.258732 | I27: =I26*$B$6 -> 23.384605 | ... M27: =M26*$B$6 -> 34.2374
A28: New free | B28: =B26-B27 -> 138 | C28: =C26-C27 -> 151.8 | D28: =D26-D27 -> 166.98 | E28: =E26-E27 -> 183.678 | F28: =F26-F27 -> 202.0458 | G28: =G26-G27 -> 222.25038 | H28: =H26-H27 -> 244.47542 | I28: =I26-I27 -> 268.92296 | ... M28: =M26-M27 -> 393.73011
A31: Free | Opening accounts | B31: =0 -> 0 | C31: =B34 -> 138 | D31: =C34 -> 269.1 | E31: =D34 -> 395.715 | F31: =E34 -> 520.03575 | G31: =F34 -> 644.07619 | H31: =G34 -> 769.71514 | I31: =H34 -> 898.73329 | J31: =I34 -> 1032.8463 | ... M31: =L34 -> 1482.547
A32: Free | New accounts | B32: =B28 -> 138 | C32: =C28 -> 151.8 | D32: =D28 -> 166.98 | E32: =E28 -> 183.678 | F32: =F28 -> 202.0458 | G32: =G28 -> 222.25038 | H32: =H28 -> 244.47542 | I32: =I28 -> 268.92296 | ... M32: =M28 -> 393.73011
A33: Free | Churned accounts | B33: =B31*$B$8 -> 0 | C33: =C31*$B$8 -> 20.7 | D33: =D31*$B$8 -> 40.365 | E33: =E31*$B$8 -> 59.35725 | F33: =F31*$B$8 -> 78.005363 | G33: =G31*$B$8 -> 96.611428 | H33: =H31*$B$8 -> 115.45727 | I33: =I31*$B$8 -> 134.80999 | ... M33: =M31*$B$8 -> 222.38204
A34: Free | Ending accounts | B34: =B31+B32-B33 -> 138 | C34: =C31+C32-C33 -> 269.1 | D34: =D31+D32-D33 -> 395.715 | E34: =E31+E32-E33 -> 520.03575 | F34: =F31+F32-F33 -> 644.07619 | G34: =G31+G32-G33 -> 769.71514 | H34: =H31+H32-H33 -> 898.73329 | I34: =I31+I32-I33 -> 1032.8463 | ... M34: =M31+M32-M33 -> 1653.895
A35: Free | Average accounts | B35: =(B31+B34)/2 -> 69 | C35: =(C31+C34)/2 -> 203.55 | D35: =(D31+D34)/2 -> 332.4075 | E35: =(E31+E34)/2 -> 457.87538 | F35: =(F31+F34)/2 -> 582.05597 | G35: =(G31+G34)/2 -> 706.89566 | H35: =(H31+H34)/2 -> 834.22421 | I35: =(I31+I34)/2 -> 965.78977 | ... M35: =(M31+M34)/2 -> 1568.221
A36: Free | Revenue | B36: =B35*$B$17 -> 0 | C36: =C35*$B$17 -> 0 | D36: =D35*$B$17 -> 0 | E36: =E35*$B$17 -> 0 | F36: =F35*$B$17 -> 0 | G36: =G35*$B$17 -> 0 | H36: =H35*$B$17 -> 0 | I36: =I35*$B$17 -> 0 | ... M36: =M35*$B$17 -> 0
A37: Free | Monitoring checks | B37: =(B35*$D$17)*DAY(EOMONTH(B$25,0))*1440/$E$17*$B$12 -> 51336 | C37: =(C35*$D$17)*DAY(EOMONTH(C$25,0))*1440/$E$17*$B$12 -> 146556 | D37: =(D35*$D$17)*DAY(EOMONTH(D$25,0))*1440/$E$17*$B$12 -> 247311.18 | E37: =(E35*$D$17)*DAY(EOMONTH(E$25,0))*1440/$E$17*$B$12 -> 340659.28 | F37: =(F35*$D$17)*DAY(EOMONTH(F$25,0))*1440/$E$17*$B$12 -> 391141.61 | G37: =(G35*$D$17)*DAY(EOMONTH(G$25,0))*1440/$E$17*$B$12 -> 525930.37 | H37: =(H35*$D$17)*DAY(EOMONTH(H$25,0))*1440/$E$17*$B$12 -> 600641.43 | I37: =(I35*$D$17)*DAY(EOMONTH(I$25,0))*1440/$E$17*$B$12 -> 718547.59 | ... M37: =(M35*$D$17)*DAY(EOMONTH(M$25,0))*1440/$E$17*$B$12 -> 1129119.1
A38: Free | AI diagnoses | B38: =(B35*$D$17)*Inputs!$B$8*$B$13*Inputs!$B$9*$F$17 -> 0 | C38: =(C35*$D$17)*Inputs!$B$8*$B$13*Inputs!$B$9*$F$17 -> 0 | D38: =(D35*$D$17)*Inputs!$B$8*$B$13*Inputs!$B$9*$F$17 -> 0 | E38: =(E35*$D$17)*Inputs!$B$8*$B$13*Inputs!$B$9*$F$17 -> 0 | F38: =(F35*$D$17)*Inputs!$B$8*$B$13*Inputs!$B$9*$F$17 -> 0 | G38: =(G35*$D$17)*Inputs!$B$8*$B$13*Inputs!$B$9*$F$17 -> 0 | H38: =(H35*$D$17)*Inputs!$B$8*$B$13*Inputs!$B$9*$F$17 -> 0 | I38: =(I35*$D$17)*Inputs!$B$8*$B$13*Inputs!$B$9*$F$17 -> 0 | ... M38: =(M35*$D$17)*Inputs!$B$8*$B$13*Inputs!$B$9*$F$17 -> 0
A39: Free | Variable service expense | B39: =B37/1000*(Inputs!$B$19+Inputs!$B$20+Inputs!$B$21+Inputs!$B$22+Inputs!$B$23+Inputs!$B$24)+B38*((((Inputs!$B$10*Inputs!$B$15+Inputs!$B$11*Inputs!$B$16)*(1-Inputs!$B$14)+(Inputs!$B$10*Inputs!$B$17+Inputs!$B$11*Inputs!$B$18)*Inputs!$B$14)/1000000*Inputs!$B$12)*$B$11+Inputs!$B$12*Inputs!$B$13)+(B35*$D$17)*Inputs!$B$25*Inputs!$B$26+((B35*$D$17)*Inputs!$B$8*$B$13)*Inputs!$B$27*Inputs!$B$28+B36*(Inputs!$B$29+Inputs!$B$31) -> 8.92032 | C39: =C37/1000*(Inputs!$B$19+Inputs!$B$20+Inputs!$B$21+Inputs!$B$22+Inputs!$B$23+Inputs!$B$24)+C38*((((Inputs!$B$10*Inputs!$B$15+Inputs!$B$11*Inputs!$B$16)*(1-Inputs!$B$14)+(Inputs!$B$10*Inputs!$B$17+Inputs!$B$11*Inputs!$B$18)*Inputs!$B$14)/1000000*Inputs!$B$12)*$B$11+Inputs!$B$12*Inputs!$B$13)+(C35*$D$17)*Inputs!$B$25*Inputs!$B$26+((C35*$D$17)*Inputs!$B$8*$B$13)*Inputs!$B$27*Inputs!$B$28+C36*(Inputs!$B$29+Inputs!$B$31) -> 25.48446 | D39: =D37/1000*(Inputs!$B$19+Inputs!$B$20+Inputs!$B$21+Inputs!$B$22+Inputs!$B$23+Inputs!$B$24)+D38*((((Inputs!$B$10*Inputs!$B$15+Inputs!$B$11*Inputs!$B$16)*(1-Inputs!$B$14)+(Inputs!$B$10*Inputs!$B$17+Inputs!$B$11*Inputs!$B$18)*Inputs!$B$14)/1000000*Inputs!$B$12)*$B$11+Inputs!$B$12*Inputs!$B$13)+(D35*$D$17)*Inputs!$B$25*Inputs!$B$26+((D35*$D$17)*Inputs!$B$8*$B$13)*Inputs!$B$27*Inputs!$B$28+D36*(Inputs!$B$29+Inputs!$B$31) -> 42.973642 | E39: =E37/1000*(Inputs!$B$19+Inputs!$B$20+Inputs!$B$21+Inputs!$B$22+Inputs!$B$23+Inputs!$B$24)+E38*((((Inputs!$B$10*Inputs!$B$15+Inputs!$B$11*Inputs!$B$16)*(1-Inputs!$B$14)+(Inputs!$B$10*Inputs!$B$17+Inputs!$B$11*Inputs!$B$18)*Inputs!$B$14)/1000000*Inputs!$B$12)*$B$11+Inputs!$B$12*Inputs!$B$13)+(E35*$D$17)*Inputs!$B$25*Inputs!$B$26+((E35*$D$17)*Inputs!$B$8*$B$13)*Inputs!$B$27*Inputs!$B$28+E36*(Inputs!$B$29+Inputs!$B$31) -> 59.194128 | F39: =F37/1000*(Inputs!$B$19+Inputs!$B$20+Inputs!$B$21+Inputs!$B$22+Inputs!$B$23+Inputs!$B$24)+F38*((((Inputs!$B$10*Inputs!$B$15+Inputs!$B$11*Inputs!$B$16)*(1-Inputs!$B$14)+(Inputs!$B$10*Inputs!$B$17+Inputs!$B$11*Inputs!$B$18)*Inputs!$B$14)/1000000*Inputs!$B$12)*$B$11+Inputs!$B$12*Inputs!$B$13)+(F35*$D$17)*Inputs!$B$25*Inputs!$B$26+((F35*$D$17)*Inputs!$B$8*$B$13)*Inputs!$B$27*Inputs!$B$28+F36*(Inputs!$B$29+Inputs!$B$31) -> 68.123831 | G39: =G37/1000*(Inputs!$B$19+Inputs!$B$20+Inputs!$B$21+Inputs!$B$22+Inputs!$B$23+Inputs!$B$24)+G38*((((Inputs!$B$10*Inputs!$B$15+Inputs!$B$11*Inputs!$B$16)*(1-Inputs!$B$14)+(Inputs!$B$10*Inputs!$B$17+Inputs!$B$11*Inputs!$B$18)*Inputs!$B$14)/1000000*Inputs!$B$12)*$B$11+Inputs!$B$12*Inputs!$B$13)+(G35*$D$17)*Inputs!$B$25*Inputs!$B$26+((G35*$D$17)*Inputs!$B$8*$B$13)*Inputs!$B$27*Inputs!$B$28+G36*(Inputs!$B$29+Inputs!$B$31) -> 91.387471 | H39: =H37/1000*(Inputs!$B$19+Inputs!$B$20+Inputs!$B$21+Inputs!$B$22+Inputs!$B$23+Inputs!$B$24)+H38*((((Inputs!$B$10*Inputs!$B$15+Inputs!$B$11*Inputs!$B$16)*(1-Inputs!$B$14)+(Inputs!$B$10*Inputs!$B$17+Inputs!$B$11*Inputs!$B$18)*Inputs!$B$14)/1000000*Inputs!$B$12)*$B$11+Inputs!$B$12*Inputs!$B$13)+(H35*$D$17)*Inputs!$B$25*Inputs!$B$26+((H35*$D$17)*Inputs!$B$8*$B$13)*Inputs!$B$27*Inputs!$B$28+H36*(Inputs!$B$29+Inputs!$B$31) -> 104.44487 | I39: =I37/1000*(Inputs!$B$19+Inputs!$B$20+Inputs!$B$21+Inputs!$B$22+Inputs!$B$23+Inputs!$B$24)+I38*((((Inputs!$B$10*Inputs!$B$15+Inputs!$B$11*Inputs!$B$16)*(1-Inputs!$B$14)+(Inputs!$B$10*Inputs!$B$17+Inputs!$B$11*Inputs!$B$18)*Inputs!$B$14)/1000000*Inputs!$B$12)*$B$11+Inputs!$B$12*Inputs!$B$13)+(I35*$D$17)*Inputs!$B$25*Inputs!$B$26+((I35*$D$17)*Inputs!$B$8*$B$13)*Inputs!$B$27*Inputs!$B$28+I36*(Inputs!$B$29+Inputs!$B$31) -> 124.8573 | ... M39: =M37/1000*(Inputs!$B$19+Inputs!$B$20+Inputs!$B$21+Inputs!$B$22+Inputs!$B$23+Inputs!$B$24)+M38*((((Inputs!$B$10*Inputs!$B$15+Inputs!$B$11*Inputs!$B$16)*(1-Inputs!$B$14)+(Inputs!$B$10*Inputs!$B$17+Inputs!$B$11*Inputs!$B$18)*Inputs!$B$14)/1000000*Inputs!$B$12)*$B$11+Inputs!$B$12*Inputs!$B$13)+(M35*$D$17)*Inputs!$B$25*Inputs!$B$26+((M35*$D$17)*Inputs!$B$8*$B$13)*Inputs!$B$27*Inputs!$B$28+M36*(Inputs!$B$29+Inputs!$B$31) -> 196.34127
A41: Starter | Opening accounts | B41: =0 -> 0 | C41: =B44 -> 7.2 | D41: =C44 -> 14.832 | E41: =D44 -> 22.95072 | F41: =E44 -> 31.615891 | G41: =F44 -> 40.892776 | H41: =G44 -> 50.852737 | I41: =H44 -> 61.573866 | J41: =I44 -> 73.141675 | ... M41: =L44 -> 113.90798
A42: Starter | New accounts | B42: =B27*$C$18 -> 7.2 | C42: =C27*$C$18 -> 7.92 | D42: =D27*$C$18 -> 8.712 | E42: =E27*$C$18 -> 9.5832 | F42: =F27*$C$18 -> 10.54152 | G42: =G27*$C$18 -> 11.595672 | H42: =H27*$C$18 -> 12.755239 | I42: =I27*$C$18 -> 14.030763 | ... M42: =M27*$C$18 -> 20.54244
A43: Starter | Churned accounts | B43: =B41*$B$7 -> 0 | C43: =C41*$B$7 -> 0.288 | D43: =D41*$B$7 -> 0.59328 | E43: =E41*$B$7 -> 0.9180288 | F43: =F41*$B$7 -> 1.2646356 | G43: =G41*$B$7 -> 1.635711 | H43: =H41*$B$7 -> 2.0341095 | I43: =I41*$B$7 -> 2.4629547 | ... M43: =M41*$B$7 -> 4.5563192
A44: Starter | Ending accounts | B44: =B41+B42-B43 -> 7.2 | C44: =C41+C42-C43 -> 14.832 | D44: =D41+D42-D43 -> 22.95072 | E44: =E41+E42-E43 -> 31.615891 | F44: =F41+F42-F43 -> 40.892776 | G44: =G41+G42-G43 -> 50.852737 | H44: =H41+H42-H43 -> 61.573866 | I44: =I41+I42-I43 -> 73.141675 | ... M44: =M41+M42-M43 -> 129.8941
A45: Starter | Average accounts | B45: =(B41+B44)/2 -> 3.6 | C45: =(C41+C44)/2 -> 11.016 | D45: =(D41+D44)/2 -> 18.89136 | E45: =(E41+E44)/2 -> 27.283306 | F45: =(F41+F44)/2 -> 36.254333 | G45: =(G41+G44)/2 -> 45.872756 | H45: =(H41+H44)/2 -> 56.213301 | I45: =(I41+I44)/2 -> 67.357771 | ... M45: =(M41+M44)/2 -> 121.90104
A46: Starter | Revenue | B46: =B45*$B$18 -> 32.4 | C46: =C45*$B$18 -> 99.144 | D46: =D45*$B$18 -> 170.02224 | E46: =E45*$B$18 -> 245.54975 | F46: =F45*$B$18 -> 326.289 | G46: =G45*$B$18 -> 412.8548 | H46: =H45*$B$18 -> 505.91971 | I46: =I45*$B$18 -> 606.21993 | ... M46: =M45*$B$18 -> 1097.1094
A47: Starter | Monitoring checks | B47: =(B45*$D$18)*DAY(EOMONTH(B$25,0))*1440/$E$18*$B$12 -> 10713.6 | C47: =(C45*$D$18)*DAY(EOMONTH(C$25,0))*1440/$E$18*$B$12 -> 31726.08 | D47: =(D45*$D$18)*DAY(EOMONTH(D$25,0))*1440/$E$18*$B$12 -> 56220.687 | E47: =(E45*$D$18)*DAY(EOMONTH(E$25,0))*1440/$E$18*$B$12 -> 81195.117 | F47: =(F45*$D$18)*DAY(EOMONTH(F$25,0))*1440/$E$18*$B$12 -> 97451.648 | G47: =(G45*$D$18)*DAY(EOMONTH(G$25,0))*1440/$E$18*$B$12 -> 136517.32 | H47: =(H45*$D$18)*DAY(EOMONTH(H$25,0))*1440/$E$18*$B$12 -> 161894.31 | I47: =(I45*$D$18)*DAY(EOMONTH(I$25,0))*1440/$E$18*$B$12 -> 200456.73 | ... M47: =(M45*$D$18)*DAY(EOMONTH(M$25,0))*1440/$E$18*$B$12 -> 351074.99
A48: Starter | AI diagnoses | B48: =(B45*$D$18)*Inputs!$B$8*$B$13*Inputs!$B$9*$F$18 -> 0.864 | C48: =(C45*$D$18)*Inputs!$B$8*$B$13*Inputs!$B$9*$F$18 -> 2.64384 | D48: =(D45*$D$18)*Inputs!$B$8*$B$13*Inputs!$B$9*$F$18 -> 4.5339264 | E48: =(E45*$D$18)*Inputs!$B$8*$B$13*Inputs!$B$9*$F$18 -> 6.5479933 | F48: =(F45*$D$18)*Inputs!$B$8*$B$13*Inputs!$B$9*$F$18 -> 8.70104 | G48: =(G45*$D$18)*Inputs!$B$8*$B$13*Inputs!$B$9*$F$18 -> 11.009461 | H48: =(H45*$D$18)*Inputs!$B$8*$B$13*Inputs!$B$9*$F$18 -> 13.491192 | I48: =(I45*$D$18)*Inputs!$B$8*$B$13*Inputs!$B$9*$F$18 -> 16.165865 | ... M48: =(M45*$D$18)*Inputs!$B$8*$B$13*Inputs!$B$9*$F$18 -> 29.25625
A49: Starter | Variable service expense | B49: =B47/1000*(Inputs!$B$19+Inputs!$B$20+Inputs!$B$21+Inputs!$B$22+Inputs!$B$23+Inputs!$B$24)+B48*((((Inputs!$B$10*Inputs!$B$15+Inputs!$B$11*Inputs!$B$16)*(1-Inputs!$B$14)+(Inputs!$B$10*Inputs!$B$17+Inputs!$B$11*Inputs!$B$18)*Inputs!$B$14)/1000000*Inputs!$B$12)*$B$11+Inputs!$B$12*Inputs!$B$13)+(B45*$D$18)*Inputs!$B$25*Inputs!$B$26+((B45*$D$18)*Inputs!$B$8*$B$13)*Inputs!$B$27*Inputs!$B$28+B46*(Inputs!$B$29+Inputs!$B$31)+B44*Inputs!$B$30+B45*Inputs!$B$32 -> 6.9732403 | C49: =C47/1000*(Inputs!$B$19+Inputs!$B$20+Inputs!$B$21+Inputs!$B$22+Inputs!$B$23+Inputs!$B$24)+C48*((((Inputs!$B$10*Inputs!$B$15+Inputs!$B$11*Inputs!$B$16)*(1-Inputs!$B$14)+(Inputs!$B$10*Inputs!$B$17+Inputs!$B$11*Inputs!$B$18)*Inputs!$B$14)/1000000*Inputs!$B$12)*$B$11+Inputs!$B$12*Inputs!$B$13)+(C45*$D$18)*Inputs!$B$25*Inputs!$B$26+((C45*$D$18)*Inputs!$B$8*$B$13)*Inputs!$B$27*Inputs!$B$28+C46*(Inputs!$B$29+Inputs!$B$31)+C44*Inputs!$B$30+C45*Inputs!$B$32 -> 18.998334 | D49: =D47/1000*(Inputs!$B$19+Inputs!$B$20+Inputs!$B$21+Inputs!$B$22+Inputs!$B$23+Inputs!$B$24)+D48*((((Inputs!$B$10*Inputs!$B$15+Inputs!$B$11*Inputs!$B$16)*(1-Inputs!$B$14)+(Inputs!$B$10*Inputs!$B$17+Inputs!$B$11*Inputs!$B$18)*Inputs!$B$14)/1000000*Inputs!$B$12)*$B$11+Inputs!$B$12*Inputs!$B$13)+(D45*$D$18)*Inputs!$B$25*Inputs!$B$26+((D45*$D$18)*Inputs!$B$8*$B$13)*Inputs!$B$27*Inputs!$B$28+D46*(Inputs!$B$29+Inputs!$B$31)+D44*Inputs!$B$30+D45*Inputs!$B$32 -> 32.143176 | E49: =E47/1000*(Inputs!$B$19+Inputs!$B$20+Inputs!$B$21+Inputs!$B$22+Inputs!$B$23+Inputs!$B$24)+E48*((((Inputs!$B$10*Inputs!$B$15+Inputs!$B$11*Inputs!$B$16)*(1-Inputs!$B$14)+(Inputs!$B$10*Inputs!$B$17+Inputs!$B$11*Inputs!$B$18)*Inputs!$B$14)/1000000*Inputs!$B$12)*$B$11+Inputs!$B$12*Inputs!$B$13)+(E45*$D$18)*Inputs!$B$25*Inputs!$B$26+((E45*$D$18)*Inputs!$B$8*$B$13)*Inputs!$B$27*Inputs!$B$28+E46*(Inputs!$B$29+Inputs!$B$31)+E44*Inputs!$B$30+E45*Inputs!$B$32 -> 45.962853 | F49: =F47/1000*(Inputs!$B$19+Inputs!$B$20+Inputs!$B$21+Inputs!$B$22+Inputs!$B$23+Inputs!$B$24)+F48*((((Inputs!$B$10*Inputs!$B$15+Inputs!$B$11*Inputs!$B$16)*(1-Inputs!$B$14)+(Inputs!$B$10*Inputs!$B$17+Inputs!$B$11*Inputs!$B$18)*Inputs!$B$14)/1000000*Inputs!$B$12)*$B$11+Inputs!$B$12*Inputs!$B$13)+(F45*$D$18)*Inputs!$B$25*Inputs!$B$26+((F45*$D$18)*Inputs!$B$8*$B$13)*Inputs!$B$27*Inputs!$B$28+F46*(Inputs!$B$29+Inputs!$B$31)+F44*Inputs!$B$30+F45*Inputs!$B$32 -> 58.96527 | G49: =G47/1000*(Inputs!$B$19+Inputs!$B$20+Inputs!$B$21+Inputs!$B$22+Inputs!$B$23+Inputs!$B$24)+G48*((((Inputs!$B$10*Inputs!$B$15+Inputs!$B$11*Inputs!$B$16)*(1-Inputs!$B$14)+(Inputs!$B$10*Inputs!$B$17+Inputs!$B$11*Inputs!$B$18)*Inputs!$B$14)/1000000*Inputs!$B$12)*$B$11+Inputs!$B$12*Inputs!$B$13)+(G45*$D$18)*Inputs!$B$25*Inputs!$B$26+((G45*$D$18)*Inputs!$B$8*$B$13)*Inputs!$B$27*Inputs!$B$28+G46*(Inputs!$B$29+Inputs!$B$31)+G44*Inputs!$B$30+G45*Inputs!$B$32 -> 76.58821 | H49: =H47/1000*(Inputs!$B$19+Inputs!$B$20+Inputs!$B$21+Inputs!$B$22+Inputs!$B$23+Inputs!$B$24)+H48*((((Inputs!$B$10*Inputs!$B$15+Inputs!$B$11*Inputs!$B$16)*(1-Inputs!$B$14)+(Inputs!$B$10*Inputs!$B$17+Inputs!$B$11*Inputs!$B$18)*Inputs!$B$14)/1000000*Inputs!$B$12)*$B$11+Inputs!$B$12*Inputs!$B$13)+(H45*$D$18)*Inputs!$B$25*Inputs!$B$26+((H45*$D$18)*Inputs!$B$8*$B$13)*Inputs!$B$27*Inputs!$B$28+H46*(Inputs!$B$29+Inputs!$B$31)+H44*Inputs!$B$30+H45*Inputs!$B$32 -> 92.712572 | I49: =I47/1000*(Inputs!$B$19+Inputs!$B$20+Inputs!$B$21+Inputs!$B$22+Inputs!$B$23+Inputs!$B$24)+I48*((((Inputs!$B$10*Inputs!$B$15+Inputs!$B$11*Inputs!$B$16)*(1-Inputs!$B$14)+(Inputs!$B$10*Inputs!$B$17+Inputs!$B$11*Inputs!$B$18)*Inputs!$B$14)/1000000*Inputs!$B$12)*$B$11+Inputs!$B$12*Inputs!$B$13)+(I45*$D$18)*Inputs!$B$25*Inputs!$B$26+((I45*$D$18)*Inputs!$B$8*$B$13)*Inputs!$B$27*Inputs!$B$28+I46*(Inputs!$B$29+Inputs!$B$31)+I44*Inputs!$B$30+I45*Inputs!$B$32 -> 112.0006 | ... M49: =M47/1000*(Inputs!$B$19+Inputs!$B$20+Inputs!$B$21+Inputs!$B$22+Inputs!$B$23+Inputs!$B$24)+M48*((((Inputs!$B$10*Inputs!$B$15+Inputs!$B$11*Inputs!$B$16)*(1-Inputs!$B$14)+(Inputs!$B$10*Inputs!$B$17+Inputs!$B$11*Inputs!$B$18)*Inputs!$B$14)/1000000*Inputs!$B$12)*$B$11+Inputs!$B$12*Inputs!$B$13)+(M45*$D$18)*Inputs!$B$25*Inputs!$B$26+((M45*$D$18)*Inputs!$B$8*$B$13)*Inputs!$B$27*Inputs!$B$28+M46*(Inputs!$B$29+Inputs!$B$31)+M44*Inputs!$B$30+M45*Inputs!$B$32 -> 199.96186
A51: Pro | Opening accounts | B51: =0 -> 0 | C51: =B54 -> 3.6 | D51: =C54 -> 7.416 | E51: =D54 -> 11.47536 | F51: =E54 -> 15.807946 | G51: =F54 -> 20.446388 | H51: =G54 -> 25.426368 | I51: =H54 -> 30.786933 | J51: =I54 -> 36.570837 | ... M51: =L54 -> 56.95399
A52: Pro | New accounts | B52: =B27*$C$19 -> 3.6 | C52: =C27*$C$19 -> 3.96 | D52: =D27*$C$19 -> 4.356 | E52: =E27*$C$19 -> 4.7916 | F52: =F27*$C$19 -> 5.27076 | G52: =G27*$C$19 -> 5.797836 | H52: =H27*$C$19 -> 6.3776196 | I52: =I27*$C$19 -> 7.0153816 | ... M52: =M27*$C$19 -> 10.27122
A53: Pro | Churned accounts | B53: =B51*$B$7 -> 0 | C53: =C51*$B$7 -> 0.144 | D53: =D51*$B$7 -> 0.29664 | E53: =E51*$B$7 -> 0.4590144 | F53: =F51*$B$7 -> 0.63231782 | G53: =G51*$B$7 -> 0.81785551 | H53: =H51*$B$7 -> 1.0170547 | I53: =I51*$B$7 -> 1.2314773 | ... M53: =M51*$B$7 -> 2.2781596
A54: Pro | Ending accounts | B54: =B51+B52-B53 -> 3.6 | C54: =C51+C52-C53 -> 7.416 | D54: =D51+D52-D53 -> 11.47536 | E54: =E51+E52-E53 -> 15.807946 | F54: =F51+F52-F53 -> 20.446388 | G54: =G51+G52-G53 -> 25.426368 | H54: =H51+H52-H53 -> 30.786933 | I54: =I51+I52-I53 -> 36.570837 | ... M54: =M51+M52-M53 -> 64.94705
A55: Pro | Average accounts | B55: =(B51+B54)/2 -> 1.8 | C55: =(C51+C54)/2 -> 5.508 | D55: =(D51+D54)/2 -> 9.44568 | E55: =(E51+E54)/2 -> 13.641653 | F55: =(F51+F54)/2 -> 18.127167 | G55: =(G51+G54)/2 -> 22.936378 | H55: =(H51+H54)/2 -> 28.106651 | I55: =(I51+I54)/2 -> 33.678885 | ... M55: =(M51+M54)/2 -> 60.95052
A56: Pro | Revenue | B56: =B55*$B$19 -> 52.2 | C56: =C55*$B$19 -> 159.732 | D56: =D55*$B$19 -> 273.92472 | E56: =E55*$B$19 -> 395.60793 | F56: =F55*$B$19 -> 525.68783 | G56: =G55*$B$19 -> 665.15496 | H56: =H55*$B$19 -> 815.09287 | I56: =I55*$B$19 -> 976.68767 | ... M56: =M55*$B$19 -> 1767.5651
A57: Pro | Monitoring checks | B57: =(B55*$D$19)*DAY(EOMONTH(B$25,0))*1440/$E$19*$B$12 -> 48211.2 | C57: =(C55*$D$19)*DAY(EOMONTH(C$25,0))*1440/$E$19*$B$12 -> 142767.36 | D57: =(D55*$D$19)*DAY(EOMONTH(D$25,0))*1440/$E$19*$B$12 -> 252993.09 | E57: =(E55*$D$19)*DAY(EOMONTH(E$25,0))*1440/$E$19*$B$12 -> 365378.03 | F57: =(F55*$D$19)*DAY(EOMONTH(F$25,0))*1440/$E$19*$B$12 -> 438532.42 | G57: =(G55*$D$19)*DAY(EOMONTH(G$25,0))*1440/$E$19*$B$12 -> 614327.95 | H57: =(H55*$D$19)*DAY(EOMONTH(H$25,0))*1440/$E$19*$B$12 -> 728524.39 | I57: =(I55*$D$19)*DAY(EOMONTH(I$25,0))*1440/$E$19*$B$12 -> 902055.26 | ... M57: =(M55*$D$19)*DAY(EOMONTH(M$25,0))*1440/$E$19*$B$12 -> 1579837.5
A58: Pro | AI diagnoses | B58: =(B55*$D$19)*Inputs!$B$8*$B$13*Inputs!$B$9*$F$19 -> 1.296 | C58: =(C55*$D$19)*Inputs!$B$8*$B$13*Inputs!$B$9*$F$19 -> 3.96576 | D58: =(D55*$D$19)*Inputs!$B$8*$B$13*Inputs!$B$9*$F$19 -> 6.8008896 | E58: =(E55*$D$19)*Inputs!$B$8*$B$13*Inputs!$B$9*$F$19 -> 9.82199 | F58: =(F55*$D$19)*Inputs!$B$8*$B$13*Inputs!$B$9*$F$19 -> 13.05156 | G58: =(G55*$D$19)*Inputs!$B$8*$B$13*Inputs!$B$9*$F$19 -> 16.514192 | H58: =(H55*$D$19)*Inputs!$B$8*$B$13*Inputs!$B$9*$F$19 -> 20.236789 | I58: =(I55*$D$19)*Inputs!$B$8*$B$13*Inputs!$B$9*$F$19 -> 24.248797 | ... M58: =(M55*$D$19)*Inputs!$B$8*$B$13*Inputs!$B$9*$F$19 -> 43.884374
A59: Pro | Variable service expense | B59: =B57/1000*(Inputs!$B$19+Inputs!$B$20+Inputs!$B$21+Inputs!$B$22+Inputs!$B$23+Inputs!$B$24)+B58*((((Inputs!$B$10*Inputs!$B$15+Inputs!$B$11*Inputs!$B$16)*(1-Inputs!$B$14)+(Inputs!$B$10*Inputs!$B$17+Inputs!$B$11*Inputs!$B$18)*Inputs!$B$14)/1000000*Inputs!$B$12)*$B$11+Inputs!$B$12*Inputs!$B$13)+(B55*$D$19)*Inputs!$B$25*Inputs!$B$26+((B55*$D$19)*Inputs!$B$8*$B$13)*Inputs!$B$27*Inputs!$B$28+B56*(Inputs!$B$29+Inputs!$B$31)+B54*Inputs!$B$30+B55*Inputs!$B$32 -> 12.093396 | C59: =C57/1000*(Inputs!$B$19+Inputs!$B$20+Inputs!$B$21+Inputs!$B$22+Inputs!$B$23+Inputs!$B$24)+C58*((((Inputs!$B$10*Inputs!$B$15+Inputs!$B$11*Inputs!$B$16)*(1-Inputs!$B$14)+(Inputs!$B$10*Inputs!$B$17+Inputs!$B$11*Inputs!$B$18)*Inputs!$B$14)/1000000*Inputs!$B$12)*$B$11+Inputs!$B$12*Inputs!$B$13)+(C55*$D$19)*Inputs!$B$25*Inputs!$B$26+((C55*$D$19)*Inputs!$B$8*$B$13)*Inputs!$B$27*Inputs!$B$28+C56*(Inputs!$B$29+Inputs!$B$31)+C54*Inputs!$B$30+C55*Inputs!$B$32 -> 35.116778 | D59: =D57/1000*(Inputs!$B$19+Inputs!$B$20+Inputs!$B$21+Inputs!$B$22+Inputs!$B$23+Inputs!$B$24)+D58*((((Inputs!$B$10*Inputs!$B$15+Inputs!$B$11*Inputs!$B$16)*(1-Inputs!$B$14)+(Inputs!$B$10*Inputs!$B$17+Inputs!$B$11*Inputs!$B$18)*Inputs!$B$14)/1000000*Inputs!$B$12)*$B$11+Inputs!$B$12*Inputs!$B$13)+(D55*$D$19)*Inputs!$B$25*Inputs!$B$26+((D55*$D$19)*Inputs!$B$8*$B$13)*Inputs!$B$27*Inputs!$B$28+D56*(Inputs!$B$29+Inputs!$B$31)+D54*Inputs!$B$30+D55*Inputs!$B$32 -> 61.236507 | E59: =E57/1000*(Inputs!$B$19+Inputs!$B$20+Inputs!$B$21+Inputs!$B$22+Inputs!$B$23+Inputs!$B$24)+E58*((((Inputs!$B$10*Inputs!$B$15+Inputs!$B$11*Inputs!$B$16)*(1-Inputs!$B$14)+(Inputs!$B$10*Inputs!$B$17+Inputs!$B$11*Inputs!$B$18)*Inputs!$B$14)/1000000*Inputs!$B$12)*$B$11+Inputs!$B$12*Inputs!$B$13)+(E55*$D$19)*Inputs!$B$25*Inputs!$B$26+((E55*$D$19)*Inputs!$B$8*$B$13)*Inputs!$B$27*Inputs!$B$28+E56*(Inputs!$B$29+Inputs!$B$31)+E54*Inputs!$B$30+E55*Inputs!$B$32 -> 88.209568 | F59: =F57/1000*(Inputs!$B$19+Inputs!$B$20+Inputs!$B$21+Inputs!$B$22+Inputs!$B$23+Inputs!$B$24)+F58*((((Inputs!$B$10*Inputs!$B$15+Inputs!$B$11*Inputs!$B$16)*(1-Inputs!$B$14)+(Inputs!$B$10*Inputs!$B$17+Inputs!$B$11*Inputs!$B$18)*Inputs!$B$14)/1000000*Inputs!$B$12)*$B$11+Inputs!$B$12*Inputs!$B$13)+(F55*$D$19)*Inputs!$B$25*Inputs!$B$26+((F55*$D$19)*Inputs!$B$8*$B$13)*Inputs!$B$27*Inputs!$B$28+F56*(Inputs!$B$29+Inputs!$B$31)+F54*Inputs!$B$30+F55*Inputs!$B$32 -> 109.0584 | G59: =G57/1000*(Inputs!$B$19+Inputs!$B$20+Inputs!$B$21+Inputs!$B$22+Inputs!$B$23+Inputs!$B$24)+G58*((((Inputs!$B$10*Inputs!$B$15+Inputs!$B$11*Inputs!$B$16)*(1-Inputs!$B$14)+(Inputs!$B$10*Inputs!$B$17+Inputs!$B$11*Inputs!$B$18)*Inputs!$B$14)/1000000*Inputs!$B$12)*$B$11+Inputs!$B$12*Inputs!$B$13)+(G55*$D$19)*Inputs!$B$25*Inputs!$B$26+((G55*$D$19)*Inputs!$B$8*$B$13)*Inputs!$B$27*Inputs!$B$28+G56*(Inputs!$B$29+Inputs!$B$31)+G54*Inputs!$B$30+G55*Inputs!$B$32 -> 147.96537 | H59: =H57/1000*(Inputs!$B$19+Inputs!$B$20+Inputs!$B$21+Inputs!$B$22+Inputs!$B$23+Inputs!$B$24)+H58*((((Inputs!$B$10*Inputs!$B$15+Inputs!$B$11*Inputs!$B$16)*(1-Inputs!$B$14)+(Inputs!$B$10*Inputs!$B$17+Inputs!$B$11*Inputs!$B$18)*Inputs!$B$14)/1000000*Inputs!$B$12)*$B$11+Inputs!$B$12*Inputs!$B$13)+(H55*$D$19)*Inputs!$B$25*Inputs!$B$26+((H55*$D$19)*Inputs!$B$8*$B$13)*Inputs!$B$27*Inputs!$B$28+H56*(Inputs!$B$29+Inputs!$B$31)+H54*Inputs!$B$30+H55*Inputs!$B$32 -> 177.07982 | I59: =I57/1000*(Inputs!$B$19+Inputs!$B$20+Inputs!$B$21+Inputs!$B$22+Inputs!$B$23+Inputs!$B$24)+I58*((((Inputs!$B$10*Inputs!$B$15+Inputs!$B$11*Inputs!$B$16)*(1-Inputs!$B$14)+(Inputs!$B$10*Inputs!$B$17+Inputs!$B$11*Inputs!$B$18)*Inputs!$B$14)/1000000*Inputs!$B$12)*$B$11+Inputs!$B$12*Inputs!$B$13)+(I55*$D$19)*Inputs!$B$25*Inputs!$B$26+((I55*$D$19)*Inputs!$B$8*$B$13)*Inputs!$B$27*Inputs!$B$28+I56*(Inputs!$B$29+Inputs!$B$31)+I54*Inputs!$B$30+I55*Inputs!$B$32 -> 217.03732 | ... M59: =M57/1000*(Inputs!$B$19+Inputs!$B$20+Inputs!$B$21+Inputs!$B$22+Inputs!$B$23+Inputs!$B$24)+M58*((((Inputs!$B$10*Inputs!$B$15+Inputs!$B$11*Inputs!$B$16)*(1-Inputs!$B$14)+(Inputs!$B$10*Inputs!$B$17+Inputs!$B$11*Inputs!$B$18)*Inputs!$B$14)/1000000*Inputs!$B$12)*$B$11+Inputs!$B$12*Inputs!$B$13)+(M55*$D$19)*Inputs!$B$25*Inputs!$B$26+((M55*$D$19)*Inputs!$B$8*$B$13)*Inputs!$B$27*Inputs!$B$28+M56*(Inputs!$B$29+Inputs!$B$31)+M54*Inputs!$B$30+M55*Inputs!$B$32 -> 383.46073
A61: Business | Opening accounts | B61: =0 -> 0 | C61: =B64 -> 1.2 | D61: =C64 -> 2.472 | E61: =D64 -> 3.82512 | F61: =E64 -> 5.2693152 | G61: =F64 -> 6.8154626 | H61: =G64 -> 8.4754561 | I61: =H64 -> 10.262311 | J61: =I64 -> 12.190279 | ... M61: =L64 -> 18.984663
A62: Business | New accounts | B62: =B27*$C$20 -> 1.2 | C62: =C27*$C$20 -> 1.32 | D62: =D27*$C$20 -> 1.452 | E62: =E27*$C$20 -> 1.5972 | F62: =F27*$C$20 -> 1.75692 | G62: =G27*$C$20 -> 1.932612 | H62: =H27*$C$20 -> 2.1258732 | I62: =I27*$C$20 -> 2.3384605 | ... M62: =M27*$C$20 -> 3.42374
A63: Business | Churned accounts | B63: =B61*$B$7 -> 0 | C63: =C61*$B$7 -> 0.048 | D63: =D61*$B$7 -> 0.09888 | E63: =E61*$B$7 -> 0.1530048 | F63: =F61*$B$7 -> 0.21077261 | G63: =G61*$B$7 -> 0.2726185 | H63: =H61*$B$7 -> 0.33901824 | I63: =I61*$B$7 -> 0.41049244 | ... M63: =M61*$B$7 -> 0.75938653
A64: Business | Ending accounts | B64: =B61+B62-B63 -> 1.2 | C64: =C61+C62-C63 -> 2.472 | D64: =D61+D62-D63 -> 3.82512 | E64: =E61+E62-E63 -> 5.2693152 | F64: =F61+F62-F63 -> 6.8154626 | G64: =G61+G62-G63 -> 8.4754561 | H64: =H61+H62-H63 -> 10.262311 | I64: =I61+I62-I63 -> 12.190279 | ... M64: =M61+M62-M63 -> 21.649017
A65: Business | Average accounts | B65: =(B61+B64)/2 -> 0.6 | C65: =(C61+C64)/2 -> 1.836 | D65: =(D61+D64)/2 -> 3.14856 | E65: =(E61+E64)/2 -> 4.5472176 | F65: =(F61+F64)/2 -> 6.0423889 | G65: =(G61+G64)/2 -> 7.6454593 | H65: =(H61+H64)/2 -> 9.3688836 | I65: =(I61+I64)/2 -> 11.226295 | ... M65: =(M61+M64)/2 -> 20.31684
A66: Business | Revenue | B66: =B65*$B$20 -> 59.4 | C66: =C65*$B$20 -> 181.764 | D66: =D65*$B$20 -> 311.70744 | E66: =E65*$B$20 -> 450.17454 | F66: =F65*$B$20 -> 598.1965 | G66: =G65*$B$20 -> 756.90047 | H66: =H65*$B$20 -> 927.51947 | I66: =I65*$B$20 -> 1111.4032 | ... M66: =M65*$B$20 -> 2011.3672
A67: Business | Monitoring checks | B67: =(B65*$D$20)*DAY(EOMONTH(B$25,0))*1440/$E$20*$B$12 -> 53568 | C67: =(C65*$D$20)*DAY(EOMONTH(C$25,0))*1440/$E$20*$B$12 -> 158630.4 | D67: =(D65*$D$20)*DAY(EOMONTH(D$25,0))*1440/$E$20*$B$12 -> 281103.44 | E67: =(E65*$D$20)*DAY(EOMONTH(E$25,0))*1440/$E$20*$B$12 -> 405975.59 | F67: =(F65*$D$20)*DAY(EOMONTH(F$25,0))*1440/$E$20*$B$12 -> 487258.24 | G67: =(G65*$D$20)*DAY(EOMONTH(G$25,0))*1440/$E$20*$B$12 -> 682586.61 | H67: =(H65*$D$20)*DAY(EOMONTH(H$25,0))*1440/$E$20*$B$12 -> 809471.54 | I67: =(I65*$D$20)*DAY(EOMONTH(I$25,0))*1440/$E$20*$B$12 -> 1002283.6 | ... M67: =(M65*$D$20)*DAY(EOMONTH(M$25,0))*1440/$E$20*$B$12 -> 1755375
A68: Business | AI diagnoses | B68: =(B65*$D$20)*Inputs!$B$8*$B$13*Inputs!$B$9*$F$20 -> 1.44 | C68: =(C65*$D$20)*Inputs!$B$8*$B$13*Inputs!$B$9*$F$20 -> 4.4064 | D68: =(D65*$D$20)*Inputs!$B$8*$B$13*Inputs!$B$9*$F$20 -> 7.556544 | E68: =(E65*$D$20)*Inputs!$B$8*$B$13*Inputs!$B$9*$F$20 -> 10.913322 | F68: =(F65*$D$20)*Inputs!$B$8*$B$13*Inputs!$B$9*$F$20 -> 14.501733 | G68: =(G65*$D$20)*Inputs!$B$8*$B$13*Inputs!$B$9*$F$20 -> 18.349102 | H68: =(H65*$D$20)*Inputs!$B$8*$B$13*Inputs!$B$9*$F$20 -> 22.485321 | I68: =(I65*$D$20)*Inputs!$B$8*$B$13*Inputs!$B$9*$F$20 -> 26.943108 | ... M68: =(M65*$D$20)*Inputs!$B$8*$B$13*Inputs!$B$9*$F$20 -> 48.760416
A69: Business | Variable service expense | B69: =B67/1000*(Inputs!$B$19+Inputs!$B$20+Inputs!$B$21+Inputs!$B$22+Inputs!$B$23+Inputs!$B$24)+B68*((((Inputs!$B$10*Inputs!$B$15+Inputs!$B$11*Inputs!$B$16)*(1-Inputs!$B$14)+(Inputs!$B$10*Inputs!$B$17+Inputs!$B$11*Inputs!$B$18)*Inputs!$B$14)/1000000*Inputs!$B$12)*$B$11+Inputs!$B$12*Inputs!$B$13)+(B65*$D$20)*Inputs!$B$25*Inputs!$B$26+((B65*$D$20)*Inputs!$B$8*$B$13)*Inputs!$B$27*Inputs!$B$28+B66*(Inputs!$B$29+Inputs!$B$31)+B64*Inputs!$B$30+B65*Inputs!$B$32 -> 11.947507 | C69: =C67/1000*(Inputs!$B$19+Inputs!$B$20+Inputs!$B$21+Inputs!$B$22+Inputs!$B$23+Inputs!$B$24)+C68*((((Inputs!$B$10*Inputs!$B$15+Inputs!$B$11*Inputs!$B$16)*(1-Inputs!$B$14)+(Inputs!$B$10*Inputs!$B$17+Inputs!$B$11*Inputs!$B$18)*Inputs!$B$14)/1000000*Inputs!$B$12)*$B$11+Inputs!$B$12*Inputs!$B$13)+(C65*$D$20)*Inputs!$B$25*Inputs!$B$26+((C65*$D$20)*Inputs!$B$8*$B$13)*Inputs!$B$27*Inputs!$B$28+C66*(Inputs!$B$29+Inputs!$B$31)+C64*Inputs!$B$30+C65*Inputs!$B$32 -> 35.300466 | D69: =D67/1000*(Inputs!$B$19+Inputs!$B$20+Inputs!$B$21+Inputs!$B$22+Inputs!$B$23+Inputs!$B$24)+D68*((((Inputs!$B$10*Inputs!$B$15+Inputs!$B$11*Inputs!$B$16)*(1-Inputs!$B$14)+(Inputs!$B$10*Inputs!$B$17+Inputs!$B$11*Inputs!$B$18)*Inputs!$B$14)/1000000*Inputs!$B$12)*$B$11+Inputs!$B$12*Inputs!$B$13)+(D65*$D$20)*Inputs!$B$25*Inputs!$B$26+((D65*$D$20)*Inputs!$B$8*$B$13)*Inputs!$B$27*Inputs!$B$28+D66*(Inputs!$B$29+Inputs!$B$31)+D64*Inputs!$B$30+D65*Inputs!$B$32 -> 61.954139 | E69: =E67/1000*(Inputs!$B$19+Inputs!$B$20+Inputs!$B$21+Inputs!$B$22+Inputs!$B$23+Inputs!$B$24)+E68*((((Inputs!$B$10*Inputs!$B$15+Inputs!$B$11*Inputs!$B$16)*(1-Inputs!$B$14)+(Inputs!$B$10*Inputs!$B$17+Inputs!$B$11*Inputs!$B$18)*Inputs!$B$14)/1000000*Inputs!$B$12)*$B$11+Inputs!$B$12*Inputs!$B$13)+(E65*$D$20)*Inputs!$B$25*Inputs!$B$26+((E65*$D$20)*Inputs!$B$8*$B$13)*Inputs!$B$27*Inputs!$B$28+E66*(Inputs!$B$29+Inputs!$B$31)+E64*Inputs!$B$30+E65*Inputs!$B$32 -> 89.398989 | F69: =F67/1000*(Inputs!$B$19+Inputs!$B$20+Inputs!$B$21+Inputs!$B$22+Inputs!$B$23+Inputs!$B$24)+F68*((((Inputs!$B$10*Inputs!$B$15+Inputs!$B$11*Inputs!$B$16)*(1-Inputs!$B$14)+(Inputs!$B$10*Inputs!$B$17+Inputs!$B$11*Inputs!$B$18)*Inputs!$B$14)/1000000*Inputs!$B$12)*$B$11+Inputs!$B$12*Inputs!$B$13)+(F65*$D$20)*Inputs!$B$25*Inputs!$B$26+((F65*$D$20)*Inputs!$B$8*$B$13)*Inputs!$B$27*Inputs!$B$28+F66*(Inputs!$B$29+Inputs!$B$31)+F64*Inputs!$B$30+F65*Inputs!$B$32 -> 109.86329 | G69: =G67/1000*(Inputs!$B$19+Inputs!$B$20+Inputs!$B$21+Inputs!$B$22+Inputs!$B$23+Inputs!$B$24)+G68*((((Inputs!$B$10*Inputs!$B$15+Inputs!$B$11*Inputs!$B$16)*(1-Inputs!$B$14)+(Inputs!$B$10*Inputs!$B$17+Inputs!$B$11*Inputs!$B$18)*Inputs!$B$14)/1000000*Inputs!$B$12)*$B$11+Inputs!$B$12*Inputs!$B$13)+(G65*$D$20)*Inputs!$B$25*Inputs!$B$26+((G65*$D$20)*Inputs!$B$8*$B$13)*Inputs!$B$27*Inputs!$B$28+G66*(Inputs!$B$29+Inputs!$B$31)+G64*Inputs!$B$30+G65*Inputs!$B$32 -> 150.19566 | H69: =H67/1000*(Inputs!$B$19+Inputs!$B$20+Inputs!$B$21+Inputs!$B$22+Inputs!$B$23+Inputs!$B$24)+H68*((((Inputs!$B$10*Inputs!$B$15+Inputs!$B$11*Inputs!$B$16)*(1-Inputs!$B$14)+(Inputs!$B$10*Inputs!$B$17+Inputs!$B$11*Inputs!$B$18)*Inputs!$B$14)/1000000*Inputs!$B$12)*$B$11+Inputs!$B$12*Inputs!$B$13)+(H65*$D$20)*Inputs!$B$25*Inputs!$B$26+((H65*$D$20)*Inputs!$B$8*$B$13)*Inputs!$B$27*Inputs!$B$28+H66*(Inputs!$B$29+Inputs!$B$31)+H64*Inputs!$B$30+H65*Inputs!$B$32 -> 179.42836 | I69: =I67/1000*(Inputs!$B$19+Inputs!$B$20+Inputs!$B$21+Inputs!$B$22+Inputs!$B$23+Inputs!$B$24)+I68*((((Inputs!$B$10*Inputs!$B$15+Inputs!$B$11*Inputs!$B$16)*(1-Inputs!$B$14)+(Inputs!$B$10*Inputs!$B$17+Inputs!$B$11*Inputs!$B$18)*Inputs!$B$14)/1000000*Inputs!$B$12)*$B$11+Inputs!$B$12*Inputs!$B$13)+(I65*$D$20)*Inputs!$B$25*Inputs!$B$26+((I65*$D$20)*Inputs!$B$8*$B$13)*Inputs!$B$27*Inputs!$B$28+I66*(Inputs!$B$29+Inputs!$B$31)+I64*Inputs!$B$30+I65*Inputs!$B$32 -> 220.46504 | ... M69: =M67/1000*(Inputs!$B$19+Inputs!$B$20+Inputs!$B$21+Inputs!$B$22+Inputs!$B$23+Inputs!$B$24)+M68*((((Inputs!$B$10*Inputs!$B$15+Inputs!$B$11*Inputs!$B$16)*(1-Inputs!$B$14)+(Inputs!$B$10*Inputs!$B$17+Inputs!$B$11*Inputs!$B$18)*Inputs!$B$14)/1000000*Inputs!$B$12)*$B$11+Inputs!$B$12*Inputs!$B$13)+(M65*$D$20)*Inputs!$B$25*Inputs!$B$26+((M65*$D$20)*Inputs!$B$8*$B$13)*Inputs!$B$27*Inputs!$B$28+M66*(Inputs!$B$29+Inputs!$B$31)+M64*Inputs!$B$30+M65*Inputs!$B$32 -> 388.9168
A73: Paying customers ending | B73: =B44+B54+B64 -> 12 | C73: =C44+C54+C64 -> 24.72 | D73: =D44+D54+D64 -> 38.2512 | E73: =E44+E54+E64 -> 52.693152 | F73: =F44+F54+F64 -> 68.154626 | G73: =G44+G54+G64 -> 84.754561 | H73: =H44+H54+H64 -> 102.62311 | I73: =I44+I54+I64 -> 121.90279 | ... M73: =M44+M54+M64 -> 216.49017
A74: Paying customers average | B74: =B45+B55+B65 -> 6 | C74: =C45+C55+C65 -> 18.36 | D74: =D45+D55+D65 -> 31.4856 | E74: =E45+E55+E65 -> 45.472176 | F74: =F45+F55+F65 -> 60.423889 | G74: =G45+G55+G65 -> 76.454593 | H74: =H45+H55+H65 -> 93.688836 | I74: =I45+I55+I65 -> 112.26295 | ... M74: =M45+M55+M65 -> 203.1684
A75: Free customers ending | B75: =B34 -> 138 | C75: =C34 -> 269.1 | D75: =D34 -> 395.715 | E75: =E34 -> 520.03575 | F75: =F34 -> 644.07619 | G75: =G34 -> 769.71514 | H75: =H34 -> 898.73329 | I75: =I34 -> 1032.8463 | ... M75: =M34 -> 1653.895
A76: Exit MRR | B76: =B44*$B$18+B54*$B$19+B64*$B$20 -> 288 | C76: =C44*$B$18+C54*$B$19+C64*$B$20 -> 593.28 | D76: =D44*$B$18+D54*$B$19+D64*$B$20 -> 918.0288 | E76: =E44*$B$18+E54*$B$19+E64*$B$20 -> 1264.6356 | F76: =F44*$B$18+F54*$B$19+F64*$B$20 -> 1635.711 | G76: =G44*$B$18+G54*$B$19+G64*$B$20 -> 2034.1095 | H76: =H44*$B$18+H54*$B$19+H64*$B$20 -> 2462.9547 | I76: =I44*$B$18+I54*$B$19+I64*$B$20 -> 2925.667 | ... M76: =M44*$B$18+M54*$B$19+M64*$B$20 -> 5195.764
A77: Revenue | B77: =B36+B46+B56+B66 -> 144 | C77: =C36+C46+C56+C66 -> 440.64 | D77: =D36+D46+D56+D66 -> 755.6544 | E77: =E36+E46+E56+E66 -> 1091.3322 | F77: =F36+F46+F56+F66 -> 1450.1733 | G77: =G36+G46+G56+G66 -> 1834.9102 | H77: =H36+H46+H56+H66 -> 2248.5321 | I77: =I36+I46+I56+I66 -> 2694.3108 | ... M77: =M36+M46+M56+M66 -> 4876.0416
A78: Monitoring checks | B78: =B37+B47+B57+B67 -> 163828.8 | C78: =C37+C47+C57+C67 -> 479679.84 | D78: =D37+D47+D57+D67 -> 837628.4 | E78: =E37+E47+E57+E67 -> 1193208 | F78: =F37+F47+F57+F67 -> 1414383.9 | G78: =G37+G47+G57+G67 -> 1959362.3 | H78: =H37+H47+H57+H67 -> 2300531.7 | I78: =I37+I47+I57+I67 -> 2823343.2 | ... M78: =M37+M47+M57+M67 -> 4815406.6
A79: AI diagnoses | B79: =B38+B48+B58+B68 -> 3.6 | C79: =C38+C48+C58+C68 -> 11.016 | D79: =D38+D48+D58+D68 -> 18.89136 | E79: =E38+E48+E58+E68 -> 27.283306 | F79: =F38+F48+F58+F68 -> 36.254333 | G79: =G38+G48+G58+G68 -> 45.872756 | H79: =H38+H48+H58+H68 -> 56.213301 | I79: =I38+I48+I58+I68 -> 67.357771 | ... M79: =M38+M48+M58+M68 -> 121.90104
A80: Variable cost of revenue | B80: =B39+B49+B59+B69 -> 39.934464 | C80: =C39+C49+C59+C69 -> 114.90004 | D80: =D39+D49+D59+D69 -> 198.30746 | E80: =E39+E49+E59+E69 -> 282.76554 | F80: =F39+F49+F59+F69 -> 346.01079 | G80: =G39+G49+G59+G69 -> 466.13671 | H80: =H39+H49+H59+H69 -> 553.66563 | I80: =I39+I49+I59+I69 -> 674.36026 | ... M80: =M39+M49+M59+M69 -> 1168.6806
A81: Fixed platform cost | B81: =Inputs!$B$33+Inputs!$B$34+Inputs!$B$35+Inputs!$B$36+Inputs!$B$37+Inputs!$B$38+Inputs!$B$39 -> 100 | C81: =Inputs!$B$33+Inputs!$B$34+Inputs!$B$35+Inputs!$B$36+Inputs!$B$37+Inputs!$B$38+Inputs!$B$39 -> 100 | D81: =Inputs!$B$33+Inputs!$B$34+Inputs!$B$35+Inputs!$B$36+Inputs!$B$37+Inputs!$B$38+Inputs!$B$39 -> 100 | E81: =Inputs!$B$33+Inputs!$B$34+Inputs!$B$35+Inputs!$B$36+Inputs!$B$37+Inputs!$B$38+Inputs!$B$39 -> 100 | F81: =Inputs!$B$33+Inputs!$B$34+Inputs!$B$35+Inputs!$B$36+Inputs!$B$37+Inputs!$B$38+Inputs!$B$39 -> 100 | G81: =Inputs!$B$33+Inputs!$B$34+Inputs!$B$35+Inputs!$B$36+Inputs!$B$37+Inputs!$B$38+Inputs!$B$39 -> 100 | H81: =Inputs!$B$33+Inputs!$B$34+Inputs!$B$35+Inputs!$B$36+Inputs!$B$37+Inputs!$B$38+Inputs!$B$39 -> 100 | I81: =Inputs!$B$33+Inputs!$B$34+Inputs!$B$35+Inputs!$B$36+Inputs!$B$37+Inputs!$B$38+Inputs!$B$39 -> 100 | ... M81: =Inputs!$B$33+Inputs!$B$34+Inputs!$B$35+Inputs!$B$36+Inputs!$B$37+Inputs!$B$38+Inputs!$B$39 -> 100
A82: Capacity scaling cost | B82: =MAX(0,ROUNDUP((B35*$D$17+B45*$D$18+B55*$D$19+B65*$D$20)/Inputs!$B$40,0)-1)*Inputs!$B$41 -> 0 | C82: =MAX(0,ROUNDUP((C35*$D$17+C45*$D$18+C55*$D$19+C65*$D$20)/Inputs!$B$40,0)-1)*Inputs!$B$41 -> 0 | D82: =MAX(0,ROUNDUP((D35*$D$17+D45*$D$18+D55*$D$19+D65*$D$20)/Inputs!$B$40,0)-1)*Inputs!$B$41 -> 0 | E82: =MAX(0,ROUNDUP((E35*$D$17+E45*$D$18+E55*$D$19+E65*$D$20)/Inputs!$B$40,0)-1)*Inputs!$B$41 -> 100 | F82: =MAX(0,ROUNDUP((F35*$D$17+F45*$D$18+F55*$D$19+F65*$D$20)/Inputs!$B$40,0)-1)*Inputs!$B$41 -> 100 | G82: =MAX(0,ROUNDUP((G35*$D$17+G45*$D$18+G55*$D$19+G65*$D$20)/Inputs!$B$40,0)-1)*Inputs!$B$41 -> 100 | H82: =MAX(0,ROUNDUP((H35*$D$17+H45*$D$18+H55*$D$19+H65*$D$20)/Inputs!$B$40,0)-1)*Inputs!$B$41 -> 200 | I82: =MAX(0,ROUNDUP((I35*$D$17+I45*$D$18+I55*$D$19+I65*$D$20)/Inputs!$B$40,0)-1)*Inputs!$B$41 -> 200 | ... M82: =MAX(0,ROUNDUP((M35*$D$17+M45*$D$18+M55*$D$19+M65*$D$20)/Inputs!$B$40,0)-1)*Inputs!$B$41 -> 400
A83: Total cost of revenue | B83: =B80+B81+B82 -> 139.93446 | C83: =C80+C81+C82 -> 214.90004 | D83: =D80+D81+D82 -> 298.30746 | E83: =E80+E81+E82 -> 482.76554 | F83: =F80+F81+F82 -> 546.01079 | G83: =G80+G81+G82 -> 666.13671 | H83: =H80+H81+H82 -> 853.66563 | I83: =I80+I81+I82 -> 974.36026 | ... M83: =M80+M81+M82 -> 1668.6806
A84: Gross profit | B84: =B77-B83 -> 4.065536 | C84: =C77-C83 -> 225.73996 | D84: =D77-D83 -> 457.34694 | E84: =E77-E83 -> 608.56669 | F84: =F77-F83 -> 904.16255 | G84: =G77-G83 -> 1168.7735 | H84: =H77-H83 -> 1394.8664 | I84: =I77-I83 -> 1719.9506 | ... M84: =M77-M83 -> 3207.3609
A85: Gross margin | B85: =IFERROR(B84/B77,0) -> 0.028232889 | C85: =IFERROR(C84/C77,0) -> 0.5123002 | D85: =IFERROR(D84/D77,0) -> 0.60523294 | E85: =IFERROR(E84/E77,0) -> 0.5576365 | F85: =IFERROR(F84/F77,0) -> 0.62348584 | G85: =IFERROR(G84/G77,0) -> 0.63696496 | H85: =IFERROR(H84/H77,0) -> 0.62034536 | I85: =IFERROR(I84/I77,0) -> 0.63836383 | ... M85: =IFERROR(M84/M77,0) -> 0.65777965
A86: Acquisition expense | B86: =B27*$B$9 -> 480 | C86: =C27*$B$9 -> 528 | D86: =D27*$B$9 -> 580.8 | E86: =E27*$B$9 -> 638.88 | F86: =F27*$B$9 -> 702.768 | G86: =G27*$B$9 -> 773.0448 | H86: =H27*$B$9 -> 850.34928 | I86: =I27*$B$9 -> 935.38421 | ... M86: =M27*$B$9 -> 1369.496
A87: Contractors | B87: =IF(COLUMN()-1>=Inputs!$B$44,Inputs!$B$43,0) -> 0 | C87: =IF(COLUMN()-1>=Inputs!$B$44,Inputs!$B$43,0) -> 0 | D87: =IF(COLUMN()-1>=Inputs!$B$44,Inputs!$B$43,0) -> 0 | E87: =IF(COLUMN()-1>=Inputs!$B$44,Inputs!$B$43,0) -> 1500 | F87: =IF(COLUMN()-1>=Inputs!$B$44,Inputs!$B$43,0) -> 1500 | G87: =IF(COLUMN()-1>=Inputs!$B$44,Inputs!$B$43,0) -> 1500 | H87: =IF(COLUMN()-1>=Inputs!$B$44,Inputs!$B$43,0) -> 1500 | I87: =IF(COLUMN()-1>=Inputs!$B$44,Inputs!$B$43,0) -> 1500 | ... M87: =IF(COLUMN()-1>=Inputs!$B$44,Inputs!$B$43,0) -> 1500
A88: Staff | B88: =IF(COLUMN()-1>=Inputs!$B$46,$B$10,0) -> 0 | C88: =IF(COLUMN()-1>=Inputs!$B$46,$B$10,0) -> 0 | D88: =IF(COLUMN()-1>=Inputs!$B$46,$B$10,0) -> 0 | E88: =IF(COLUMN()-1>=Inputs!$B$46,$B$10,0) -> 0 | F88: =IF(COLUMN()-1>=Inputs!$B$46,$B$10,0) -> 0 | G88: =IF(COLUMN()-1>=Inputs!$B$46,$B$10,0) -> 0 | H88: =IF(COLUMN()-1>=Inputs!$B$46,$B$10,0) -> 0 | I88: =IF(COLUMN()-1>=Inputs!$B$46,$B$10,0) -> 0 | ... M88: =IF(COLUMN()-1>=Inputs!$B$46,$B$10,0) -> 0
A89: Founder pay | B89: =Inputs!$B$47 -> 0 | C89: =Inputs!$B$47 -> 0 | D89: =Inputs!$B$47 -> 0 | E89: =Inputs!$B$47 -> 0 | F89: =Inputs!$B$47 -> 0 | G89: =Inputs!$B$47 -> 0 | H89: =Inputs!$B$47 -> 0 | I89: =Inputs!$B$47 -> 0 | ... M89: =Inputs!$B$47 -> 0
A90: Administration | B90: =Inputs!$B$42 -> 150 | C90: =Inputs!$B$42 -> 150 | D90: =Inputs!$B$42 -> 150 | E90: =Inputs!$B$42 -> 150 | F90: =Inputs!$B$42 -> 150 | G90: =Inputs!$B$42 -> 150 | H90: =Inputs!$B$42 -> 150 | I90: =Inputs!$B$42 -> 150 | ... M90: =Inputs!$B$42 -> 150
A91: Total operating expense | B91: =B86+B87+B88+B89+B90 -> 630 | C91: =C86+C87+C88+C89+C90 -> 678 | D91: =D86+D87+D88+D89+D90 -> 730.8 | E91: =E86+E87+E88+E89+E90 -> 2288.88 | F91: =F86+F87+F88+F89+F90 -> 2352.768 | G91: =G86+G87+G88+G89+G90 -> 2423.0448 | H91: =H86+H87+H88+H89+H90 -> 2500.3493 | I91: =I86+I87+I88+I89+I90 -> 2585.3842 | ... M91: =M86+M87+M88+M89+M90 -> 3019.496
A92: Operating profit / net cash flow | B92: =B84-B91 -> -625.93446 | C92: =C84-C91 -> -452.26004 | D92: =D84-D91 -> -273.45306 | E92: =E84-E91 -> -1680.3133 | F92: =F84-F91 -> -1448.6055 | G92: =G84-G91 -> -1254.2713 | H92: =H84-H91 -> -1105.4829 | I92: =I84-I91 -> -865.43364 | ... M92: =M84-M91 -> 187.86493
A93: Cumulative cash flow | B93: =0+B92 -> -625.93446 | C93: =B93+C92 -> -1078.1945 | D93: =C93+D92 -> -1351.6476 | E93: =D93+E92 -> -3031.9609 | F93: =E93+F92 -> -4480.5663 | G93: =F93+G92 -> -5734.8376 | H93: =G93+H92 -> -6840.3205 | I93: =H93+I92 -> -7705.7541 | J93: =I93+J92 -> -8280.7998 | ... M93: =L93+M92 -> -8575.0904
A94: Cash from editable starting cash | B94: =Inputs!$B$49+B93 -> 14374.066 | C94: =Inputs!$B$49+C93 -> 13921.805 | D94: =Inputs!$B$49+D93 -> 13648.352 | E94: =Inputs!$B$49+E93 -> 11968.039 | F94: =Inputs!$B$49+F93 -> 10519.434 | G94: =Inputs!$B$49+G93 -> 9265.1624 | H94: =Inputs!$B$49+H93 -> 8159.6795 | I94: =Inputs!$B$49+I93 -> 7294.2459 | ... M94: =Inputs!$B$49+M93 -> 6424.9096
A95: Cash from $5k | B95: =Inputs!$B$54+B93 -> 4374.0655 | C95: =Inputs!$B$54+C93 -> 3921.8055 | D95: =Inputs!$B$54+D93 -> 3648.3524 | E95: =Inputs!$B$54+E93 -> 1968.0391 | F95: =Inputs!$B$54+F93 -> 519.43367 | G95: =Inputs!$B$54+G93 -> -734.8376 | H95: =Inputs!$B$54+H93 -> -1840.3205 | I95: =Inputs!$B$54+I93 -> -2705.7541 | ... M95: =Inputs!$B$54+M93 -> -3575.0904
A96: Cash from $15k | B96: =Inputs!$B$55+B93 -> 14374.066 | C96: =Inputs!$B$55+C93 -> 13921.805 | D96: =Inputs!$B$55+D93 -> 13648.352 | E96: =Inputs!$B$55+E93 -> 11968.039 | F96: =Inputs!$B$55+F93 -> 10519.434 | G96: =Inputs!$B$55+G93 -> 9265.1624 | H96: =Inputs!$B$55+H93 -> 8159.6795 | I96: =Inputs!$B$55+I93 -> 7294.2459 | ... M96: =Inputs!$B$55+M93 -> 6424.9096
A97: Cash from $30k | B97: =Inputs!$B$56+B93 -> 29374.066 | C97: =Inputs!$B$56+C93 -> 28921.805 | D97: =Inputs!$B$56+D93 -> 28648.352 | E97: =Inputs!$B$56+E93 -> 26968.039 | F97: =Inputs!$B$56+F93 -> 25519.434 | G97: =Inputs!$B$56+G93 -> 24265.162 | H97: =Inputs!$B$56+H93 -> 23159.68 | I97: =Inputs!$B$56+I93 -> 22294.246 | ... M97: =Inputs!$B$56+M93 -> 21424.91
A98: ARPPU | B98: =IFERROR(B77/B74,0) -> 24 | C98: =IFERROR(C77/C74,0) -> 24 | D98: =IFERROR(D77/D74,0) -> 24 | E98: =IFERROR(E77/E74,0) -> 24 | F98: =IFERROR(F77/F74,0) -> 24 | G98: =IFERROR(G77/G74,0) -> 24 | H98: =IFERROR(H77/H74,0) -> 24 | I98: =IFERROR(I77/I74,0) -> 24 | ... M98: =IFERROR(M77/M74,0) -> 24
A99: ARPU all accounts | B99: =IFERROR(B77/(B35+B45+B55+B65),0) -> 1.92 | C99: =IFERROR(C77/(C35+C45+C55+C65),0) -> 1.9856699 | D99: =IFERROR(D77/(D35+D45+D55+D65),0) -> 2.0765835 | E99: =IFERROR(E77/(E35+E45+E55+E65),0) -> 2.1681485 | F99: =IFERROR(F77/(F35+F45+F55+F65),0) -> 2.2571499 | G99: =IFERROR(G77/(G35+G45+G55+G65),0) -> 2.342388 | H99: =IFERROR(H77/(H35+H45+H55+H65),0) -> 2.4232142 | I99: =IFERROR(I77/(I35+I45+I55+I65),0) -> 2.4992385 | ... M99: =IFERROR(M77/(M35+M45+M55+M65),0) -> 2.752665
A100: Cost per average paying account | B100: =IFERROR(B83/B74,0) -> 23.322411 | C100: =IFERROR(C83/C74,0) -> 11.704795 | D100: =IFERROR(D83/D74,0) -> 9.4744094 | E100: =IFERROR(E83/E74,0) -> 10.616724 | F100: =IFERROR(F83/F74,0) -> 9.0363397 | G100: =IFERROR(G83/G74,0) -> 8.7128409 | H100: =IFERROR(H83/H74,0) -> 9.1117114 | I100: =IFERROR(I83/I74,0) -> 8.6792682 | ... M100: =IFERROR(M83/M74,0) -> 8.2132883
A101: Gross profit per average paying account | B101: =B98-B100 -> 0.67758933 | C101: =C98-C100 -> 12.295205 | D101: =D98-D100 -> 14.525591 | E101: =E98-E100 -> 13.383276 | F101: =F98-F100 -> 14.96366 | G101: =G98-G100 -> 15.287159 | H101: =H98-H100 -> 14.888289 | I101: =I98-I100 -> 15.320732 | ... M101: =M98-M100 -> 15.786712
A102: LTV fully loaded | B102: =IF(B101>0,B101/$B$7,0) -> 16.939733 | C102: =IF(C101>0,C101/$B$7,0) -> 307.38012 | D102: =IF(D101>0,D101/$B$7,0) -> 363.13977 | E102: =IF(E101>0,E101/$B$7,0) -> 334.5819 | F102: =IF(F101>0,F101/$B$7,0) -> 374.09151 | G102: =IF(G101>0,G101/$B$7,0) -> 382.17898 | H102: =IF(H101>0,H101/$B$7,0) -> 372.20722 | I102: =IF(I101>0,I101/$B$7,0) -> 383.0183 | ... M102: =IF(M101>0,M101/$B$7,0) -> 394.66779
A103: LTV to CAC fully loaded | B103: =IF(B101>0,B102/$B$9,0) -> 0.42349333 | C103: =IF(C101>0,C102/$B$9,0) -> 7.684503 | D103: =IF(D101>0,D102/$B$9,0) -> 9.0784941 | E103: =IF(E101>0,E102/$B$9,0) -> 8.3645476 | F103: =IF(F101>0,F102/$B$9,0) -> 9.3522877 | G103: =IF(G101>0,G102/$B$9,0) -> 9.5544744 | H103: =IF(H101>0,H102/$B$9,0) -> 9.3051804 | I103: =IF(I101>0,I102/$B$9,0) -> 9.5754574 | ... M103: =IF(M101>0,M102/$B$9,0) -> 9.8666948
A104: CAC payback months | B104: =IF(B101>0,$B$9/B101,0) -> 59.032806 | C104: =IF(C101>0,$B$9/C101,0) -> 3.2533008 | D104: =IF(D101>0,$B$9/D101,0) -> 2.7537607 | E104: =IF(E101>0,$B$9/E101,0) -> 2.9888048 | F104: =IF(F101>0,$B$9/F101,0) -> 2.6731428 | G104: =IF(G101>0,$B$9/G101,0) -> 2.6165751 | H104: =IF(H101>0,$B$9/H101,0) -> 2.6866755 | I104: =IF(I101>0,$B$9/I101,0) -> 2.6108413 | ... M104: =IF(M101>0,$B$9/M101,0) -> 2.5337766
A105: Cash bridge check | B105: =B94-Inputs!$B$49-B93 -> 0 | C105: =C94-Inputs!$B$49-C93 -> 0 | D105: =D94-Inputs!$B$49-D93 -> 0 | E105: =E94-Inputs!$B$49-E93 -> 0 | F105: =F94-Inputs!$B$49-F93 -> 0 | G105: =G94-Inputs!$B$49-G93 -> 0 | H105: =H94-Inputs!$B$49-H93 -> 0 | I105: =I94-Inputs!$B$49-I93 -> 0 | ... M105: =M94-Inputs!$B$49-M93 -> 0

Sheet AI 2x
A1: AI 2x — hypothetical 12-month forecast
A4: Initial monthly signups | B4: =Inputs!$B$2 -> 150
A5: Monthly signup growth | B5: =Inputs!$B$3 -> 0.1
A6: Paid conversion rate | B6: =Inputs!$B$4 -> 0.08
A7: Monthly paid churn | B7: =Inputs!$B$5 -> 0.04
A8: Monthly free churn | B8: =Inputs!$B$6 -> 0.15
A9: Blended acquisition CAC | B9: =Inputs!$B$7 -> 40
A10: Staff monthly budget | B10: =Inputs!$B$45 -> 3000
A11: AI cost stress multiplier | B11: 2
A12: Monitoring frequency multiplier | B12: =Inputs!$B$51 -> 1
A13: Incident volume multiplier | B13: =Inputs!$B$52 -> 1
A17: Free | B17: =Pricing!B2 -> 0 | C17: =Pricing!C2 -> 0 | D17: =Pricing!D2 -> 1 | E17: =Pricing!E2 -> 15 | F17: =Pricing!F2 -> 0
A18: Starter | B18: =Pricing!B3 -> 9 | C18: =Pricing!C3 -> 0.6 | D18: =Pricing!D3 -> 3 | E18: =Pricing!E3 -> 5 | F18: =Pricing!F3 -> 1
A19: Pro | B19: =Pricing!B4 -> 29 | C19: =Pricing!C4 -> 0.3 | D19: =Pricing!D4 -> 10 | E19: =Pricing!E4 -> 5 | F19: =Pricing!F4 -> 1
A20: Business | B20: =Pricing!B5 -> 99 | C20: =Pricing!C5 -> 0.1 | D20: =Pricing!D5 -> 30 | E20: =Pricing!E5 -> 5 | F20: =Pricing!F5 -> 1
B25: 46296 | C25: 46327 | D25: 46357 | E25: 46388 | F25: 46419 | G25: 46447 | H25: 46478 | I25: 46508 | J25: 46539 | K25: 46569 | L25: 46600 | M25: 46631
A26: New signups | B26: =$B$4 -> 150 | C26: =B26*(1+$B$5) -> 165 | D26: =C26*(1+$B$5) -> 181.5 | E26: =D26*(1+$B$5) -> 199.65 | F26: =E26*(1+$B$5) -> 219.615 | G26: =F26*(1+$B$5) -> 241.5765 | H26: =G26*(1+$B$5) -> 265.73415 | I26: =H26*(1+$B$5) -> 292.30757 | J26: =I26*(1+$B$5) -> 321.53832 | ... M26: =L26*(1+$B$5) -> 427.96751
A27: New paid | B27: =B26*$B$6 -> 12 | C27: =C26*$B$6 -> 13.2 | D27: =D26*$B$6 -> 14.52 | E27: =E26*$B$6 -> 15.972 | F27: =F26*$B$6 -> 17.5692 | G27: =G26*$B$6 -> 19.32612 | H27: =H26*$B$6 -> 21.258732 | I27: =I26*$B$6 -> 23.384605 | ... M27: =M26*$B$6 -> 34.2374
A28: New free | B28: =B26-B27 -> 138 | C28: =C26-C27 -> 151.8 | D28: =D26-D27 -> 166.98 | E28: =E26-E27 -> 183.678 | F28: =F26-F27 -> 202.0458 | G28: =G26-G27 -> 222.25038 | H28: =H26-H27 -> 244.47542 | I28: =I26-I27 -> 268.92296 | ... M28: =M26-M27 -> 393.73011
A31: Free | Opening accounts | B31: =0 -> 0 | C31: =B34 -> 138 | D31: =C34 -> 269.1 | E31: =D34 -> 395.715 | F31: =E34 -> 520.03575 | G31: =F34 -> 644.07619 | H31: =G34 -> 769.71514 | I31: =H34 -> 898.73329 | J31: =I34 -> 1032.8463 | ... M31: =L34 -> 1482.547
A32: Free | New accounts | B32: =B28 -> 138 | C32: =C28 -> 151.8 | D32: =D28 -> 166.98 | E32: =E28 -> 183.678 | F32: =F28 -> 202.0458 | G32: =G28 -> 222.25038 | H32: =H28 -> 244.47542 | I32: =I28 -> 268.92296 | ... M32: =M28 -> 393.73011
A33: Free | Churned accounts | B33: =B31*$B$8 -> 0 | C33: =C31*$B$8 -> 20.7 | D33: =D31*$B$8 -> 40.365 | E33: =E31*$B$8 -> 59.35725 | F33: =F31*$B$8 -> 78.005363 | G33: =G31*$B$8 -> 96.611428 | H33: =H31*$B$8 -> 115.45727 | I33: =I31*$B$8 -> 134.80999 | ... M33: =M31*$B$8 -> 222.38204
A34: Free | Ending accounts | B34: =B31+B32-B33 -> 138 | C34: =C31+C32-C33 -> 269.1 | D34: =D31+D32-D33 -> 395.715 | E34: =E31+E32-E33 -> 520.03575 | F34: =F31+F32-F33 -> 644.07619 | G34: =G31+G32-G33 -> 769.71514 | H34: =H31+H32-H33 -> 898.73329 | I34: =I31+I32-I33 -> 1032.8463 | ... M34: =M31+M32-M33 -> 1653.895
A35: Free | Average accounts | B35: =(B31+B34)/2 -> 69 | C35: =(C31+C34)/2 -> 203.55 | D35: =(D31+D34)/2 -> 332.4075 | E35: =(E31+E34)/2 -> 457.87538 | F35: =(F31+F34)/2 -> 582.05597 | G35: =(G31+G34)/2 -> 706.89566 | H35: =(H31+H34)/2 -> 834.22421 | I35: =(I31+I34)/2 -> 965.78977 | ... M35: =(M31+M34)/2 -> 1568.221
A36: Free | Revenue | B36: =B35*$B$17 -> 0 | C36: =C35*$B$17 -> 0 | D36: =D35*$B$17 -> 0 | E36: =E35*$B$17 -> 0 | F36: =F35*$B$17 -> 0 | G36: =G35*$B$17 -> 0 | H36: =H35*$B$17 -> 0 | I36: =I35*$B$17 -> 0 | ... M36: =M35*$B$17 -> 0
A37: Free | Monitoring checks | B37: =(B35*$D$17)*DAY(EOMONTH(B$25,0))*1440/$E$17*$B$12 -> 205344 | C37: =(C35*$D$17)*DAY(EOMONTH(C$25,0))*1440/$E$17*$B$12 -> 586224 | D37: =(D35*$D$17)*DAY(EOMONTH(D$25,0))*1440/$E$17*$B$12 -> 989244.72 | E37: =(E35*$D$17)*DAY(EOMONTH(E$25,0))*1440/$E$17*$B$12 -> 1362637.1 | F37: =(F35*$D$17)*DAY(EOMONTH(F$25,0))*1440/$E$17*$B$12 -> 1564566.4 | G37: =(G35*$D$17)*DAY(EOMONTH(G$25,0))*1440/$E$17*$B$12 -> 2103721.5 | H37: =(H35*$D$17)*DAY(EOMONTH(H$25,0))*1440/$E$17*$B$12 -> 2402565.7 | I37: =(I35*$D$17)*DAY(EOMONTH(I$25,0))*1440/$E$17*$B$12 -> 2874190.4 | ... M37: =(M35*$D$17)*DAY(EOMONTH(M$25,0))*1440/$E$17*$B$12 -> 4516476.4
A38: Free | AI diagnoses | B38: =(B35*$D$17)*Inputs!$B$8*$B$13*Inputs!$B$9*$F$17 -> 0 | C38: =(C35*$D$17)*Inputs!$B$8*$B$13*Inputs!$B$9*$F$17 -> 0 | D38: =(D35*$D$17)*Inputs!$B$8*$B$13*Inputs!$B$9*$F$17 -> 0 | E38: =(E35*$D$17)*Inputs!$B$8*$B$13*Inputs!$B$9*$F$17 -> 0 | F38: =(F35*$D$17)*Inputs!$B$8*$B$13*Inputs!$B$9*$F$17 -> 0 | G38: =(G35*$D$17)*Inputs!$B$8*$B$13*Inputs!$B$9*$F$17 -> 0 | H38: =(H35*$D$17)*Inputs!$B$8*$B$13*Inputs!$B$9*$F$17 -> 0 | I38: =(I35*$D$17)*Inputs!$B$8*$B$13*Inputs!$B$9*$F$17 -> 0 | ... M38: =(M35*$D$17)*Inputs!$B$8*$B$13*Inputs!$B$9*$F$17 -> 0
A39: Free | Variable service expense | B39: =B37/1000*(Inputs!$B$19+Inputs!$B$20+Inputs!$B$21+Inputs!$B$22+Inputs!$B$23+Inputs!$B$24)+B38*((((Inputs!$B$10*Inputs!$B$15+Inputs!$B$11*Inputs!$B$16)*(1-Inputs!$B$14)+(Inputs!$B$10*Inputs!$B$17+Inputs!$B$11*Inputs!$B$18)*Inputs!$B$14)/1000000*Inputs!$B$12)*$B$11+Inputs!$B$12*Inputs!$B$13)+(B35*$D$17)*Inputs!$B$25*Inputs!$B$26+((B35*$D$17)*Inputs!$B$8*$B$13)*Inputs!$B$27*Inputs!$B$28+B36*(Inputs!$B$29+Inputs!$B$31) -> 35.10168 | C39: =C37/1000*(Inputs!$B$19+Inputs!$B$20+Inputs!$B$21+Inputs!$B$22+Inputs!$B$23+Inputs!$B$24)+C38*((((Inputs!$B$10*Inputs!$B$15+Inputs!$B$11*Inputs!$B$16)*(1-Inputs!$B$14)+(Inputs!$B$10*Inputs!$B$17+Inputs!$B$11*Inputs!$B$18)*Inputs!$B$14)/1000000*Inputs!$B$12)*$B$11+Inputs!$B$12*Inputs!$B$13)+(C35*$D$17)*Inputs!$B$25*Inputs!$B$26+((C35*$D$17)*Inputs!$B$8*$B$13)*Inputs!$B$27*Inputs!$B$28+C36*(Inputs!$B$29+Inputs!$B$31) -> 100.22802 | D39: =D37/1000*(Inputs!$B$19+Inputs!$B$20+Inputs!$B$21+Inputs!$B$22+Inputs!$B$23+Inputs!$B$24)+D38*((((Inputs!$B$10*Inputs!$B$15+Inputs!$B$11*Inputs!$B$16)*(1-Inputs!$B$14)+(Inputs!$B$10*Inputs!$B$17+Inputs!$B$11*Inputs!$B$18)*Inputs!$B$14)/1000000*Inputs!$B$12)*$B$11+Inputs!$B$12*Inputs!$B$13)+(D35*$D$17)*Inputs!$B$25*Inputs!$B$26+((D35*$D$17)*Inputs!$B$8*$B$13)*Inputs!$B$27*Inputs!$B$28+D36*(Inputs!$B$29+Inputs!$B$31) -> 169.10234 | E39: =E37/1000*(Inputs!$B$19+Inputs!$B$20+Inputs!$B$21+Inputs!$B$22+Inputs!$B$23+Inputs!$B$24)+E38*((((Inputs!$B$10*Inputs!$B$15+Inputs!$B$11*Inputs!$B$16)*(1-Inputs!$B$14)+(Inputs!$B$10*Inputs!$B$17+Inputs!$B$11*Inputs!$B$18)*Inputs!$B$14)/1000000*Inputs!$B$12)*$B$11+Inputs!$B$12*Inputs!$B$13)+(E35*$D$17)*Inputs!$B$25*Inputs!$B$26+((E35*$D$17)*Inputs!$B$8*$B$13)*Inputs!$B$27*Inputs!$B$28+E36*(Inputs!$B$29+Inputs!$B$31) -> 232.93036 | F39: =F37/1000*(Inputs!$B$19+Inputs!$B$20+Inputs!$B$21+Inputs!$B$22+Inputs!$B$23+Inputs!$B$24)+F38*((((Inputs!$B$10*Inputs!$B$15+Inputs!$B$11*Inputs!$B$16)*(1-Inputs!$B$14)+(Inputs!$B$10*Inputs!$B$17+Inputs!$B$11*Inputs!$B$18)*Inputs!$B$14)/1000000*Inputs!$B$12)*$B$11+Inputs!$B$12*Inputs!$B$13)+(F35*$D$17)*Inputs!$B$25*Inputs!$B$26+((F35*$D$17)*Inputs!$B$8*$B$13)*Inputs!$B$27*Inputs!$B$28+F36*(Inputs!$B$29+Inputs!$B$31) -> 267.60605 | G39: =G37/1000*(Inputs!$B$19+Inputs!$B$20+Inputs!$B$21+Inputs!$B$22+Inputs!$B$23+Inputs!$B$24)+G38*((((Inputs!$B$10*Inputs!$B$15+Inputs!$B$11*Inputs!$B$16)*(1-Inputs!$B$14)+(Inputs!$B$10*Inputs!$B$17+Inputs!$B$11*Inputs!$B$18)*Inputs!$B$14)/1000000*Inputs!$B$12)*$B$11+Inputs!$B$12*Inputs!$B$13)+(G35*$D$17)*Inputs!$B$25*Inputs!$B$26+((G35*$D$17)*Inputs!$B$8*$B$13)*Inputs!$B$27*Inputs!$B$28+G36*(Inputs!$B$29+Inputs!$B$31) -> 359.61196 | H39: =H37/1000*(Inputs!$B$19+Inputs!$B$20+Inputs!$B$21+Inputs!$B$22+Inputs!$B$23+Inputs!$B$24)+H38*((((Inputs!$B$10*Inputs!$B$15+Inputs!$B$11*Inputs!$B$16)*(1-Inputs!$B$14)+(Inputs!$B$10*Inputs!$B$17+Inputs!$B$11*Inputs!$B$18)*Inputs!$B$14)/1000000*Inputs!$B$12)*$B$11+Inputs!$B$12*Inputs!$B$13)+(H35*$D$17)*Inputs!$B$25*Inputs!$B$26+((H35*$D$17)*Inputs!$B$8*$B$13)*Inputs!$B$27*Inputs!$B$28+H36*(Inputs!$B$29+Inputs!$B$31) -> 410.772 | I39: =I37/1000*(Inputs!$B$19+Inputs!$B$20+Inputs!$B$21+Inputs!$B$22+Inputs!$B$23+Inputs!$B$24)+I38*((((Inputs!$B$10*Inputs!$B$15+Inputs!$B$11*Inputs!$B$16)*(1-Inputs!$B$14)+(Inputs!$B$10*Inputs!$B$17+Inputs!$B$11*Inputs!$B$18)*Inputs!$B$14)/1000000*Inputs!$B$12)*$B$11+Inputs!$B$12*Inputs!$B$13)+(I35*$D$17)*Inputs!$B$25*Inputs!$B$26+((I35*$D$17)*Inputs!$B$8*$B$13)*Inputs!$B$27*Inputs!$B$28+I36*(Inputs!$B$29+Inputs!$B$31) -> 491.31657 | ... M39: =M37/1000*(Inputs!$B$19+Inputs!$B$20+Inputs!$B$21+Inputs!$B$22+Inputs!$B$23+Inputs!$B$24)+M38*((((Inputs!$B$10*Inputs!$B$15+Inputs!$B$11*Inputs!$B$16)*(1-Inputs!$B$14)+(Inputs!$B$10*Inputs!$B$17+Inputs!$B$11*Inputs!$B$18)*Inputs!$B$14)/1000000*Inputs!$B$12)*$B$11+Inputs!$B$12*Inputs!$B$13)+(M35*$D$17)*Inputs!$B$25*Inputs!$B$26+((M35*$D$17)*Inputs!$B$8*$B$13)*Inputs!$B$27*Inputs!$B$28+M36*(Inputs!$B$29+Inputs!$B$31) -> 772.19201
A41: Starter | Opening accounts | B41: =0 -> 0 | C41: =B44 -> 7.2 | D41: =C44 -> 14.832 | E41: =D44 -> 22.95072 | F41: =E44 -> 31.615891 | G41: =F44 -> 40.892776 | H41: =G44 -> 50.852737 | I41: =H44 -> 61.573866 | J41: =I44 -> 73.141675 | ... M41: =L44 -> 113.90798
A42: Starter | New accounts | B42: =B27*$C$18 -> 7.2 | C42: =C27*$C$18 -> 7.92 | D42: =D27*$C$18 -> 8.712 | E42: =E27*$C$18 -> 9.5832 | F42: =F27*$C$18 -> 10.54152 | G42: =G27*$C$18 -> 11.595672 | H42: =H27*$C$18 -> 12.755239 | I42: =I27*$C$18 -> 14.030763 | ... M42: =M27*$C$18 -> 20.54244
A43: Starter | Churned accounts | B43: =B41*$B$7 -> 0 | C43: =C41*$B$7 -> 0.288 | D43: =D41*$B$7 -> 0.59328 | E43: =E41*$B$7 -> 0.9180288 | F43: =F41*$B$7 -> 1.2646356 | G43: =G41*$B$7 -> 1.635711 | H43: =H41*$B$7 -> 2.0341095 | I43: =I41*$B$7 -> 2.4629547 | ... M43: =M41*$B$7 -> 4.5563192
A44: Starter | Ending accounts | B44: =B41+B42-B43 -> 7.2 | C44: =C41+C42-C43 -> 14.832 | D44: =D41+D42-D43 -> 22.95072 | E44: =E41+E42-E43 -> 31.615891 | F44: =F41+F42-F43 -> 40.892776 | G44: =G41+G42-G43 -> 50.852737 | H44: =H41+H42-H43 -> 61.573866 | I44: =I41+I42-I43 -> 73.141675 | ... M44: =M41+M42-M43 -> 129.8941
A45: Starter | Average accounts | B45: =(B41+B44)/2 -> 3.6 | C45: =(C41+C44)/2 -> 11.016 | D45: =(D41+D44)/2 -> 18.89136 | E45: =(E41+E44)/2 -> 27.283306 | F45: =(F41+F44)/2 -> 36.254333 | G45: =(G41+G44)/2 -> 45.872756 | H45: =(H41+H44)/2 -> 56.213301 | I45: =(I41+I44)/2 -> 67.357771 | ... M45: =(M41+M44)/2 -> 121.90104
A46: Starter | Revenue | B46: =B45*$B$18 -> 32.4 | C46: =C45*$B$18 -> 99.144 | D46: =D45*$B$18 -> 170.02224 | E46: =E45*$B$18 -> 245.54975 | F46: =F45*$B$18 -> 326.289 | G46: =G45*$B$18 -> 412.8548 | H46: =H45*$B$18 -> 505.91971 | I46: =I45*$B$18 -> 606.21993 | ... M46: =M45*$B$18 -> 1097.1094
A47: Starter | Monitoring checks | B47: =(B45*$D$18)*DAY(EOMONTH(B$25,0))*1440/$E$18*$B$12 -> 96422.4 | C47: =(C45*$D$18)*DAY(EOMONTH(C$25,0))*1440/$E$18*$B$12 -> 285534.72 | D47: =(D45*$D$18)*DAY(EOMONTH(D$25,0))*1440/$E$18*$B$12 -> 505986.19 | E47: =(E45*$D$18)*DAY(EOMONTH(E$25,0))*1440/$E$18*$B$12 -> 730756.06 | F47: =(F45*$D$18)*DAY(EOMONTH(F$25,0))*1440/$E$18*$B$12 -> 877064.83 | G47: =(G45*$D$18)*DAY(EOMONTH(G$25,0))*1440/$E$18*$B$12 -> 1228655.9 | H47: =(H45*$D$18)*DAY(EOMONTH(H$25,0))*1440/$E$18*$B$12 -> 1457048.8 | I47: =(I45*$D$18)*DAY(EOMONTH(I$25,0))*1440/$E$18*$B$12 -> 1804110.5 | ... M47: =(M45*$D$18)*DAY(EOMONTH(M$25,0))*1440/$E$18*$B$12 -> 3159675
A48: Starter | AI diagnoses | B48: =(B45*$D$18)*Inputs!$B$8*$B$13*Inputs!$B$9*$F$18 -> 2.592 | C48: =(C45*$D$18)*Inputs!$B$8*$B$13*Inputs!$B$9*$F$18 -> 7.93152 | D48: =(D45*$D$18)*Inputs!$B$8*$B$13*Inputs!$B$9*$F$18 -> 13.601779 | E48: =(E45*$D$18)*Inputs!$B$8*$B$13*Inputs!$B$9*$F$18 -> 19.64398 | F48: =(F45*$D$18)*Inputs!$B$8*$B$13*Inputs!$B$9*$F$18 -> 26.10312 | G48: =(G45*$D$18)*Inputs!$B$8*$B$13*Inputs!$B$9*$F$18 -> 33.028384 | H48: =(H45*$D$18)*Inputs!$B$8*$B$13*Inputs!$B$9*$F$18 -> 40.473577 | I48: =(I45*$D$18)*Inputs!$B$8*$B$13*Inputs!$B$9*$F$18 -> 48.497595 | ... M48: =(M45*$D$18)*Inputs!$B$8*$B$13*Inputs!$B$9*$F$18 -> 87.768749
